Workbook
Name AMO_TM: 'Project Basics & Benchmarks'!$C$12
Name AnnualCapEx_Benchmark: CapEx!$O$42
Name AnnualCapEx_Benchmark_withMaintenance: CapEx!$O$44
Name AnnualCapEx_NewTech: CapEx!$G$42
Name AnnualCapEx_NewTech_withMaintenance: CapEx!$G$44
Name AnnualConstructionCapEx_Benchmark: CapEx!$O$36
Name AnnualConstructionCapEx_NewTech: CapEx!$G$36
Name AnnualEnergyCost_Benchmark: OpEx!$M$88
Name AnnualEnergyCost_NewTech: OpEx!$F$88
Name AnnualLaborCost_Benchmark: OpEx!$M$86
Name AnnualLaborCost_NewTech: OpEx!$F$86
Name AnnualMatCost_Benchmark: OpEx!$M$87
Name AnnualMatCost_NewTech: OpEx!$F$87
Name AnnualNonProcessCapEx_Benchmark: CapEx!$O$31
Name AnnualNonProcessCapEx_NewTech: CapEx!$G$31
Name AnnualOpEx_Benchmark: OpEx!$M$90
Name AnnualOpEx_NewTech: OpEx!$F$90
Name AnnualOtherCapEx_Benchmark: CapEx!$O$41
Name AnnualOtherCapEx_NewTech: CapEx!$G$41
Name AnnualOtherRecurring_Benchmark: OpEx!$M$89
Name AnnualOtherRecurring_NewTech: OpEx!$F$89
Name AnnualOverheadCost_Benchmark: OpEx!#REF!
Name AnnualOverheadCost_NewTech: OpEx!#REF!
Name AnnualProcessCapEx_Benchmark: CapEx!$O$26
Name AnnualProcessCapEx_NewTech: CapEx!$G$26
Name AnnualUsePhaseEmissions_Current: 'Use Phase Energy'!$J$34
Name AnnualUsePhaseEmissions_Hypothetical: 'Use Phase Energy'!$O$34
Name AnnualUsePhaseEnergy_Current: 'Use Phase Energy'!$H$34
Name AnnualUsePhaseEnergy_Hypoth: 'Use Phase Energy'!$M$34
Name BasicsBenchmarks: 'Project Basics & Benchmarks'!$B$5
Name Benchmark_Apps: 'Project Basics & Benchmarks'!$E$30
Name Benchmark_Status: 'Project Basics & Benchmarks'!$F$30
Name CH4_GWP: 'GWP Ref Tables'!$E$9
Name Challenges_Additive_Manufacturing: 'Dropdown Menu Options'!$D$54:$M$54
Name Challenges_Advanced_Materials: 'Dropdown Menu Options'!$D$55:$M$55
Name Challenges_Advanced_Sensors: 'Dropdown Menu Options'!$D$56:$M$56
Name Challenges_CHP: 'Dropdown Menu Options'!$D$57:$M$57
Name Challenges_Clean_Water: 'Dropdown Menu Options'!$D$68:$M$68
Name Challenges_Composite_Materials: 'Dropdown Menu Options'!$D$58:$M$58
Name Challenges_Critical_Materials: 'Dropdown Menu Options'!$D$59:$M$59
Name Challenges_Cybersecurity: 'Dropdown Menu Options'!$D$69:$M$69
Name Challenges_Energy_Efficient_Computing: 'Dropdown Menu Options'!$D$70:$M$70
Name Challenges_Materials_Harsh: 'Dropdown Menu Options'!$D$61:$M$61
Name Challenges_Motor_Driven_Systems: 'Dropdown Menu Options'!$D$71:$M$71
Name Challenges_Other: 'Dropdown Menu Options'!$D$72:$M$72
Name Challenges_Process_Heating: 'Dropdown Menu Options'!$D$62:$M$62
Name Challenges_Process_Intensification: 'Dropdown Menu Options'!$D$63:$M$63
Name Challenges_Roll_to_Roll_Processing: 'Dropdown Menu Options'!$D$64:$M$64
Name Challenges_Sustainable_Manufacturing: 'Dropdown Menu Options'!$D$65:$M$65
Name Challenges_Thermal_Conversion_Materials: 'Dropdown Menu Options'!$D$60:$M$60
Name Challenges_Waste_Heat_Recovery: 'Dropdown Menu Options'!$D$66:$M$66
Name Challenges_Wide_Bandgap_Semiconductors: 'Dropdown Menu Options'!$D$67:$M$67
Name Commercial_Benchmark: 'Project Basics & Benchmarks'!$D$30
Name CurrentMarketShare_Benchmark: Market!$E$21
Name CurrentMarketShare_NewTech: Market!$E$20
Name CurrentMarketShare_OtherTech: Market!$E$22
Name DataPlanning: #REF!
Name e: '[1]Project Basics & Benchmarks'!$D$41
Name EIA: 'EIA Ref Tables'!$B$3
Name EndUse_Product: 'Project Basics & Benchmarks'!$C$24

Sheet TECHTEST Landing Page
C1: U.S. DEPARTMENT OF ENERGY (DOE) OFFICE OF ENERGY EFFICIENCY AND RENEWABLE ENERGY (EERE)
C2: Techno-economic, Energy & Carbon Heuristic Tool for Early Stage Technologies (TECHTEST)
C3: Version 1.0
C4: Release: February 19, 2023
C6: What can I expect from TECHTEST?
C7: • TECHTEST is a tool that collects specific categorical cost, energy, and emissions data about a new technology and the associated benchmark technology for comparison. • TECHTEST will develop a series of charts and tables that will project the economic and sustainable viability of the product compared to its comparable current market technology. There are two ways to fill out TECHTEST:
C12: • Full Analytical Approach: Review each section of the lifecycle separately, enter more granular data. (Recommended for first time users)
C13: • Rapid Data Entry Approach: Abbreviated approach, little to no explanation of steps. (Recommended for multiple scenario testing)
C15: TECHTEST Data
C16: •TECHTEST utilizes CO2-e and costs associated with materials and energy sources to fill out the back end of the calculation. The cost vectors and corresponding sources can be found in the link below:
C17: Link to energy/cost data tables.
C18: Link to global warming potential data tables
... C31: Other Cells: Not intended for editing

Sheet Full Entry Home Page
B2: Method 1. Full Analytical Approach
C4: This method generates results from scratch, starting with source data. This is the recommended method for most users who are starting from scratch. If you are beginning with a complete cost, energy, and emissions analysis in another format and simply need to "port" data into the IPA template, you can consider the Rapid Data Entry Approach. To estimate the potential cost & environmental impacts of a new technology, complete all green input tabs. You will input data for both the new technology (being developed in this project) and for the commercial benchmark technology (that you will be comparing to). Follow the instructions provided to enter data in cells that are shaded blue (text or numeric entry) or gold (dropdown menu selection). Be as complete and specific as possible in your data entries. Document assumptions, references, calculations, and estimation methods used. It works best to complete tabs in order from left to right - but it is OK to fill them out of order, if needed. If filling tabs out-of-order, follow instructions carefully to enter certain data points in earlier tabs as needed, rather than over-writing formulae in the sheet. This will avoid problems with duplicate data entries, cell reference errors, and named variables. Data should be entered ONLY in the blue and gold cells.
C5: Data input tabs for the Full Analytical Approach are linked below:
B7: 1 | C7: Project Basics & Benchmarks (Tier 1)
B8: 2 | C8: Market (Tier 2)
B9: 3 | C9: Functional Unit (Tier 2)
B10: 4 | C10: Raw Materials (Including: Embodied Energy, Emissions, and Costs (Tier 2))
B11: 5 | C11: Manufacturing Energy (Manufacturing Phase Energy & Emissions (Tier 2))
B12: 6 | C12: Use Phase Energy (Energy andEmissions (Tier 2))
B13: 7 | C13: Grid Mix
B14: 8 | C14: CapEx (Tier 2)
B15: 9 | C15: OpEx (Tier 2)
C16: As data fields in the input tabs are filled, summary result tables and plots will automatically start to appear in the two results output tabs (shaded navy blue). In these tabs, the new technology will be compared head-to-head with the commercial benchmark technology on an energy and cost basis. After completing all of the Input tabs, you can scroll through the Summary Results Output tabs to view results summaries in tabular and graphical "dashboard" formats. Notes that the accuracy of the generated tables and plots depends on the completeness of data in the Input tabs. After reviewing, you may wish to go back to the input tabs to add further detail and improve the quality of the results.
C17: The results summary output tabs for the Full Analytical Approach are linked below:
B18: 1 | C18: Results Summary Tables
B19: 2 | C19: Graphical Results Dashboard

Sheet Rapid Data Entry Home Page
B2: Method 2. Rapid Data Entry Approach
C4: The Rapid Data Entry Approach, which requires high-level data entries only, is intended for users who have already completed an analysis in another format, but wish to quickly "port" results into TECHTEST to generate results tables and dashboards in the IPA format.
C5: It is also possible to mix-and-match the two approaches by partially completing the Rapid Data Entry sheet using available data, then making more detailed calculations in appropriate tabs of the Full Analytical Approach to estimate missing data. Results from Full Analytical tabs can be copied and pasted (as values) into appropriate cells of the Rapid Data Entry Approach to populate a complete dataset.
C6: To estimate the potential cost & environmental impacts of a new technology, first complete the two light-green Tier 1 data input tabs, also used in Method 1 (Project Basics and Benchmarks, and Performance Metrics). Then, skip ahead to the orange "Rapid Data Input" tab for Method 2. In this sheet, you will input high-level cost, energy, and emissions data for both the new technology (being developed in this project) and for the commercial benchmark technology (that you will be comparing to). Follow the instructions provided to enter data in cells that are shaded blue. Be as complete and specific as possible in your data entries. Document assumptions, references, calculations, and estimation methods used.
C7: Data input tabs for the Rapid Data Entry Method are linked below:
B9: 1 | C9: Project Basics and Benchmarks (Tier 1)
B10: 2 | C10: Rapid Data Input Sheet for Method 2 (Tier 2)
C12: As data fields in the input tabs are filled, summary result tables and plots will automatically start to appear in the Method 2 results output tabs (shaded deep red). In these tabs, the new technology will be compared head-to-head with the commercial benchmark technology on an energy and cost basis - in the same format as Method 1. Notes that the accuracy of the generated tables and plots depends on the completeness of data in the Input tabs. After reviewing, you may wish to go back to the input tabs to add further detail and improve the quality of the results.
C13: The results summary output tabs for the Rapid Data Entry Approach are linked below:
B14: 1 | C14: Results Summary Tables (Method 2)
B15: 2 | C15: Graphical Results Dashboard (Method 2)

Sheet Project Basics & Benchmarks
B1: U.S. DEPARTMENT OF ENERGY (DOE) OFFICE OF ENERGY EFFICIENCY AND RENEWABLE ENERGY (EERE)
B2: Techno-economic, Energy & Carbon Heuristic Tool for Early Stage Technologies (TECHTEST)
C4: Return to Full Entry Home Page | D4: Return to Rapid Data Entry Home Page
B5: Project & Technology Description
B7: Project Title | C7: Waste Heat Recovery Cooling in Beverage Manufacturing
B8: Lead Organization | C8: Hypothetical Organization
B9: Collaborative Partner(s) | C9: Staff
B10: Principal Investigator Name | C10: John Doe
B11: Principal Investigator Organization | C11: Hypotentical National Laboratory
B12: AMO Technology Manager | C12: Jane Doe
B13: Project Start | C13: 44927
B14: Project End | C14: 45658
B15: Funding Mechanism | C15: R&D Project
B16: =IF(C15="Consortium","Consortium Name:",IF(C15="FOA (Funding Opportunity Announcement)","FOA Title:",""))
B17: =IF(C15="FOA (Funding Opportunity Announcement)","FOA Topic Area (if multiple):","")
B18: =IF(C15="FOA (Funding Opportunity Announcement)","FOA Subtopic (if any):","")
B19: Technology Diagram (insert in cells to right) | C19: TBD
B20: Technology Benchmarking
B22: Define the generic market-end use product. If the new technology, commercial benchmark, other competing technologies produce different products that serve the same function and would be used in the same market, the generic market end-use product should be defined generally enough to encompass these different products or variations. For example, a Market End Use Product could be "automotive high strength steel" rather than the more specific "HSLA 350 steel produced by XYZ process." Defining a product and market that is too-specific may overly restrict the impact analysis.
B24: Generic Market End-Use Product*: | C24: Cooled Waste Water
C25: * The "generic" market end-use product should be defined generally enough to encompass the end-use products of all competing technologies (new technology, commercial benchmark, other competing technologies), if the end products are different but would be used to serve the same function. Specific differences in the end products or applications can be specified in the table below.
B27: Definitions of Competing Technologies and Products | D27: Technology Definition | E27: Specific Product or Application | F27: Technology Status
D28: Define the technology. | E28: Identify the end-use products and/or key applications for this technology, noting any differences. | F28: Is this technology a current typical technology, a state-of-the-art technology, or an emerging technology?
C29: New Technology (developed in this project) | D29: Waste Heat Recovery (Heat Pump) | E29: Cooled Waste Water | F29: Typical Technology
C30: Commercial Benchmark Technology | D30: Evaporative Condenser | E30: Cooled Waste Water | F30: Typical Technology
C31: Other Competing Technologies (list relevant technologies, separating by commas)
B33: Energy, Emissions & Cost Impact Drivers | D33: Note: This section examines emissions over the entire lifecycle.
B35: Energy & Emissions Impacts by Life Cycle Phase | C35: In your opinion, would this technology be likely to impact the energy and/or emissions associated with … | D35: Yes/No | E35: Mechanism (Explain why this technology would be likely to have an impact.)
C36: … raw materials used in the manufacturing process? | D36: No
C37: … manufacturing the end-use product? | D37: Yes | E37: Higher energy efficiency, no cooling water needed
C38: … using, transporting, or disposing of the end-use product? | D38: No
B40: Manufacturing Cost Impacts by Cost Component | C40: In your opinion, would this technology be likely to impact the manufacturing costs associated with … | D40: Yes/No | E40: Mechanism
C41: … capital equipment? | D41: No
C42: … raw materials used in manufacturing? | D42: No
C43: … energy used in manufacturing? | D43: No
C44: … manufacturing labor? | D44: No
B46: Impacts by Sector | C46: In your opinion, would this technology be likely to impact the following sectors (energy, emissions, or cost)? | D46: Yes/No | E46: Mechanism
B47: For each sector that would be impacted by the new technology, briefly describe the mechanisms of potential impacts. (Assume successful commercialization and adoption.) | C47: Mining | D47: No
C48: Manufacturing | D48: Yes | E48: Used to save energy in beverage manufacturing
C49: Transportation | D49: No
C50: Energy Generation (utility scale) | D50: No
C51: Energy Generation (device scale) | D51: No
C52: Construction | D52: No
C53: Electronics | D53: No
C54: Consumer Goods | D54: No
C55: Other Sector (please specify) | D55: No
B57: Patents & Publications
B59: List key patents and publications (by awardee) related to or resulting from this project. Add as many rows as needed.
B65: References, Notes, and Assumptions
B67: List key references and assumptions used to prepare the data provided in this sheet. Add as many rows as needed.
B73: Return to Home Page

Sheet Functional Unit
B1: U.S. DEPARTMENT OF ENERGY (DOE) OFFICE OF ENERGY EFFICIENCY AND RENEWABLE ENERGY (EERE)
B2: Techno-economic, Energy & Carbon Heuristic Tool for Early Stage Technologies (TECHTEST)
B3: Functional Units and Reference Quantities
C4: Return to Planning Page
B5: An explanation of best practices for choosing a functional unit can be found in DOE's "Functional Units" short tutorial video:
B6: https://www.youtube.com/watch?v=6_5j8kTomOo&ab_channel=U.S.DepartmentofEnergy
B8: A Functional Unit defines the quantity of a product or product system based on the performance it delivers in its end-use application. The purpose of defining a performance-based functional unit is to facilitate accurate comparisons (of environmental or cost metrics) for disparate products or systems that serve the same final function. The functional unit can be used to objectively compare the new technology to the commercial benchmark technology. The process can be broken down into two steps:
B11: Describing the final function for the technology and defining the functional unit.
G12: Examples
B13: – If the technology is a production method, you can define the functional unit based on a quantity of product that the process creates. For Example: A steel smelting process could be defined based on its ability to produce 1 kg of automotive steel. – If the technology is a product, you can define the functional unit based on a quantitative measure of the intended function of the product. For Example: A light souce could be defined based on its ability to produce 1,000 lumens of brightness for 1,000 hours. | G13: The total volume of catalyst required to produce 1 ton of ethylene.
G14: The mass of steel required to produce an automotive B-pillar for an average mid-size sedan.
G15: All light bulbs required to produce 1,000 lumens of brightness over 100,000 hours.
G16: All shipping pallets required to deliver 100,000 lbs of product load at a dynamic load rating of 5,000 lbs.
B17: Step 1: Based on the functional unit, specify a reference quantity for the New Technology that can be compared to an equivalent reference quantity for the Commercial Benchmark Technology.
B18: Use the functional unit to specify a production reference quantity for the new technology, as shown in the examples below.
C20: Functional Unit Based Reference Quantity for the New Technology: | D20: 2 | E20: Million Gallons | F20: of | G20: Cooled Waste Water | H20: for New Technology
D21: Value | E21: Unit | G21: of Product
D22: Examples: | E22: 80 kg of new ethylene catalyst
E23: 1,000,000 lumen-hours produced by a new LED bulb
E24: 9 kg of dual-phase high strength steel
E25: 18 recycled polymer pallet shipping pallets in novel design
B27: Finally, specific the performance-equivalent production reference quantity for the commercial benchmark technology, as shown in the examples below. Note that this value may be the same or different from the reference quantity for the new technology. It depends on how you've defined your functional unit, and whether the new technology will serve as a drop-in replacement for the benchmark technology.
C29: Performance Equivalent Reference Quantity for the Commercial Benchmark: | D29: 2 | E29: =E20 -> Million Gallons | F29: of | G29: =IF(G20="","",G20) -> Cooled Waste Water | H29: for Commercial Benchmark Technology
D30: Value | E30: Unit | G30: of Product
D31: Examples: | E31: 90 kg of conventional ethylene catalyst
E32: 1,000,000 lumen-hours produced by a current typical lightbulb
E33: 13 kg of conventional mild steel
E34: 24 conventional wood stringer pallets
C35: Explain Differentiation in Functional Units
C36: =IF(D20<>D29,"The default assumption is that there will not be a difference in performance equivalence, make sure the difference can be explained by writing out the logic in the blue box below.","Proceed to Step 2 for Functional Unit review.") -> Proceed to Step 2 for Functional Unit review.
B41: Step 2: Verify the Performance Equivalency Summary of the Functional Unit for the New Technology and the Commerical Benchmark.
C44: Functional Unit
C45: =IF(ISBLANK(H12),"",H12)
C47: New Technology | G47: Commercial Benchmark
B48: Technology Name | C48: =New_Technology -> Waste Heat Recovery (Heat Pump) | G48: =Commercial_Benchmark -> Evaporative Condenser
B49: Specific Product | C49: =G20 -> Cooled Waste Water | G49: =G29 -> Cooled Waste Water
B50: Functional Unit Based Reference Qty. | C50: =D20 -> 2 | D50: =E20 -> Million Gallons | G50: =D29 -> 2 | H50: =E29 -> Million Gallons
C51: New Technology Production Equivalent | D51: (units) | G51: Benchmark Production Equivalent | H51: (units)
B53: Throughout this analysis, all energy consumption and cost data will be reported in terms of the functional unit based reference quantities derived above.
B55: References, Notes, and Assumptions
B57: List key references and assumptions used to prepare the data provided in this sheet. Add as many rows as needed.
B63: Calculations
B64: Use this section for project-specific calculations and detailed references supporting the data above. Add as many rows as needed.
B74: Return to Home Page

Sheet Raw Materials
B1: U.S. DEPARTMENT OF ENERGY (DOE) OFFICE OF ENERGY EFFICIENCY AND RENEWABLE ENERGY (EERE)
B2: Techno-economic, Energy & Carbon Heuristic Tool for Early Stage Technologies (TECHTEST)
E3: Return to Planning Page
B4: Raw Material Embodied Energy, Emissions, and Costs
B6: In this tab, you will estimate the embodied energy, embodied carbon, and cost for raw material inputs to manufacturing, for the New Technology (left) and for the Commercial Benchmark (right). Note that the technology definitions and product definitions are imported by default from the Benchmarking section of the "Project Basics" tab; and reference volumes are imported from the "Ref Volume" tab. If any edits to these values are needed, please modify in those tabs to ensure changes are carried through entire analysis.
C7: New Technology (at Industrial Scale) | M7: Commercial Benchmark
B8: Technology Name | C8: =New_Technology -> Waste Heat Recovery (Heat Pump) | L8: Technology Name | M8: =Commercial_Benchmark -> Evaporative Condenser
B9: Specific Product | C9: =New_Technology_Apps -> Cooled Waste Water | L9: Specific Product | M9: =Benchmark_Apps -> Cooled Waste Water
B10: Reference Volume | C10: =Ref_Volume -> 2 | D10: =Ref_Volume_Unit -> Million Gallons | L10: Reference Volume | M10: =Ref_Volume_Benchmark -> 2 | N10: =Ref_Volume_Unit -> Million Gallons
C11: (reference volume) | D11: (units) | M11: (reference volume) | N11: (units)
B13: List all significant input materials in the table below. Considering the reference volume specified in the prior tab (and shown above), specify for each input material the amount required to produce the reference quanity, as well as the specific embodied energy, specific embodied carbon*, and specific cost for each material. Follow the same process for the new technology (left) and commercial benchmark technology (right) to facilitate comparisons.
B14: Embodied energy and carbon for input materials may conveniently be estimated using NREL's Materials Flow Through Industry (MFI) tool (using the exact materials if available, or using similar "proxy" materials as an estimate). Indicate the specific MFI material names used for estimates (or other sources and assumptions) in the "References, Notes, and Assumptions" section below. The tool tab linked below can be used to easily extract embodied energy and carbon values from MFI results output. MFI embodied energy and carbon results can then be pasted as values in the Specific Embodied Energy column.
B15: Calculator Tool: Extracting Embodied Energy & Carbon from MFI
B16: New Technology - Raw Material Inputs | E16: Enter MFI embodied energy data in this column ↓ | F16: Enter MFI embodied carbon data in this column ↓ | L16: Commercial Benchmark - Raw Material Inputs | O16: Enter MFI embodied energy data in this column (if applicable) ↓ | P16: Enter MFI embodied carbon data in this column ↓
B17: Material Inputs (list) | C17: Amount of Material (to produce reference volume) | D17: unit | E17: Specific Embodied Energy (Btu/unit) (for this material) | F17: Specific Embodied Carbon (lbs CO2-eq/unit) (for this material) | G17: Specific Cost ($/unit) (for this material) | H17: Embodied Energy (MMBtu) (per reference volume of product) | I17: Embodied Carbon (lbs CO2-eq) (per reference volume of product) | J17: Cost ($) (per reference volume of product) | L17: Material Inputs (list) | M17: Amount of Material (to produce reference volume) | N17: unit | O17: Specific Embodied Energy (Btu/unit) (for this material) | P17: Specific Embodied Carbon (CO2-eq/unit) (for this material) | Q17: Specific Cost ($/unit) (for this material) | R17: Embodied Energy (MMBtu) (per reference volume of product) | S17: Embodied Carbon (lbs CO2-eq) (per reference volume of product) | T17: Cost ($) (per reference volume of product)
B18: Lubrication | C18: 2.34 | D18: kg | E18: 80564.445 | F18: 4.71325 | G18: 6 | H18: =IF(B18<>"",C18*E18*0.000001,"") -> 0.1885208 | I18: =IF(B18<>"",C18*F18,"") -> 11.029005 | J18: =IF(B18<>"",C18*G18,"") -> 14.04 | L18: City water supply to evaporative condensers | M18: =B47 -> 17010.309 | N18: gallons | O18: =B89 -> 17.939392 | P18: =B94 -> 0.0025036189 | Q18: =B69/1000 -> 0.002 | R18: =IF(L18<>"",M18*O18*0.000001,"") -> 0.3051546 | S18: =IF(L18<>"",M18*P18,"") -> 42.587331 | T18: =IF(L18<>"",M18*Q18,"") -> 34.020619
B19: Copper | C19: =Q49 -> 0.36730356 | D19: kg | E19: =R49 -> 39808.319 | F19: =S49 -> 2.6 | H19: =IF(B19<>"",C19*E19*0.000001,"") -> 0.014621737 | I19: =IF(B19<>"",C19*F19,"") -> 0.95498926 | J19: =IF(B19<>"",C19*G19,"") -> 0 | L19: Biocide chemical additon to cooling loop for micro mitigation | M19: =C66 -> 3.322326 | N19: gallons | O19: =B84 -> 119.56102 | P19: =B104 -> 0.013231125 | Q19: =B74 -> 19.090909 | R19: =IF(L19<>"",M19*O19*0.000001,"") -> 0.0003972207 | S19: =IF(L19<>"",M19*P19,"") -> 0.043958111 | T19: =IF(L19<>"",M19*Q19,"") -> 63.426224
B20: Elastomer | C20: =Q50 -> 0.16056986 | D20: kg | E20: =R50 -> 94781.7 | F20: =S50 -> 5.545 | H20: =IF(B20<>"",C20*E20*0.000001,"") -> 0.015219085 | I20: =IF(B20<>"",C20*F20,"") -> 0.89035989 | J20: =IF(B20<>"",C20*G20,"") -> 0 | L20: Steel low Alloy | M20: =Q74 -> 0.31749784 | N20: kg | O20: =R74 -> 19051.1 | P20: 1.37 | R20: =IF(L20<>"",M20*O20*0.000001,"") -> 0.0060486831 | S20: =IF(L20<>"",M20*P20,"") -> 0.43497204 | T20: =IF(L20<>"",M20*Q20,"") -> 0
B21: HDPE | C21: =Q51 -> 0.0050178082 | D21: kg | E21: =R51 -> 69190.6 | F21: =S51 -> 1.57 | H21: =IF(B21<>"",C21*E21*0.000001,"") -> 0.00034718516 | I21: =IF(B21<>"",C21*F21,"") -> 0.0078779589 | J21: =IF(B21<>"",C21*G21,"") -> 0 | L21: Stainless Steel | M21: =Q75 -> 0.34946467 | N21: kg | O21: =R75 -> 53741.394 | P21: 6.15 | R21: =IF(L21<>"",M21*O21*0.000001,"") -> 0.018780718 | S21: =IF(L21<>"",M21*P21,"") -> 2.1492077 | T21: =IF(L21<>"",M21*Q21,"") -> 0
B22: Low alloyed steel | C22: =Q52 -> 0.32113973 | D22: kg | E22: =R52 -> 19051.124 | F22: =S52 -> 1.37 | H22: =IF(B22<>"",C22*E22*0.000001,"") -> 0.0061180728 | I22: =IF(B22<>"",C22*F22,"") -> 0.43996142 | J22: =IF(B22<>"",C22*G22,"") -> 0 | L22: Aluminium | M22: =Q76 -> 0.39875732 | N22: kg | O22: =R76 -> 146912.1 | P22: 9.16 | R22: =IF(L22<>"",M22*O22*0.000001,"") -> 0.058582275 | S22: =IF(L22<>"",M22*P22,"") -> 3.652617 | T22: =IF(L22<>"",M22*Q22,"") -> 0
B23: Lubricating Oil (Manufacturing) | C23: =Q53 -> 0.027096164 | D23: kg | E23: =R53 -> 80564.445 | F23: =S53 -> 4.71325 | H23: =IF(B23<>"",C23*E23*0.000001,"") -> 0.0021829874 | I23: =IF(B23<>"",C23*F23,"") -> 0.127711 | J23: =IF(B23<>"",C23*G23,"") -> 0 | L23: Bricks | M23: =Q77 -> 0.34626548 | N23: Bricks | O23: =R77 -> 2843.46 | P23: 0.24 | R23: =IF(L23<>"",M23*O23*0.000001,"") -> 0.00098459203 | S23: =IF(L23<>"",M23*P23,"") -> 0.083103714 | T23: =IF(L23<>"",M23*Q23,"") -> 0
B24: PVC | C24: =Q54 -> 0.016056986 | D24: kg | E24: =R54 -> 73171.48 | F24: =S54 -> 2.41 | H24: =IF(B24<>"",C24*E24*0.000001,"") -> 0.0011749135 | I24: =IF(B24<>"",C24*F24,"") -> 0.038697337 | J24: =IF(B24<>"",C24*G24,"") -> 0 | L24: Methacrylate | M24: =Q78 -> 0.28817819 | N24: kg | O24: =R78 -> 110079.81 | P24: 5.9 | R24: =IF(L24<>"",M24*O24*0.000001,"") -> 0.031722602 | S24: =IF(L24<>"",M24*P24,"") -> 1.7002513 | T24: =IF(L24<>"",M24*Q24,"") -> 0
B25: Reinforced Steel | C25: =Q55 -> 1.3046301 | D25: kg | E25: =R55 -> 19051.1 | F25: =S55 -> 1.37 | H25: =IF(B25<>"",C25*E25*0.000001,"") -> 0.024854639 | I25: =IF(B25<>"",C25*F25,"") -> 1.7873433 | J25: =IF(B25<>"",C25*G25,"") -> 0 | L25: Polyurethane | M25: =Q79 -> 0.025744085 | N25: kg | O25: =R79 -> 68337.822 | P25: 3.76 | R25: =IF(L25<>"",M25*O25*0.000001,"") -> 0.0017592947 | S25: =IF(L25<>"",M25*P25,"") -> 0.096797761 | T25: =IF(L25<>"",M25*Q25,"") -> 0
H26: =IF(B26<>"",C26*E26*0.000001,"") | I26: =IF(B26<>"",C26*F26,"") | J26: =IF(B26<>"",C26*G26,"") | L26: PVC | M26: =Q80 -> 0.49518472 | N26: kg | O26: =R80 -> 73171.704 | P26: 3.1 | R26: =IF(L26<>"",M26*O26*0.000001,"") -> 0.03623351 | S26: =IF(L26<>"",M26*P26,"") -> 1.5350726 | T26: =IF(L26<>"",M26*Q26,"") -> 0
H27: =IF(B27<>"",C27*E27*0.000001,"") | I27: =IF(B27<>"",C27*F27,"") | J27: =IF(B27<>"",C27*G27,"") | R27: =IF(L27<>"",M27*O27*0.000001,"") | S27: =IF(L27<>"",M27*P27,"") | T27: =IF(L27<>"",M27*Q27,"")
G28: Total embodied energy and cost for input materials: | H28: =SUM(H18:H27) -> 0.25303942 | I28: =SUM(I18:I27) -> 15.275945 | J28: =SUM(J18:J27) -> 14.04 | Q28: Total embodied energy and cost for input materials: | R28: =SUM(R18:R27) -> 0.4596635 | S28: =SUM(S18:S27) -> 52.283311 | T28: =SUM(T18:T27) -> 97.446843
B30: *The IPA team defines "embodied carbon" for a material as the 10-year Global Warming Potential (GWP) of greenhouse gas emissions associated with the material's extraction, processing, and manufacturing. IPCC 2013 (AR5) data are used for 10-year GWP emissions factors. Emissions are calculated automatically in MFI. If calculating independently, the latest IPCC data for GWP and combustion emissions factors are available in the Reference Data tab linked below:
B31: Reference Data: 10-Year GWP & Combustion Emission Factors
B33: References, Notes, and Assumptions
B35: List key references and assumptions used to prepare the data provided in this sheet. Add as many rows as needed. | C35: To determine Biocide dosing per unit of cooling water: https://www.unitedlabsinc.com/content/pdf/label/336label.pdf
C36: Biocide cost example: https://www.coolingtowerchemicals.com/Polymeric-Quaternary-Amine-p/4655.htm
C37: Embodied Energy of chlorine (common biocide): https://pubs.acs.org/doi/10.1021/es404300y#:~:text=The%20embodied%20energy%20is%20based,during%20the%20water%20treatment%20process.
C38: Embodied Energy and Carbon of water: https://www.ncbi.nlm.nih.gov/pmc/articles/PMC8933528/
C39: Embodied Carbon of chlorine (common biocide): https://legacy.winnipeg.ca/finance/findata/matmgt/documents/2012/682-2012/682-2012_Appendix_H-WSTP_South_End_Plant_Process_Selection_Report/Appendix%207.pdf
C40: Materials Embodied Energies: https://en.wikipedia.org/wiki/Embodied_energy
C41: Materials Embodied Energies II: https://greenbuildingencyclopaedia.uk/wp-content/uploads/2014/07/Full-BSRIA-ICE-guide.pdf
B44: Calculations
B45: 100000 | C45: gallons/day average water consumption at the brewery wastewater plant (based on institutional knowledge/experience) | M45: Material Cost Calculations Waste Heat Recovery System
B46: 0.5 | C46: assumed % of city water usage to evaporative condensers compared to total wastewater plant city water usage (based on institutional knowledge/experience)
B47: =M104 -> 17010.309 | C47: gallons/day of city water usage fed to evaporative condensers | M47: Material for a 5 kWh heat pump, converted to 366.3 kWh (Assuming Linear Scale Up)
M48: Material | N48: Unit | O48: Amount per Unit | P48: Scaled up to 366.3 kWh | Q48: Scaled to per Functional Unit | R48: Embodied btu/kg | S48: Embodied kg CO2/kg
B49: https://www.unitedlabsinc.com/content/pdf/label/336label.pdf | M49: Copper | N49: kg | O49: 36.6 | P49: =O49*366.3/5 -> 2681.316 | Q49: =P49/$P$67 -> 0.36730356 | R49: 39808.319 | S49: 2.6
M50: Elastomer | N50: kg | O50: 16 | P50: =O50*366.3/5 -> 1172.16 | Q50: =P50/$P$67 -> 0.16056986 | R50: 94781.7 | S50: =(3.61+7.48)/2 -> 5.545
M51: HDPE | N51: kg | O51: 0.5 | P51: =O51*366.3/5 -> 36.63 | Q51: =P51/$P$67 -> 0.0050178082 | R51: 69190.6 | S51: 1.57
M52: Low alloyed steel | N52: kg | O52: 32 | P52: =O52*366.3/5 -> 2344.32 | Q52: =P52/$P$67 -> 0.32113973 | R52: 19051.124 | S52: 1.37
M53: Lubricating Oil | N53: kg | O53: 2.7 | P53: =O53*366.3/5 -> 197.802 | Q53: =P53/$P$67 -> 0.027096164 | R53: =R50*0.85 -> 80564.445 | S53: =S50*0.85 -> 4.71325
M54: PVC | N54: kg | O54: 1.6 | P54: =O54*366.3/5 -> 117.216 | Q54: =P54/$P$67 -> 0.016056986 | R54: 73171.48 | S54: 2.41
M55: Reinforced Steel | N55: kg | O55: 130 | P55: =O55*366.3/5 -> 9523.8 | Q55: =P55/$P$67 -> 1.3046301 | R55: 19051.1 | S55: 1.37
M58: Convert MMbtu to MJ | P58: Conversion to daily output for heat pump
P59: 30 | Q59: Pump energy use: MMbtu / day
M60: 1 MJ = | N60: 0.00095 | O60: MMbtu | P60: 293.07107 | Q60: kWh in 1 MMbtu
M61: 1 MJ = | N61: 947.82 | O61: btu | P61: =P59*P60 -> 8792.1321 | Q61: kWh/day used by heat pump
B62: *assume system has microbrial control during normal operations. 13-38 ounces per 1000 gallons of cooling water. Assume 25 oz biocide required as this is in the middle of the range | P62: =P61/24 -> 366.33884 | Q62: kWh per hour (assuming ~24 hour use)
B63: 25 | C63: ounces biocide per | E63: 1000 | F63: gallons of water
B64: 128 | C64: ounces = | D64: 1 | E64: gallon
B65: =B63/B64 -> 0.1953125 | C65: gallons biocide per | E65: 1000 | F65: gallons of water | P65: Conversion from 20 Year Lifetime to Functional Unit
B66: Total Biocide/day Required: | C66: =B65*B47/E65 -> 3.322326 | D66: gallons | P66: 20 | Q66: Years
P67: =20*365 -> 7300 | Q67: Days
B68: Costs
B69: 2 | C69: per 1000 gallons of industrial city water cost estimation for St. Louis
M70: Material Cost Calculations Waste Heat Recovery System
B71: *various typies of biocides out there, but see source below for a 55 gallon drum.
B72: https://www.coolingtowerchemicals.com/Polymeric-Quaternary-Amine-p/4655.htm | O72: Material for a 4 kWh heat pump, converted to 366.3 kWh (Assuming Linear Scale Up)
B73: 55 | C73: gallon drum of biocide = | E73: 1050 | M73: Material | N73: Unit | O73: Amount per Unit | P73: Scaled up to 366.3 kWh | Q73: Scaled to per Functional Unit | R73: Embodied btu/kg | S73: Embodied kg CO2/kg
B74: =E73/B73 -> 19.090909 | C74: per gallon of biocide | M74: Steel low Alloy | N74: kg | O74: 25.307 | P74: =O74*$P$62/4 -> 2317.7342 | Q74: =P74/P$67 -> 0.31749784 | R74: 19051.1 | S74: 1.37
M75: Stainless Steel | N75: kg | O75: 27.855 | P75: =O75*$P$62/4 -> 2551.0921 | Q75: =P75/P$67 -> 0.34946467 | R75: =56.7*N61 -> 53741.394 | S75: 6.15
B76: Embodied Energy | M76: Aluminium | N76: kg | O76: 31.784 | P76: =O76*$P$62/4 -> 2910.9284 | Q76: =P76/P$67 -> 0.39875732 | R76: =155*N61 -> 146912.1 | S76: 9.16
B77: Chlorine Embodied Energy Source: | C77: https://pubs.acs.org/doi/10.1021/es404300y#:~:text=The%20embodied%20energy%20is%20based,during%20the%20water%20treatment%20process. | M77: Bricks | N77: kg | O77: 27.6 | P77: =O77*$P$62/4 -> 2527.738 | Q77: =P77/P$67 -> 0.34626548 | R77: =3*N61 -> 2843.46 | S77: 0.24
M78: Methacrylate | N78: kg | O78: 22.97 | P78: =O78*$P$62/4 -> 2103.7008 | Q78: =P78/P$67 -> 0.28817819 | R78: =N61*116.14 -> 110079.81 | S78: 5.9
B79: 22.7 | C79: MJ/KG of chlorine embodied energy | M79: Polyurethane | N79: kg | O79: 2.052 | P79: =O79*$P$62/4 -> 187.93182 | Q79: =P79/P$67 -> 0.025744085 | R79: =72.1*N61 -> 68337.822 | S79: 3.76
B80: 1.468 | C80: g/l density of chlorine | M80: PVC | N80: kg | O80: 39.47 | P80: =O80*$P$62/4 -> 3614.8485 | Q80: =P80/P$67 -> 0.49518472 | R80: =77.2*N61 -> 73171.704 | S80: 3.1
B81: 1 | C81: MJ = | D81: 947.817 | E81: BTU
B82: 1 | C82: liter = | E82: 0.264172 | F82: gallons
B83: =B79*D81 -> 21515.446 | C83: BTU/KG
B84: =B83/1000*B80/E82 -> 119.56102 | C84: BTU/gallon
B85: Embodied energy of water source: | C85: https://www.ncbi.nlm.nih.gov/pmc/articles/PMC8933528/ | M85: Waste Water Estimation
B86: 0.005 | C86: MJ/KG embodied energy of water
B87: 1 | C87: KG/L density of water | M87: Q=m*cp*dT | N87: Base Formula
B88: =B86*B87 -> 0.005 | C88: MJ/L
B89: =B88/E82*D81 -> 17.939392 | C89: BTU/gallon | M89: dT | N89: 5 | O89: dF
M90: cP | N90: 1 | O90: btu/lb-F
B91: 0.0003 | C91: KG CO2/KG | D91: embodied carbon for tap water | M91: m | N91: 16680000 | O91: lbs of water per day
B92: 1 | C92: KG = | D92: 2.20462 | E92: pounds | N92: 2000000 | O92: gallons WWTR per day required to be cooled from 105 dF to 100 dF
B93: =B91*D92 -> 0.000661386 | C93: pounds CO2/KG tap water | N93: 8.34 | O93: lbs/gallon density of water
B94: =B93*B87/E82 -> 0.0025036189 | C94: pounds CO2/gallon of tap water
M95: Q= | N95: 83400000 | O95: BTUs removal required to cool 2 million gallons of WWTR per day from 105 to 100 dF
M97: *assume latent heat of evaporation from cooling water in evap condensers cools the wastewater
M99: 970 | N99: BTU/lb | O99: latent heat of water
M101: 85979.381 | N101: lbs water needed
B102: 1.08 | C102: KG CO2 per KG of chlorine | M102: 10309.278 | N102: gallons of water
B103: =B102*D92 -> 2.3809896 | C103: pounds CO2/KG of chlorine | M103: 0.65 | N103: Inefficiency Factor
B104: =B103/1000*B80/E82 -> 0.013231125 | C104: pounds CO2 per gallon of chlorine | M104: =M102*(1+M103) -> 17010.309 | N104: Total Gal of Water
B107: Return to Home Page

Sheet Market
B1: U.S. DEPARTMENT OF ENERGY (DOE) OFFICE OF ENERGY EFFICIENCY AND RENEWABLE ENERGY (EERE)
B2: Techno-economic, Energy & Carbon Heuristic Tool for Early Stage Technologies (TECHTEST)
C3: Return to Planning Page
B4: Market Size
B6: Quantify the total size of the end-use product market. Provide calculations and references at the bottom of the sheet. The end-use product should be defined in the Benchmarking section of the Project Basics tab.
B8: Annual U.S. Production of End-use Product: | C8: =2*365*10000 -> 7300000 | D8: Million Gallons | E8: =IF(EndUse_Product<>""," of "&EndUse_Product&" per year","of (end-use product not yet defined) per year") -> of Cooled Waste Water per year
C9: (all U.S. production, all facilities) | D9: (units)
B11: If the new technology will NOT be deployed in an existing market, or there is not yet any U.S. production of the end-use product, explain below.
B12: Comments:
B14: Market Breakdown
B16: Estimate the percent market share for the new technology, the commercial benchmark, and other competing technologies: - In the "Current Conditions" column, estimate the market breakdown based on the current U.S. market. - In the "Overnight Adoption" column, estimate the market breakdown in a hypothetical "overnight adoption" marketplace where the new technology is fully deployed, but all other market conditions remain the same as the current U.S. market. The total market share in each column should sum to 100%.
C18: Technology* | D18: Product / Application*: | E18: Pre-Deployment | F18: Full Deployment
E19: Market Share (%): Current Conditions | F19: Market Share (%): "Target Potential Market at Full Deployment" Hypothetical Scenario
B20: New Technology: | C20: =New_Technology -> Waste Heat Recovery (Heat Pump) | D20: =New_Technology_Apps -> Cooled Waste Water | E20: 0 | F20: 1
B21: Commercial Benchmark: | C21: =Commercial_Benchmark -> Evaporative Condenser | D21: =Benchmark_Apps -> Cooled Waste Water | E21: 1 | F21: 0
B22: Other Competing Technologies: | C22: =Other_Competing -> 0 | D22: =Other_Competing_Apps -> 0
D23: Sum: | E23: =SUM(E20:E22) -> 1 | F23: =SUM(F20:F22) -> 1
B25: *Note that the technology and product definitions are imported from the Benchmarking section of the "Project Basics" tab. If any edits to these definitions are needed, please modify the definitions in that tab.
B27: References, Notes, and Assumptions
B29: List key references and assumptions used to prepare the data provided in this sheet. Add as many rows as needed.
B35: Calculations
B36: Use this section for project-specific calculations and detailed references supporting the data above. Add as many rows as needed.
B38: Assumed that there are 2 million gallons procceses per day per tower, and there are 10000 towers across the US.
B62: Return to Home Page

Sheet Manufacturing Energy
B1: U.S. DEPARTMENT OF ENERGY (DOE) OFFICE OF ENERGY EFFICIENCY AND RENEWABLE ENERGY (EERE)
B2: Techno-economic, Energy & Carbon Heuristic Tool for Early Stage Technologies (TECHTEST)
C3: Return to Planning Page
B4: Manufacturing Energy, Emissions, and Energy Costs
B5: Estimate onsite energy consumption (in the blue input cells) by energy/fuel type. Energy consumption totals should correspond to the reference volume of finished product, as provided in the Ref Volume tab. Follow the same process for the new technology (left) and commercial benchmark technology (right) to facilitate comparisons. Default data are provided for energy prices, GWP, and source-to-site ratios (in the violet cells). These are based on industrial sector averages (see Summary Ref Tables tab) and can be user-adjusted from the default values for greater accuracy, if better estimates are available. IPCC AR5 values for 100-Year Global Warming Potential (GWP) are used to esimate the emissions associated with energy consumption. See the GWP & Combustion Data tab (linked below) for source data and assumptions.
C7: New Technology (at Industrial Scale) | M7: Commercial Benchmark
B8: Technology Name | C8: =New_Technology -> Waste Heat Recovery (Heat Pump) | L8: Technology Name | M8: =Commercial_Benchmark -> Evaporative Condenser
B9: Specific Product | C9: =New_Technology_Apps -> Cooled Waste Water | L9: Specific Product | M9: =Benchmark_Apps -> Cooled Waste Water
B10: Reference Volume | C10: =Ref_Volume -> 2 | D10: =Ref_Volume_Unit -> Million Gallons | L10: Reference Volume | M10: =Ref_Volume_Benchmark -> 2 | N10: =Ref_Volume_Unit -> Million Gallons
C11: (ref volume) | D11: (units) | M11: (ref volume) | N11: (units)
B13: New Technology - Energy Consumption & Cost Data (to produce reference volume) | L13: Commercial Benchmark - Energy Consumption & Cost Data (to produce reference volume)
D14: Data entry | E14: Default sector data* (Can be modified if needed. If modifying value, change background color to blue) | N14: Data entry | O14: Default sector data* (Can be modified if needed. If modifying value, change background color to blue)
D15: ↓ | N15: ↓
B16: Fuel or Energy Type | C16: Energy Source (Dropdowns available for Petroleum, Coal, and Renewable) | D16: Onsite Energy Consumption* (MMBtu) | E16: Specific Price ($/MMBtu) | F16: Specific 100-yr GWP (lb CO2-eq / MMBtu) | G16: Source-to-Site Ratio (electricity and steam only) | H16: Primary Energy Consumption, including offsite losses (MMBtu) | I16: Energy Cost ($) | J16: GWP Emissions (lb CO2-eq) | L16: Fuel or Energy Type | M16: Energy Source (Dropdowns available for Petroleum, Coal, and Renewable) | N16: Onsite Energy Consumption* (MMBtu) | O16: Specific Price ($/MMBtu) | P16: Specific 100-yr GWP (lb CO2-eq / MMBtu) | Q16: Source-to-Site Ratio (electricity and steam only) | R16: Primary Energy Consumption, including offsite losses (MMBtu) | S16: Energy Cost ($) | T16: GWP Emissions (lb CO2-eq)
B17: Electricity | C17: Electricity | D17: =F61*C69 -> 0.0048050532 | E17: =IF(ISNUMBER('Summary Ref Tables'!J8),'Summary Ref Tables'!J8,"") -> 21.043376 | F17: ='Grid Mix Customization'!F31 -> 108.58735 | G17: ='Summary Ref Tables'!F8 -> 2.8593558 | H17: =IF(D17<>"",D17*G17,"") -> 0.013739356 | I17: =IF(D17<>"",D17*E17,"") -> 0.10111454 | J17: =IF(D17<>"",D17*F17,"") -> 0.52176797 | L17: Electricity | M17: Electricity | N17: =B82+D17 -> 0.37120338 | O17: =IF(ISNUMBER('Summary Ref Tables'!J8),'Summary Ref Tables'!J8,"") -> 21.043376 | P17: ='Grid Mix Customization'!F31 -> 108.58735 | Q17: ='Summary Ref Tables'!F8 -> 2.8593558 | R17: =IF(N17<>"",N17*Q17,"") -> 1.0614025 | S17: =IF(N17<>"",N17*O17,"") -> 7.8113723 | T17: =IF(N17<>"",N17*P17,"") -> 40.30799
B18: Petroleum | C18: Diesel & distillate fuel oil | E18: =INDEX('Summary Ref Tables'!J9:J16,MATCH(C18,'Summary Ref Tables'!E9:E16,0)) -> 18.343154 | F18: =INDEX('Summary Ref Tables'!K9:K16,MATCH(C18,'Summary Ref Tables'!E9:E16,0)) -> 172.926 | G18: ='Summary Ref Tables'!F9 -> 1 | H18: =IF(D18<>"",D18*G18,"") | I18: =IF(D18<>"",D18*E18,"") | J18: =IF(D18<>"",D18*F18,"") | L18: Petroleum | M18: Diesel & distillate fuel oil | O18: =INDEX('Summary Ref Tables'!J9:J16,MATCH(M18,'Summary Ref Tables'!E9:E16,0)) -> 18.343154 | P18: =INDEX('Summary Ref Tables'!K9:K16,MATCH(M18,'Summary Ref Tables'!E9:E16,0)) -> 172.926 | Q18: ='Summary Ref Tables'!F9 -> 1 | R18: =IF(N18<>"",N18*Q18,"") | S18: =IF(N18<>"",N18*O18,"") | T18: =IF(N18<>"",N18*P18,"")
B19: Coal | C19: Anthracite | E19: =INDEX('Summary Ref Tables'!J17:J20,MATCH(C19,'Summary Ref Tables'!E17:E20,0)) -> 6.5924774 | F19: =INDEX('Summary Ref Tables'!K17:K20,MATCH(C19,'Summary Ref Tables'!E17:E20,0)) -> 229.7867 | G19: ='Summary Ref Tables'!F17 -> 1 | H19: =IF(D19<>"",D19*G19,"") | I19: =IF(D19<>"",D19*E19,"") | J19: =IF(D19<>"",D19*F19,"") | L19: Coal | M19: Anthracite | O19: =INDEX('Summary Ref Tables'!J17:J20,MATCH(M19,'Summary Ref Tables'!E17:E20,0)) -> 6.5924774 | P19: =INDEX('Summary Ref Tables'!K17:K20,MATCH(M19,'Summary Ref Tables'!E17:E20,0)) -> 229.7867 | Q19: ='Summary Ref Tables'!F17 -> 1 | R19: =IF(N19<>"",N19*Q19,"") | S19: =IF(N19<>"",N19*O19,"") | T19: =IF(N19<>"",N19*P19,"")
B20: Natural Gas | C20: Natural Gas | D20: =F62*C69 -> 0.01334737 | E20: =IF(ISNUMBER('Summary Ref Tables'!J21),'Summary Ref Tables'!J21,"") -> 5.7940327 | F20: ='Summary Ref Tables'!K21 -> 130.6149 | G20: ='Summary Ref Tables'!F21 -> 1 | H20: =IF(D20<>"",D20*G20,"") -> 0.01334737 | I20: =IF(D20<>"",D20*E20,"") -> 0.077335098 | J20: =IF(D20<>"",D20*F20,"") -> 1.7433654 | L20: Natural Gas | M20: Natural Gas | N20: =D20 -> 0.01334737 | O20: ='Summary Ref Tables'!J21 -> 5.7940327 | P20: ='Summary Ref Tables'!K21 -> 130.6149 | Q20: ='Summary Ref Tables'!F21 -> 1 | R20: =IF(N20<>"",N20*Q20,"") -> 0.01334737 | S20: =IF(N20<>"",N20*O20,"") -> 0.077335098 | T20: =IF(N20<>"",N20*P20,"") -> 1.7433654
B21: Renewable | C21: Wood Biomass | E21: =INDEX('Summary Ref Tables'!I22:I30,MATCH(C21,'Summary Ref Tables'!E22:E30,0)) -> 2.89 | F21: =INDEX('Summary Ref Tables'!K22:K30,MATCH(C21,'Summary Ref Tables'!E22:E30,0)) -> 264.93605 | G21: ='Summary Ref Tables'!F19 -> 1 | H21: =IF(D21<>"",D21*G21,"") | I21: =IF(D21<>"",D21*E21,"") | J21: =IF(D21<>"",D21*F21,"") | L21: Renewable | M21: Wood Biomass | O21: =INDEX('Summary Ref Tables'!J22:J30,MATCH(M21,'Summary Ref Tables'!E22:E30,0)) -> 2.89 | P21: =INDEX('Summary Ref Tables'!K22:K30,MATCH(M21,'Summary Ref Tables'!E22:E30,0)) -> 264.93605 | Q21: ='Summary Ref Tables'!F19 -> 1 | R21: =IF(N21<>"",N21*Q21,"") | S21: =IF(N21<>"",N21*O21,"") | T21: =IF(N21<>"",N21*P21,"")
B22: Steam | C22: Steam and Hot Water** | E22: =IF(ISNUMBER('Summary Ref Tables'!J30),'Summary Ref Tables'!J30,"") -> 4.7 | F22: ='Summary Ref Tables'!K30 -> 146.39001 | G22: ='Summary Ref Tables'!F30 -> 1.1992 | H22: =IF(D22<>"",D22*G22,"") | I22: =IF(D22<>"",D22*E22,"") | J22: =IF(D22<>"",D22*F22,"") | L22: Steam | M22: Steam and Hot Water** | O22: =IF(ISNUMBER('Summary Ref Tables'!J30),'Summary Ref Tables'!J30,"") -> 4.7 | P22: ='Summary Ref Tables'!K30 -> 146.39001 | Q22: ='Summary Ref Tables'!F30 -> 1.1992 | R22: =IF(N22<>"",N22*Q22,"") | S22: =IF(N22<>"",N22*O22,"") | T22: =IF(N22<>"",N22*P22,"")
B23: Custom Input I | E23: =IF(C23="","",INDEX('Summary Ref Tables'!J8:J30,MATCH(C23,'Summary Ref Tables'!E8:E30,0))) | F23: =IF(C23="","",INDEX('Summary Ref Tables'!K8:K30,MATCH(C23,'Summary Ref Tables'!E8:E30,0))) | G23: =IF(C23="","",INDEX('Summary Ref Tables'!F8:F30,MATCH(C23,'Summary Ref Tables'!E8:E30,0))) | H23: =IF(D23<>"",D23*G23,"") | I23: =IF(D23<>"",D23*E23,"") | J23: =IF(D23<>"",D23*F23,"") | L23: Custom Input I | O23: =IF(M23="","",INDEX('Summary Ref Tables'!J8:J30,MATCH(M23,'Summary Ref Tables'!E8:E30,0))) | P23: =IF(M23="","",INDEX('Summary Ref Tables'!K8:K30,MATCH(M23,'Summary Ref Tables'!E8:E30,0))) | Q23: =IF(M23="","",INDEX('Summary Ref Tables'!F8:F30,MATCH(M23,'Summary Ref Tables'!E8:E30,0))) | R23: =IF(N23<>"",N23*Q23,"") | S23: =IF(N23<>"",N23*O23,"") | T23: =IF(N23<>"",N23*P23,"")
B24: Custom Input II | E24: =IF(C24="","",INDEX('Summary Ref Tables'!J8:J30,MATCH(C24,'Summary Ref Tables'!E8:E30,0))) | F24: =IF(C24="","",INDEX('Summary Ref Tables'!K8:K30,MATCH(C24,'Summary Ref Tables'!E8:E30,0))) | G24: =IF(C24="","",INDEX('Summary Ref Tables'!F8:F30,MATCH(C24,'Summary Ref Tables'!E8:E30,0))) | H24: =IF(D24<>"",D24*G24,"") | I24: =IF(D24<>"",D24*E24,"") | J24: =IF(D24<>"",D24*F24,"") | L24: Custom Input II | M24: Liquified Petroleum Gas | O24: =IF(M24="","",INDEX('Summary Ref Tables'!J8:J30,MATCH(M24,'Summary Ref Tables'!E8:E30,0))) -> 12.217275 | P24: =IF(M24="","",INDEX('Summary Ref Tables'!K8:K30,MATCH(M24,'Summary Ref Tables'!E8:E30,0))) -> 146.8969 | Q24: =IF(M24="","",INDEX('Summary Ref Tables'!F8:F30,MATCH(M24,'Summary Ref Tables'!E8:E30,0))) -> 1 | R24: =IF(N24<>"",N24*Q24,"") | S24: =IF(N24<>"",N24*O24,"") | T24: =IF(N24<>"",N24*P24,"")
B25: Custom Input III | C25: Petroleum Coke | E25: =IF(C25="","",INDEX('Summary Ref Tables'!J8:J30,MATCH(C25,'Summary Ref Tables'!E8:E30,0))) -> 4.3129584 | F25: =IF(C25="","",INDEX('Summary Ref Tables'!K8:K30,MATCH(C25,'Summary Ref Tables'!E8:E30,0))) -> 227.3544 | G25: =IF(C25="","",INDEX('Summary Ref Tables'!F8:F30,MATCH(C25,'Summary Ref Tables'!E8:E30,0))) -> 1 | H25: =IF(D25<>"",D25*G25,"") | I25: =IF(D25<>"",D25*E25,"") | J25: =IF(D25<>"",D25*F25,"") | L25: Custom Input III | O25: =IF(M25="","",INDEX('Summary Ref Tables'!J8:J30,MATCH(M25,'Summary Ref Tables'!E8:E30,0))) | P25: =IF(M25="","",INDEX('Summary Ref Tables'!K8:K30,MATCH(M25,'Summary Ref Tables'!E8:E30,0))) | Q25: =IF(M25="","",INDEX('Summary Ref Tables'!F8:F30,MATCH(M25,'Summary Ref Tables'!E8:E30,0))) | R25: =IF(N25<>"",N25*Q25,"") | S25: =IF(N25<>"",N25*O25,"") | T25: =IF(N25<>"",N25*P25,"")
H26: =SUM(H17:H25) -> 0.027086726 | I26: =SUM(I17:I25) -> 0.17844964 | J26: =SUM(J17:J25) -> 2.2651334 | R26: =SUM(R17:R25) -> 1.0747499 | S26: =SUM(S17:S25) -> 7.8887074 | T26: =SUM(T17:T25) -> 42.051355
B27: * Link to reference data tab
B28: ** To avoid double-counting, only enter Steam data in this row if fuel/electricity used to generate the steam is not already included above.
B30: Manufacturing Process Emissions (if applicable)
B31: If there are process emissions associated with either the new technology or commercial benchmark technology, list the emissions and associated 100-year GWP below. Do not include any emissions associated with combustion of fuels (already captured above). If there are no significant process emissions, leave this section blank.
C33: New Technology - Process Emissions (to produce reference volume) | M33: Commercial Benchmark - Process Emissions (to produce reference volume)
C34: Emission Type (chemical name or acronym) | D34: Amount emitted (lb) | E34: 100-Year GWP* | F34: Suggested 100-Year GWP | G34: Embodied Carbon (lb CO2-eq) | M34: Emission Type (chemical name or acronym) | N34: Amount emitted (lb) | O34: 100-Year GWP* | P34: Suggested 100-Year GWP | Q34: Embodied Carbon (lb CO2-eq)
C35: R-134a | D35: 0.049174521 | E35: 1300 | F35: {=_xlfn.SWITCH(C35,'GWP Ref Tables'!D8,'GWP Ref Tables'!E8,'GWP Ref Tables'!D9,CH4_GWP,'GWP Ref Tables'!D10,N2O_GWP,'GWP Ref Tables'!D11,'GWP Ref Tables'!E11,'GWP Ref Tables'!D12,'GWP Ref Tables'!E12,"")} | G35: =IF(C35<>"",D35*E35,"") -> 63.926877 | P35: {=_xlfn.SWITCH(M35,'GWP Ref Tables'!D8,'GWP Ref Tables'!E8,'GWP Ref Tables'!D9,CH4_GWP,'GWP Ref Tables'!D10,N2O_GWP,'GWP Ref Tables'!D11,'GWP Ref Tables'!E11,'GWP Ref Tables'!D12,'GWP Ref Tables'!E12,"")} | Q35: =IF(M35<>"",N35*O35,"")
F36: {=_xlfn.SWITCH(C36,'GWP Ref Tables'!D8,'GWP Ref Tables'!E8,'GWP Ref Tables'!D9,CH4_GWP,'GWP Ref Tables'!D10,N2O_GWP,'GWP Ref Tables'!D11,'GWP Ref Tables'!E11,'GWP Ref Tables'!D12,'GWP Ref Tables'!E12,"")} | G36: =IF(C36<>"",D36*E36,"") | P36: {=_xlfn.SWITCH(M36,'GWP Ref Tables'!D9,'GWP Ref Tables'!E9,'GWP Ref Tables'!D10,CH4_GWP,'GWP Ref Tables'!D11,N2O_GWP,'GWP Ref Tables'!D12,'GWP Ref Tables'!E12,'GWP Ref Tables'!D13,'GWP Ref Tables'!E13,"")} -> 0 | Q36: =IF(M36<>"",N36*O36,"")
F37: {=_xlfn.SWITCH(C37,'GWP Ref Tables'!D8,'GWP Ref Tables'!E8,'GWP Ref Tables'!D9,CH4_GWP,'GWP Ref Tables'!D10,N2O_GWP,'GWP Ref Tables'!D11,'GWP Ref Tables'!E11,'GWP Ref Tables'!D12,'GWP Ref Tables'!E12,"")} | G37: =IF(C37<>"",D37*E37,"") | P37: {=_xlfn.SWITCH(M37,'GWP Ref Tables'!D10,'GWP Ref Tables'!E10,'GWP Ref Tables'!D11,CH4_GWP,'GWP Ref Tables'!D12,N2O_GWP,'GWP Ref Tables'!D13,'GWP Ref Tables'!E13,'GWP Ref Tables'!D14,'GWP Ref Tables'!E14,"")} -> 0 | Q37: =IF(M37<>"",N37*O37,"")
F38: Total: | G38: =SUM(G35:G37) -> 63.926877 | P38: Total | Q38: =SUM(Q35:Q37) -> 0
C40: * Use IPCC AR5 values for 100-Year Global Warming Potential (GWP). See the GWP Data tab (linked below) for excerpted GWP values for the most common emissions types, and a link to the full IPCC report for a complete list.
C41: Reference Data Tables: Global Warming Potential
B43: References, Notes, and Assumptions
B45: List key references and assumptions used to prepare the data provided in this sheet. Add as many rows as needed. | C45: Residential Heat Pump LCA from 2022:
C46: https://reader.elsevier.com/reader/sd/pii/S2212827122000580?token=494650C2CFA0DC2FF939A96C42BEA8B301FCFD6FBACF9839DDD737C0FF902E07A5E5444A7DDD55D24AFA2FEA0A34E46F&originRegion=us-east-1&originCreation=20230110001925
C47: https://ww2.arb.ca.gov/resources/documents/high-gwp-refrigerants
B51: Calculations
B52: Use this section for project-specific calculations and detailed references supporting the data above. Add as many rows as needed.
B53: All Material Costs for comparable Heat Pump (Only Energy and process emissions are included in this section)
B54: Material for a 5 kWh heat pump, converted to 366.3 kWh (Assuming Linear Scale Up) | H54: Conversion to daily output for heat pump
B55: Material | C55: Unit | D55: Amount per Unit | E55: Scaled up to 366.3 kWh | F55: Scaled to per Functional Unit | G55: Energy | H55: 30 | I55: Pump energy use: MMbtu / day
B56: Copper | C56: kg | D56: 36.6 | E56: =D56*366.3/5 -> 2681.316 | F56: =E56/$H$63 -> 0.36730356 | G56: N | H56: 293.07107 | I56: kWh in 1 MMbtu
B57: Elastomer | C57: kg | D57: 16 | E57: =D57*366.3/5 -> 1172.16 | F57: =E57/$H$63 -> 0.16056986 | G57: N | H57: =H55*H56 -> 8792.1321 | I57: kWh/day used by heat pump
B58: HDPE | C58: kg | D58: 0.5 | E58: =D58*366.3/5 -> 36.63 | F58: =E58/$H$63 -> 0.0050178082 | G58: N | H58: =H57/24 -> 366.33884 | I58: kWh per hour (assuming ~24 hour use)
B59: Low alloyed steel | C59: kg | D59: 32 | E59: =D59*366.3/5 -> 2344.32 | F59: =E59/$H$63 -> 0.32113973 | G59: N
B60: Lubricating Oil | C60: kg | D60: 2.7 | E60: =D60*366.3/5 -> 197.802 | F60: =E60/$H$63 -> 0.027096164 | G60: N
B61: Medium-voltage Electricity | C61: MJ | D61: 504 | E61: =D61*366.3/5 -> 36923.04 | F61: =E61/$H$63 -> 5.0579507 | G61: Y | H61: Conversion from 20 Year Lifetime to Functional Unit
B62: Natural Gas | C62: MJ | D62: 1400 | E62: =D62*366.3/5 -> 102564 | F62: =E62/$H$63 -> 14.049863 | G62: Y | H62: 20 | I62: Years
B63: PVC | C63: kg | D63: 1.6 | E63: =D63*366.3/5 -> 117.216 | F63: =E63/$H$63 -> 0.016056986 | G63: N | H63: =20*365 -> 7300 | I63: Days
B64: R-134a | C64: kg | D64: 4.9 | E64: =D64*366.3/5 -> 358.974 | F64: =E64/$H$63 -> 0.049174521 | G64: N
B65: Reinforced Steel | C65: kg | D65: 130 | E65: =D65*366.3/5 -> 9523.8 | F65: =E65/$H$63 -> 1.3046301 | G65: N
B67: Convert MMbtu to MJ
B69: 1 MJ = | C69: 0.00095 | D69: MMbtu
B73: **For this section, we are going to assume the manufacturing energy for the Benchmark is the energy required to supply the raw materials that support/enable the evaporative cooling loop for the evaporative condensers.
B74: **Note that actual city water costs are included within "OpEx" tab in "Other Recurring Costs" section
B75: Evaporative Condenser
B76: 5 | C76: hp motor/pump used to tranport/supply the (4) evaporative condensers with city water for cooling
B77: 1 | C77: hp motor on chemical pump used to supply/dose city water for cooling with biocide for microbial control
B78: =B76+B77 -> 6 | C78: hp of continuous pumping power needed to supply raw materials for evaorative condensers
B79: 0.7457 | C79: kW = | D79: 1 | E79: hp
B80: =B78*B79*24 -> 107.3808 | C80: kWh daily electricity required
B81: 3412.14 | C81: BTU per kWh
B82: =B80*B81/1000000 -> 0.36639832 | C82: MMBTUs in daily electricity required
B103: Return to Home Page

Sheet Use Phase Energy
B1: U.S. DEPARTMENT OF ENERGY (DOE) OFFICE OF ENERGY EFFICIENCY AND RENEWABLE ENERGY (EERE)
B2: Techno-economic, Energy & Carbon Heuristic Tool for Early Stage Technologies (TECHTEST)
C3: Return to Planning Page
B4: Use Phase Energy and Emissions
B6: Complete this tab for any technology expected to have an energy impact during final use of the finished product in its end-use sector. Technologies for which the Use Phase is important include energy-consuming devices or systems, energy-producing devices or systems, or material/component inputs to such systems. For example, a lightweight material may provide fuel savings (compared to typical materials) when used in a vehicle; and an energy-efficient device may provide electricity savings (compared to typical devices) when used in a consumer application. If the technology is not expected to have use phase impacts, leave this section blank. Technologies for which the Use Phase is not expected to be important include technologies where the end-use product is identical to that produced using current typical technologies. For example, a new production route for a commodity chemical would not be expected to have use phase impacts because the end-use product (the commodity chemical) is identical. To evaluate the use phase energy impact, estimate the total U.S. annual energy consumption (for the end-use market impacted by the technology) based on two scenarios:
B7: 1. Current Annual Energy Consumption
B8: 2. Hypothetical Annual Energy Consumption, Based on "Overnight Replacement" with New Technology
B9: In the "Current" scenario, assume the current market size and market conditions. Consider the entire market, including all facilities and manufacturers. In the "Overnight Replacement" scenario, assume a hypothetical market in which the new technology was immediately and fully deployed (at its maximum anticipated market share), with the market size and all other market conditions held constant (this is a simplification). Enter data on an annual basis in the blue cells below, considering the U.S. market and breaking down by sector and energy source. Enter data only into rows for sector(s) and energy sources applicable to the technology. For convenience, sector-average values for GWP and source-to-site ratio (based on EIA and IPCC reference data) are provided in the purple cells. These data may be over-written if more accurate facility- or industry-specific data are available. Provide your references, assumptions, source data, and calculations in the sections at the bottom of this tab.
D11: Default sector data* (can be modified if needed) | F11: Data entry** ↓ | K11: Data entry** ↓
D12: ↓ | E12: ↓ | F12: Current Annual U.S. Energy & Emissions - Product Use Phase (based on current technologies in use) | K12: Hypothetical Annual Energy & Emissions - Product Use Phase (based on "overnight replacement" with new technology)
B13: Sector & Energy Type | C13: Energy Source | D13: Specific 100-yr GWP (lb CO2-eq / MMBtu) | E13: Source-to-Site Ratio (Btu primary / Btu onsite) | F13: Annual Onsite Energy Consumption (MMBtu) | G13: Specific Price ($/MMBtu) | H13: Annual Primary Energy Consumption, including offsite losses (MMBtu) | I13: Annual Associated Cost ($) | J13: Annual Associated GWP Emissions (tons CO2-eq) | K13: Annual Energy Consumption (fuel specific units) | L13: Specific Price ($/MMBtu) | M13: Annual Primary Energy Consumption (MMBtu) | N13: Annual Associated Cost ($) | O13: Annual Associated GWP Emissions (tons CO2-eq)
B14: Industrial Sector | H14: =IF(F14<>"",(F14*#REF!)/1000000,"") | J14: =IF(H14<>"",(H14*E14)/1000000,"") | M14: =IF(K14<>"",(K14*F14)/1000000,"")
B15: Electricity | C15: Electricity | D15: ='Grid Mix Customization'!F31 -> 108.58735 | E15: ='Summary Ref Tables'!F8 -> 2.8593558 | F15: =D51*US_Annual_Production/Ref_Volume -> 44577450 | G15: =IF(ISNUMBER('Summary Ref Tables'!J8),'Summary Ref Tables'!J8,"") -> 21.043376 | H15: =IF(F15<>"",F15*$E15,"") -> 1.2746279e+08 | I15: =IF(F15<>"",G15*$F15,"") -> 9.3806006e+08 | J15: =IF(F15<>"",F15*$D15*0.0005,"") -> 2420273.5 | K15: =C93*US_Annual_Production/Ref_Volume -> 1.0813019e+08 | L15: =IF(ISNUMBER('Summary Ref Tables'!J8),'Summary Ref Tables'!J8,"") -> 21.043376 | M15: =IF(K15<>"",K15*$E15,"") -> 3.0918269e+08 | N15: =IF(K15<>"",L15*$K15,"") -> 2.2754243e+09 | O15: =IF(K15<>"",K15*$D15*0.0005,"") -> 5870785.4
B16: Petroleum Look Up | C16: Motor Gasoline | D16: =INDEX('Summary Ref Tables'!K9:K16,MATCH(C16,'Summary Ref Tables'!E9:E16,0)) -> 161.7612 | E16: 1 | G16: =INDEX('Summary Ref Tables'!J9:J16,MATCH(C16,'Summary Ref Tables'!E9:E16,0)) -> 21.540594 | H16: =IF(F16<>"",F16*$E16,"") | I16: =IF(F16<>"",G16*$F16,"") | J16: =IF(F16<>"",F16*$D16*0.0005,"") | L16: =INDEX('Summary Ref Tables'!J9:J16,MATCH(C16,'Summary Ref Tables'!E9:E16,0)) -> 21.540594 | M16: =IF(K16<>"",K16*$E16,"") | N16: =IF(K16<>"",L16*$K16,"") | O16: =IF(K16<>"",K16*$D16*0.0005,"")
B17: Coal Look Up | C17: Coal Coke | D17: =INDEX('Summary Ref Tables'!K17:K20,MATCH(C17,'Summary Ref Tables'!E17:E20,0)) -> 250.46252 | E17: ='Summary Ref Tables'!F17 -> 1 | G17: =INDEX('Summary Ref Tables'!J17:J20,MATCH(C17,'Summary Ref Tables'!E17:E20,0)) -> 7.661341 | H17: =IF(F17<>"",F17*$E17,"") | I17: =IF(F17<>"",G17*$F17,"") | J17: =IF(F17<>"",F17*$D17*0.0005,"") | L17: =INDEX('Summary Ref Tables'!J17:J20,MATCH(C17,'Summary Ref Tables'!E17:E20,0)) -> 7.661341 | M17: =IF(K17<>"",K17*$E17,"") | N17: =IF(K17<>"",L17*$K17,"") | O17: =IF(K17<>"",K17*$D17*0.0005,"")
B18: Natural Gas | C18: Natural Gas | D18: ='Summary Ref Tables'!K21 -> 130.6149 | E18: ='Summary Ref Tables'!F21 -> 1 | G18: =IF(ISNUMBER('Summary Ref Tables'!J21),'Summary Ref Tables'!J21,"") -> 5.7940327 | H18: =IF(F18<>"",F18*$E18,"") | I18: =IF(F18<>"",G18*$F18,"") | J18: =IF(F18<>"",F18*$D18*0.0005,"") | K18: =(C98*-1)*US_Annual_Production/Ref_Volume -> -2.227717e+08 | L18: =IF(ISNUMBER('Summary Ref Tables'!J21),'Summary Ref Tables'!J21,"") -> 5.7940327 | M18: =IF(K18<>"",K18*$E18,"") -> -2.227717e+08 | N18: =IF(K18<>"",L18*$K18,"") -> -1.2907465e+09 | O18: =IF(K18<>"",K18*$D18*0.0005,"") -> -14548652
B19: Renewable Look Up | C19: Solar | D19: =INDEX('Summary Ref Tables'!K22:K29,MATCH(C19,'Summary Ref Tables'!E22:E29,0)) -> 31.015814 | E19: ='Summary Ref Tables'!F22 -> 1 | G19: =INDEX('Summary Ref Tables'!J22:J29,MATCH(C19,'Summary Ref Tables'!E22:E29,0)) -> 14.067408 | H19: =IF(F19<>"",F19*$E19,"") | I19: =IF(F19<>"",G19*$F19,"") | J19: =IF(F19<>"",F19*$D19*0.0005,"") | L19: =INDEX('Summary Ref Tables'!J22:J29,MATCH(C19,'Summary Ref Tables'!E22:E29,0)) -> 14.067408 | M19: =IF(K19<>"",K19*$E19,"") | N19: =IF(K19<>"",L19*$K19,"") | O19: =IF(K19<>"",K19*$D19*0.0005,"")
B20: Steam | C20: Steam and Hot Water* | D20: ='Summary Ref Tables'!K30 -> 146.39001 | E20: ='Summary Ref Tables'!F30 -> 1.1992 | G20: =IF(ISNUMBER('Summary Ref Tables'!J30),'Summary Ref Tables'!J30,"") -> 4.7 | H20: =IF(F20<>"",F20*$E20,"") | I20: =IF(F20<>"",G20*$F20,"") | J20: =IF(F20<>"",F20*$D20*0.0005,"") | L20: =IF(ISNUMBER('Summary Ref Tables'!J30),'Summary Ref Tables'!J30,"") -> 4.7 | M20: =IF(K20<>"",K20*$E20,"") | N20: =IF(K20<>"",L20*$K20,"") | O20: =IF(K20<>"",K20*$D20*0.0005,"")
B21: Custom Input I | D21: =IF(C21="","",INDEX('Summary Ref Tables'!K8:K30,MATCH(C21,'Summary Ref Tables'!E8:E30,0))) | E21: =IF(C21="","",INDEX('Summary Ref Tables'!F8:F30,MATCH(C21,'Summary Ref Tables'!E8:E30,0))) | G21: =IF(C21="","",INDEX('Summary Ref Tables'!J8:J30,MATCH(C21,'Summary Ref Tables'!E8:E30,0))) | H21: =IF(F21<>"",F21*$E21,"") | I21: =IF(F21<>"",G21*$F21,"") | J21: =IF(F21<>"",F21*$D21*0.0005,"") | L21: =IF(C21="","",INDEX('Summary Ref Tables'!J8:J30,MATCH(C21,'Summary Ref Tables'!E8:E30,0))) | M21: =IF(K21<>"",K21*$E21,"") | N21: =IF(K21<>"",L21*$K21,"") | O21: =IF(K21<>"",K21*$D21*0.0005,"")
B22: Custom Input II | D22: =IF(C22="","",INDEX('Summary Ref Tables'!K8:K30,MATCH(C22,'Summary Ref Tables'!E8:E30,0))) | E22: =IF(C22="","",INDEX('Summary Ref Tables'!F8:F30,MATCH(C22,'Summary Ref Tables'!E8:E30,0))) | G22: =IF(C22="","",INDEX('Summary Ref Tables'!J8:J30,MATCH(C22,'Summary Ref Tables'!E8:E30,0))) | H22: =IF(F22<>"",F22*$E22,"") | I22: =IF(F22<>"",G22*$F22,"") | J22: =IF(F22<>"",F22*$D22*0.0005,"") | L22: =IF(C22="","",INDEX('Summary Ref Tables'!J8:J30,MATCH(C22,'Summary Ref Tables'!E8:E30,0))) | M22: =IF(K22<>"",K22*$E22,"") | N22: =IF(K22<>"",L22*$K22,"") | O22: =IF(K22<>"",K22*$D22*0.0005,"")
B23: Custom Input III | D23: =IF(C23="","",INDEX('Summary Ref Tables'!K8:K30,MATCH(C23,'Summary Ref Tables'!E8:E30,0))) | E23: =IF(C23="","",INDEX('Summary Ref Tables'!F8:F30,MATCH(C23,'Summary Ref Tables'!E8:E30,0))) | G23: =IF(C23="","",INDEX('Summary Ref Tables'!J8:J30,MATCH(C23,'Summary Ref Tables'!E8:E30,0))) | H23: =IF(F23<>"",F23*$E23,"") | I23: =IF(F23<>"",G23*$F23,"") | J23: =IF(F23<>"",F23*$D23*0.0005,"") | L23: =IF(C23="","",INDEX('Summary Ref Tables'!J8:J30,MATCH(C23,'Summary Ref Tables'!E8:E30,0))) | M23: =IF(K23<>"",K23*$E23,"") | N23: =IF(K23<>"",L23*$K23,"") | O23: =IF(K23<>"",K23*$D23*0.0005,"")
B26: Transportation Sector | N26: =IF(G26<>"",L26*$K26,"")
B27: Electricity | C27: Electricity | D27: ='Grid Mix Customization'!F31 -> 108.58735 | E27: ='Summary Ref Tables'!F34 -> 2.8593799 | G27: =IF(ISNUMBER('Summary Ref Tables'!J34),'Summary Ref Tables'!J34,"") -> 21.043376 | H27: =IF(F27<>"",F27*$E27,"") | I27: =IF(F27<>"",G27*$F27,"") | J27: =IF(F27<>"",F27*$D27*0.0005,"") | L27: =IF(ISNUMBER('Summary Ref Tables'!J8),'Summary Ref Tables'!J8,"") -> 21.043376 | M27: =IF(K27<>"",K27*$E27,"") | N27: =IF(K27<>"",L27*$K27,"") | O27: =IF(K27<>"",K27*$D27*0.0005,"")
B28: Petroleum Look Up | C28: Motor gasoline | D28: =INDEX('Summary Ref Tables'!K35:K41,MATCH(C28,'Summary Ref Tables'!E35:E41,0)) -> 165.29626 | E28: ='Summary Ref Tables'!F35 -> 1 | G28: =INDEX('Summary Ref Tables'!J35:J41,MATCH(C28,'Summary Ref Tables'!E35:E41,0)) -> 18.638955 | H28: =IF(F28<>"",F28*$E28,"") | I28: =IF(F28<>"",G28*$F28,"") | J28: =IF(F28<>"",F28*$D28*0.0005,"") | L28: =INDEX('Summary Ref Tables'!J35:J41,MATCH(C28,'Summary Ref Tables'!E35:E41,0)) -> 18.638955 | M28: =IF(K28<>"",K28*$E28,"") | N28: =IF(K28<>"",L28*$K28,"") | O28: =IF(K28<>"",K28*$D28*0.0005,"")
B29: Natural Gas | C29: Natural Gas (pipelines and fuel) | D29: ='Summary Ref Tables'!K42 -> 138.17138 | E29: ='Summary Ref Tables'!F42 -> 1 | G29: =IF(ISNUMBER('Summary Ref Tables'!J21),'Summary Ref Tables'!J21,"") -> 5.7940327 | H29: =IF(F29<>"",F29*$E29,"") | I29: =IF(F29<>"",G29*$F29,"") | J29: =IF(F29<>"",F29*$D29*0.0005,"") | L29: =IF(ISNUMBER('Summary Ref Tables'!J21),'Summary Ref Tables'!J21,"") -> 5.7940327 | M29: =IF(K29<>"",K29*$E29,"") | N29: =IF(K29<>"",L29*$K29,"") | O29: =IF(K29<>"",K29*$D29*0.0005,"")
B30: Renewable Fuels | C30: Biomass | D30: ='Summary Ref Tables'!K43 -> 165.2502 | E30: ='Summary Ref Tables'!F43 -> 1 | G30: =IF(ISNUMBER('Summary Ref Tables'!J22),'Summary Ref Tables'!J22,"") -> 2.89 | H30: =IF(F30<>"",F30*$E30,"") | I30: =IF(F30<>"",G30*$F30,"") | J30: =IF(F30<>"",F30*$D30*0.0005,"") | L30: =IF(ISNUMBER('Summary Ref Tables'!J22),'Summary Ref Tables'!J22,"") -> 2.89 | M30: =IF(K30<>"",K30*$E30,"") | N30: =IF(K30<>"",L30*$K30,"") | O30: =IF(K30<>"",K30*$D30*0.0005,"")
B31: Custom Input I | D31: =IF(C31="","",INDEX('Summary Ref Tables'!K34:K43,MATCH(C31,'Summary Ref Tables'!E34:E43,0))) | E31: =IF(C31="","",INDEX('Summary Ref Tables'!F34:F43,MATCH(C31,'Summary Ref Tables'!E34:E43,0))) | G31: =IF(C31="","",INDEX('Summary Ref Tables'!J34:J43,MATCH(C31,'Summary Ref Tables'!E34:E43,0))) | H31: =IF(F31<>"",F31*$E31,"") | I31: =IF(F31<>"",G31*$F31,"") | J31: =IF(F31<>"",F31*$D31*0.0005,"") | L31: =IF(C31="","",INDEX('Summary Ref Tables'!J34:J43,MATCH(C31,'Summary Ref Tables'!E34:E43,0))) | M31: =IF(K31<>"",K31*$E31,"") | N31: =IF(K31<>"",L31*$K31,"") | O31: =IF(K31<>"",K31*$D31*0.0005,"")
B32: Custom Input II | D32: =IF(C32="","",INDEX('Summary Ref Tables'!K34:K43,MATCH(C32,'Summary Ref Tables'!E34:E43,0))) | E32: =IF(C32="","",INDEX('Summary Ref Tables'!F34:F43,MATCH(C32,'Summary Ref Tables'!E34:E43,0))) | G32: =IF(C32="","",INDEX('Summary Ref Tables'!J34:J43,MATCH(C32,'Summary Ref Tables'!E34:E43,0))) | H32: =IF(F32<>"",F32*$E32,"") | I32: =IF(F32<>"",G32*$F32,"") | J32: =IF(F32<>"",F32*$D32*0.0005,"") | L32: =IF(C32="","",INDEX('Summary Ref Tables'!J34:J43,MATCH(C32,'Summary Ref Tables'!E34:E43,0))) | M32: =IF(K32<>"",K32*$E32,"") | N32: =IF(K32<>"",L32*$K32,"") | O32: =IF(K32<>"",K32*$D32*0.0005,"")
B33: Custom Input III | D33: =IF(C33="","",INDEX('Summary Ref Tables'!K34:K43,MATCH(C33,'Summary Ref Tables'!E34:E43,0))) | E33: =IF(C33="","",INDEX('Summary Ref Tables'!F34:F43,MATCH(C33,'Summary Ref Tables'!E34:E43,0))) | G33: =IF(C33="","",INDEX('Summary Ref Tables'!J34:J43,MATCH(C33,'Summary Ref Tables'!E34:E43,0))) | H33: =IF(F33<>"",F33*$E33,"") | I33: =IF(F33<>"",G33*$F33,"") | J33: =IF(F33<>"",F33*$D33*0.0005,"") | L33: =IF(C33="","",INDEX('Summary Ref Tables'!J34:J43,MATCH(C33,'Summary Ref Tables'!E34:E43,0))) | M33: =IF(K33<>"",K33*$E33,"") | N33: =IF(K33<>"",L33*$K33,"") | O33: =IF(K33<>"",K33*$D33*0.0005,"")
F34: Current Annual Energy & Emissions: | H34: =SUM(H15:H33) -> 1.2746279e+08 | I34: =SUM(I15:I33) -> 9.3806006e+08 | J34: =SUM(J15:J33) -> 2420273.5 | K34: Hypothetical Annual Energy & Emissions: | M34: =SUM(M15:M33) -> 86410986 | N34: =SUM(N15:N33) -> 9.846778e+08 | O34: =SUM(O15:O33) -> -8677866.8
F35: or equivalently: | H35: =AnnualUsePhaseEnergy_Current*0.000001 -> 127.46279 | J35: =AnnualUsePhaseEmissions_Current*0.000001 -> 2.4202735 | K35: or equivalently: | M35: =AnnualUsePhaseEnergy_Hypoth*0.000001 -> 86.410986 | O35: =AnnualUsePhaseEmissions_Hypothetical*0.000001 -> -8.6778668
B36: *Link to reference data tab
B38: References, Notes, and Assumptions
B40: List key references and assumptions used to prepare the data provided in this sheet. Add as many rows as needed. | C40: IHP Calculations: https://www.energy.gov/sites/prod/files/2014/05/f15/heatpump.pdf
B46: Calculations
B47: Use this section for project-specific calculations and detailed references supporting the data above. Add as many rows as needed.
B48: Commercial Benchmark Electricity Usage via Evaporative Cooling Units
B49: 4 fans at 50 hp each operator to cool this water, so to estimate electricity required:
B50: 100 hp * 4 fans * 0.7457 kW/hp * 24 hours per dayday = 3579.36 kWh from grid used to cool 2 million gallons of wastewater each day
B51: 3579.36 kWh * 3412.14 BTU / kWh * 1 MMBTU/1000000 BTUs = | D51: 12.213 | E51: MMBTUs per day in electricity consumption for grid to cool 2 million gallons of wastewater a day
B53: Waste Heat Recovery Unit/Heat Pump Calculations for Electricity Usage Required and Heating Captured/Delivered by Heat Pump
B54: Source: | C54: https://www.energy.gov/sites/prod/files/2014/05/f15/heatpump.pdf
C55: **see page 12
B57: Approach Temp: | C57: 20 | D57: dF | E57: **assumed value based on DOE source above
B59: Working Fluid
B60: Tin: | C60: =C65-C57 -> 80 | D60: dF
B61: Tout: | C61: =175+C57 -> 195 | D61: dF | E61: **assume heat generated would replace steam heat required for sterilization/hot water at 175 dF
B63: Heat Source (i.e. WWTR stream)
B64: Tin: | C64: 105 | D64: dF
B65: Tout: | C65: 100 | D65: dF
B67: Ideal CHP: | C67: =(C61+C61*2)/(C61-C60) -> 5.0869565 | D67: **not sure where "460" came from on page 12 of source, but assuming its tout of working fluid x 2
B69: Assume actual COPHP is 75% ideal, so operating COPHP is below:
B70: Efficiency: | C70: 0.75
B71: COPHP: | C71: =C67*C70 -> 3.8152174
B73: Now we can calculate Win, which is the electrical input required to operate the heat pump
B77: Qin represents the heat deliverd to the heat pump from the wastewater (i.e. heat delivered represents cooling of wastewater from 105 to 100 dF).
B87: WWTR Flow: | C87: 2 | D87: million gallons per day
B88: Density of Water: | C88: 8.34 | D88: lbs/gallon
B89: C (specific heat) of water: | C89: 1 | D89: BTU/lb-F
B90: Qin = | C90: =C87*1000000*C88*C89*(C64-C65) -> 83400000 | D90: BTU/day
B91: Qin = | C91: =C90/1000000 -> 83.4 | D91: MMBTU/day
B93: Win = | C93: =C91/(C71-1) -> 29.62471 | D93: MMBTU/day
B94: Now we can calculate Qout, which is the heat delivered by the heat pump (which offsets steam demand produced through combustion of natural gas in a boiler)
B97: Heat Transfer Inefficiency: | C97: 0.54 | D97: %
B98: Qout= | C98: =(C91+C93)*C97 -> 61.033344 | D98: MMBTU/day
B100: Return to Home Page

Sheet CapEx
B1: U.S. DEPARTMENT OF ENERGY (DOE) OFFICE OF ENERGY EFFICIENCY AND RENEWABLE ENERGY (EERE)
B2: Techno-economic, Energy & Carbon Heuristic Tool for Early Stage Technologies (TECHTEST)
D3: Return to Planning Page
B4: Manufacturing Capital Expenses (CapEx)
B6: In this tab, you will estimate capital expenses (CapEx - i.e., non-recurring / one-time costs) for the new technology (left) and for the commercial benchmark (right). The reference production volumes (as entered into the Reference Volume tab) are shown below for each technology. If you need to change these, edit in the Reference Volume tab.
C8: New Technology (at Industrial Scale) | K8: Commercial Benchmark
B9: Technology Name | C9: =New_Technology -> Waste Heat Recovery (Heat Pump) | J9: Technology Name | K9: =Commercial_Benchmark -> Evaporative Condenser
B10: Specific Product | C10: =New_Technology_Apps -> Cooled Waste Water | J10: Specific Product | K10: =Benchmark_Apps -> Cooled Waste Water
B11: Reference Volume | C11: =Ref_Volume -> 2 | D11: =Ref_Volume_Unit -> Million Gallons | J11: Reference Volume | K11: =Ref_Volume_Benchmark -> 2 | L11: =Ref_Volume_Unit -> Million Gallons
C12: (ref volume) | D12: (units) | K12: (ref volume) | L12: (units)
B14: For the new technology, indicate the annual production volume for the industrial scale facility that will be used to assess capital expenses (i.e., one-time expenses). This facility size will also be used as a basis to assess operating expenses in the next tab. | J14: For the commercial benchmark, indicate the annual production volume for the industrial scale facility that will be used to assess capital expenses (i.e., one-time expenses). This facility size will also be used as a basis to assess operating expenses in the next tab.
B15: Annual Facility Production of End-use Product: | C15: =C11*365 -> 730 | D15: =Ref_Volume_Unit -> Million Gallons | E15: =IF(EndUse_Product<>""," of "&EndUse_Product&" per year","of (end-use product not yet defined) per year") -> of Cooled Waste Water per year | J15: Annual Facility Production of End-use Product: | K15: =K11*365 -> 730 | L15: =Ref_Volume_Unit -> Million Gallons | M15: =IF(EndUse_Product<>""," of "&EndUse_Product&" per year","of (end-use product not yet defined) per year") -> of Cooled Waste Water per year
C16: (facility product.) | D16: (units) | K16: (facility product.) | L16: (units)
B18: For both the new technology (left) and commercial benchmark (right), list capital expenses in the tables below. Consider a facility of the size and typical production volume indicated above. For each item listed, name the expense and estimate the purchase price and expected lifetime (for depreciation purposes). For financed equipment, calculate and include the cost of financing. Use the spaces below to list references, assumptions and calculations. Do not include recoverable "working capital" expenses. A default value of 5% of CapEx annually is assumed for annual equipment and facility maintenance. This value may be adjusted if desired.
B20: New Technology - Capital Expenses (CapEx) | J20: Commerical Benchmark Technology - Capital Expenses (CapEx)
B21: CapEx Category | C21: Examples | D21: Capital Expense Items (descriptions) | E21: Purchase Price ($) | F21: Expected Equipment Lifetime (years) | G21: Annual Capital Cost for Facility ($) | H21: Capital Cost for Functional Unit ($) | J21: CapEx Category | K21: Examples | L21: Capital Expense Items (descriptions) | M21: Purchase Price ($) | N21: Expected Equipment Lifetime (years) | O21: Annual Capital Cost for Facility ($) | P21: Scaled Annual Capital Cost ($) (Adjusted to new tech. facility size) | Q21: Capital Cost for Functional Unit ($)
B22: Process Equipment | C22: furnaces, reactors | D22: Waste Heat Recovery System (e.g. IHP) | E22: =B67 -> 254305.6 | F22: 10 | G22: =IF(E22<>"",E22/F22,"") -> 25430.56 | H22: =IF(E22<>"",IF(Facility_Production_NewTech<>"",G22*Ref_Volume/Facility_Production_NewTech,"No Facility Data"),"") -> 69.672767 | J22: Process Equipment | K22: furnaces, reactors | L22: Evaporative condensers (4 total) | M22: =B61*4 -> 1000000 | N22: 25 | O22: =IF(M22<>"",M22/N22,"") -> 40000 | P22: =IF(O22<>"", O22*(Facility_Production_NewTech/Facility_Production_Benchmark)*(Ref_Volume_Benchmark/Ref_Volume),"") -> 40000 | Q22: =IF(N22<>"",IF(Facility_Production_Benchmark<>"",O22*Ref_Volume_Benchmark/Facility_Production_Benchmark,"No Facility Data"),"") -> 109.58904
G23: =IF(E23<>"",E23/F23,"") | H23: =IF(E23<>"",IF(Facility_Production_NewTech<>"",G23*Ref_Volume/Facility_Production_NewTech,"No Facility Data"),"") | O23: =IF(M23<>"",M23/N23,"") | P23: =IF(O23<>"", O23*(Facility_Production_NewTech/Facility_Production_Benchmark)*(Ref_Volume_Benchmark/Ref_Volume),"") | Q23: =IF(N23<>"",IF(Facility_Production_Benchmark<>"",O23*Ref_Volume_Benchmark/Facility_Production_Benchmark,"No Facility Data"),"")
G24: =IF(E24<>"",E24/F24,"") | H24: =IF(E24<>"",IF(Facility_Production_NewTech<>"",G24*Ref_Volume/Facility_Production_NewTech,"No Facility Data"),"") | O24: =IF(M24<>"",M24/N24,"") | P24: =IF(O24<>"", O24*(Facility_Production_NewTech/Facility_Production_Benchmark)*(Ref_Volume_Benchmark/Ref_Volume),"") | Q24: =IF(N24<>"",IF(Facility_Production_Benchmark<>"",O24*Ref_Volume_Benchmark/Facility_Production_Benchmark,"No Facility Data"),"")
G25: =IF(E25<>"",E25/F25,"") | H25: =IF(E25<>"",IF(Facility_Production_NewTech<>"",G25*Ref_Volume/Facility_Production_NewTech,"No Facility Data"),"") | O25: =IF(M25<>"",M25/N25,"") | P25: =IF(O25<>"", O25*(Facility_Production_NewTech/Facility_Production_Benchmark)*(Ref_Volume_Benchmark/Ref_Volume),"") | Q25: =IF(N25<>"",IF(Facility_Production_Benchmark<>"",O25*Ref_Volume_Benchmark/Facility_Production_Benchmark,"No Facility Data"),"")
F26: Process Equipment Total: | G26: =IF(SUM(G22:G25)>0,SUM(G22:G25),"") -> 25430.56 | H26: =IF(SUM(H22:H25)>0,SUM(H22:H25),"") -> 69.672767 | N26: Process Equipment Total: | O26: =IF(SUM(O22:O25)>0,SUM(O22:O25),"") -> 40000 | P26: =IF(SUM(P22:P25)>0,SUM(P22:P25),"") -> 40000 | Q26: =IF(SUM(Q22:Q25)>0,SUM(Q22:Q25),"") -> 109.58904
B27: Non-process Equipment | C27: piping, control systems, power equipment | D27: Piping | E27: 50000 | F27: 35 | G27: =IF(E27<>"",E27/F27,"") -> 1428.5714 | H27: =IF(E27<>"",IF(Facility_Production_NewTech<>"",G27*Ref_Volume/Facility_Production_NewTech,"No Facility Data"),"") -> 3.9138943 | J27: Nonprocess Equipment | K27: piping, control systems, power equipment. | L27: Piping | M27: 50000 | N27: 35 | O27: =IF(M27<>"",M27/N27,"") -> 1428.5714 | P27: =IF(O27<>"", O27*(Facility_Production_NewTech/Facility_Production_Benchmark)*(Ref_Volume_Benchmark/Ref_Volume),"") -> 1428.5714 | Q27: =IF(N27<>"",IF(Facility_Production_Benchmark<>"",O27*Ref_Volume_Benchmark/Facility_Production_Benchmark,"No Facility Data"),"") -> 3.9138943
G28: =IF(E28<>"",E28/F28,"") | H28: =IF(E28<>"",IF(Facility_Production_NewTech<>"",G28*Ref_Volume/Facility_Production_NewTech,"No Facility Data"),"") | O28: =IF(M28<>"",M28/N28,"") | P28: =IF(O28<>"", O28*(Facility_Production_NewTech/Facility_Production_Benchmark)*(Ref_Volume_Benchmark/Ref_Volume),"") | Q28: =IF(N28<>"",IF(Facility_Production_Benchmark<>"",O28*Ref_Volume_Benchmark/Facility_Production_Benchmark,"No Facility Data"),"")
G29: =IF(E29<>"",E29/F29,"") | H29: =IF(E29<>"",IF(Facility_Production_NewTech<>"",G29*Ref_Volume/Facility_Production_NewTech,"No Facility Data"),"") | O29: =IF(M29<>"",M29/N29,"") | P29: =IF(O29<>"", O29*(Facility_Production_NewTech/Facility_Production_Benchmark)*(Ref_Volume_Benchmark/Ref_Volume),"") | Q29: =IF(N29<>"",IF(Facility_Production_Benchmark<>"",O29*Ref_Volume_Benchmark/Facility_Production_Benchmark,"No Facility Data"),"")
G30: =IF(E30<>"",E30/F30,"") | H30: =IF(E30<>"",IF(Facility_Production_NewTech<>"",G30*Ref_Volume/Facility_Production_NewTech,"No Facility Data"),"") | O30: =IF(M30<>"",M30/N30,"") | P30: =IF(O30<>"", O30*(Facility_Production_NewTech/Facility_Production_Benchmark)*(Ref_Volume_Benchmark/Ref_Volume),"") | Q30: =IF(N30<>"",IF(Facility_Production_Benchmark<>"",O30*Ref_Volume_Benchmark/Facility_Production_Benchmark,"No Facility Data"),"")
F31: Non-Process Equipment Total: | G31: =IF(SUM(G27:G30)>0,SUM(G27:G30),"") -> 1428.5714 | H31: =IF(SUM(H27:H30)>0,SUM(H27:H30),"") -> 3.9138943 | N31: Non-Process Equipment Total: | O31: =IF(SUM(O27:O30)>0,SUM(O27:O30),"") -> 1428.5714 | P31: =IF(SUM(P27:P30)>0,SUM(P27:P30),"") -> 1428.5714 | Q31: =IF(SUM(Q27:Q30)>0,SUM(Q27:Q30),"") -> 3.9138943
B32: Engineering & Construction | C32: engineering, design, procurement, construction | D32: Design | E32: 10000 | F32: 15 | G32: =IF(E32<>"",E32/F32,"") -> 666.66667 | H32: =IF(E32<>"",IF(Facility_Production_NewTech<>"",G32*Ref_Volume/Facility_Production_NewTech,"No Facility Data"),"") -> 1.826484 | J32: Engineering & Construction | K32: engineering, design, procurement, construction | L32: Design | M32: 10000 | N32: 25 | O32: =IF(M32<>"",M32/N32,"") -> 400 | P32: =IF(O32<>"", O32*(Facility_Production_NewTech/Facility_Production_Benchmark)*(Ref_Volume_Benchmark/Ref_Volume),"") -> 400 | Q32: =IF(N32<>"",IF(Facility_Production_Benchmark<>"",O32*Ref_Volume_Benchmark/Facility_Production_Benchmark,"No Facility Data"),"") -> 1.0958904
D33: Installation | E33: =E22*0.5 -> 127152.8 | F33: 15 | G33: =IF(E33<>"",E33/F33,"") -> 8476.8533 | H33: =IF(E33<>"",IF(Facility_Production_NewTech<>"",G33*Ref_Volume/Facility_Production_NewTech,"No Facility Data"),"") -> 23.224256 | L33: Installation | M33: =M22*0.5 -> 500000 | N33: 25 | O33: =IF(M33<>"",M33/N33,"") -> 20000 | P33: =IF(O33<>"", O33*(Facility_Production_NewTech/Facility_Production_Benchmark)*(Ref_Volume_Benchmark/Ref_Volume),"") -> 20000 | Q33: =IF(N33<>"",IF(Facility_Production_Benchmark<>"",O33*Ref_Volume_Benchmark/Facility_Production_Benchmark,"No Facility Data"),"") -> 54.794521
G34: =IF(E34<>"",E34/F34,"") | H34: =IF(E34<>"",IF(Facility_Production_NewTech<>"",G34*Ref_Volume/Facility_Production_NewTech,"No Facility Data"),"") | O34: =IF(M34<>"",M34/N34,"") | P34: =IF(O34<>"", O34*(Facility_Production_NewTech/Facility_Production_Benchmark)*(Ref_Volume_Benchmark/Ref_Volume),"") | Q34: =IF(N34<>"",IF(Facility_Production_Benchmark<>"",O34*Ref_Volume_Benchmark/Facility_Production_Benchmark,"No Facility Data"),"")
G35: =IF(E35<>"",E35/F35,"") | H35: =IF(E35<>"",IF(Facility_Production_NewTech<>"",G35*Ref_Volume/Facility_Production_NewTech,"No Facility Data"),"") | O35: =IF(M35<>"",M35/N35,"") | P35: =IF(O35<>"", O35*(Facility_Production_NewTech/Facility_Production_Benchmark)*(Ref_Volume_Benchmark/Ref_Volume),"") | Q35: =IF(N35<>"",IF(Facility_Production_Benchmark<>"",O35*Ref_Volume_Benchmark/Facility_Production_Benchmark,"No Facility Data"),"")
F36: Engineering & Construction Total: | G36: =IF(SUM(G32:G35)>0,SUM(G32:G35),"") -> 9143.5199 | H36: =IF(SUM(H32:H35)>0,SUM(H32:H35),"") -> 25.05074 | N36: Engineering & Construction Total: | O36: =IF(SUM(O32:O35)>0,SUM(O32:O35),"") -> 20400 | P36: =IF(SUM(P32:P35)>0,SUM(P32:P35),"") -> 20400 | Q36: =IF(SUM(Q32:Q35)>0,SUM(Q32:Q35),"") -> 55.890411
B37: Other CapEx | C37: land, commissioning, contingency | G37: =IF(E37<>"",E37/F37,"") | H37: =IF(E37<>"",IF(Facility_Production_NewTech<>"",G37*Ref_Volume/Facility_Production_NewTech,"No Facility Data"),"") | J37: Other CapEx | K37: land, commissioning, contingency, spare parts. | O37: =IF(M37<>"",M37/N37,"") | P37: =IF(O37<>"", O37*(Facility_Production_NewTech/Facility_Production_Benchmark)*(Ref_Volume_Benchmark/Ref_Volume),"") | Q37: =IF(N37<>"",IF(Facility_Production_Benchmark<>"",O37*Ref_Volume_Benchmark/Facility_Production_Benchmark,"No Facility Data"),"")
G38: =IF(E38<>"",E38/F38,"") | H38: =IF(E38<>"",IF(Facility_Production_NewTech<>"",G38*Ref_Volume/Facility_Production_NewTech,"No Facility Data"),"") | O38: =IF(M38<>"",M38/N38,"") | P38: =IF(O38<>"", O38*(Facility_Production_NewTech/Facility_Production_Benchmark)*(Ref_Volume_Benchmark/Ref_Volume),"") | Q38: =IF(N38<>"",IF(Facility_Production_Benchmark<>"",O38*Ref_Volume_Benchmark/Facility_Production_Benchmark,"No Facility Data"),"")
G39: =IF(E39<>"",E39/F39,"") | H39: =IF(E39<>"",IF(Facility_Production_NewTech<>"",G39*Ref_Volume/Facility_Production_NewTech,"No Facility Data"),"") | O39: =IF(M39<>"",M39/N39,"") | P39: =IF(O39<>"", O39*(Facility_Production_NewTech/Facility_Production_Benchmark)*(Ref_Volume_Benchmark/Ref_Volume),"") | Q39: =IF(N39<>"",IF(Facility_Production_Benchmark<>"",O39*Ref_Volume_Benchmark/Facility_Production_Benchmark,"No Facility Data"),"")
G40: =IF(E40<>"",E40/F40,"") | H40: =IF(E40<>"",IF(Facility_Production_NewTech<>"",G40*Ref_Volume/Facility_Production_NewTech,"No Facility Data"),"") | O40: =IF(M40<>"",M40/N40,"") | P40: =IF(O40<>"", O40*(Facility_Production_NewTech/Facility_Production_Benchmark)*(Ref_Volume_Benchmark/Ref_Volume),"") | Q40: =IF(N40<>"",IF(Facility_Production_Benchmark<>"",O40*Ref_Volume_Benchmark/Facility_Production_Benchmark,"No Facility Data"),"")
F41: Other CapEx Total: | G41: =IF(SUM(G37:G40)>0,SUM(G37:G40),"") | H41: =IF(SUM(H37:H40)>0,SUM(H37:H40),"") | N41: Other CapEx Total: | O41: =IF(SUM(O37:O40)>0,SUM(O37:O40),"") | P41: =IF(SUM(P37:P40)>0,SUM(P37:P40),"") | Q41: =IF(SUM(Q37:Q40)>0,SUM(Q37:Q40),"")
F42: Total Capital Expense: | G42: =SUM(AnnualProcessCapEx_NewTech,AnnualNonProcessCapEx_NewTech,AnnualConstructionCapEx_NewTech,AnnualOtherCapEx_NewTech) -> 36002.651 | H42: =SUM(RefProcessCapEx_NewTech,RefNonProcessCapEx_NewTech,RefConstructionCapEx_NewTech,RefOtherCapEx_NewTech) -> 98.637401 | N42: Total Capital Expense: | O42: =SUM(AnnualProcessCapEx_Benchmark,AnnualNonProcessCapEx_Benchmark,AnnualConstructionCapEx_Benchmark,AnnualOtherCapEx_Benchmark) -> 61828.571 | P42: =SUM(ScaledProcessCapEx_Benchmark,ScaledNonProcessCapEx_Benchmark,ScaledConstructionCapEx_Benchmark,ScaledOtherCapEx_Benchmark) -> 61828.571 | Q42: =SUM(RefProcessCapEx_Benchmark,RefNonProcessCapEx_Benchmark,RefConstructionCapEx_Benchmark,RefOtherCapEx_Benchmark) -> 169.39335
F43: Annual Capital Equipment/Facility Maintenance (typical value 5%): | G43: 0.05 | H43: =G43 -> 0.05 | N43: Annual Capital Equipment/Facility Maintenance (typical value 5%): | O43: 0.05 | P43: =O43 -> 0.05 | Q43: =EquipMaintenanceRate_Benchmark -> 0.05
F44: Total Capital Expense, Including Maintenance: | G44: =AnnualCapEx_NewTech*(1+G43) -> 37802.784 | H44: =RefCapEx_NewTech*(1+H43) -> 103.56927 | N44: Total Capital Expense, Including Maintenance: | O44: =AnnualCapEx_Benchmark*(1+O43) -> 64920 | P44: =ScaledCapEx_Benchmark*(1+P43) -> 64920 | Q44: =RefCapEx_Benchmark*(1+Q43) -> 177.86301
G45: per | H45: per | O45: per | P45: per | Q45: per
G46: =TEXT(Facility_Production_NewTech,"#,##0")&" "&Ref_Volume_Unit -> 730 Million Gallons | H46: =TEXT(Ref_Volume,"#,##0")&" "&Ref_Volume_Unit -> 2 Million Gallons | O46: =TEXT(Facility_Production_Benchmark,"#,##0")&" "&Ref_Volume_Unit -> 730 Million Gallons | P46: =TEXT(Facility_Production_NewTech*Ref_Volume_Benchmark/Ref_Volume,"#,##0")&" "&Ref_Volume_Unit -> 730 Million Gallons | Q46: =TEXT(Ref_Volume_Benchmark,"#,##0")&" "&Ref_Volume_Unit -> 2 Million Gallons
G47: (Annual Facility Production) | H47: (Reference Volume) | O47: (Annual Facility Production) | P47: (Scaled Facility Production, New Tech Equivalent) | Q47: (Reference Volume)
B49: References, Notes, and Assumptions
B51: List key references and assumptions used to prepare the data provided in this sheet. Add as many rows as needed. | C51: Average heat pump life expectancy: https://glascohvac.com/heating/heat-pumps/long-heat-pump-last/#:~:text=Heat%20pumps%20normally%20last%20an,your%20heat%20pump%20is%20maintenance.
C52: Assumed steel piping used: source notes 20-50 year life expectancy, so chose 35 years as an in-between (https://abbottsplumbing.com/plumbing-replacement/how-long-do-pipes-last/#:~:text=They%20still%20last%20a%20pretty,drain%20lines%20will%20last%20indefinitely.)
C53: **for "Engineering & Construction" sections, I'm not sure if an expected lifetime applies, so I inputted the shortest expectancy from the equipment sections.
C54: For estimating heat pump costs: https://www.energy.gov/sites/prod/files/2014/05/f15/heatpump.pdf
B57: Calculations
B58: Use this section for project-specific calculations and detailed references supporting the data above. Add as many rows as needed.
B60: Costs of evaporative condensers vary based on size and application, but costs for evaproative condensers for the NH3 system priced around $250k.
B61: 250000 | C61: per condenser, 4 condensers total
B63: Per source (https://www.energy.gov/sites/prod/files/2014/05/f15/heatpump.pdf), "heat-pump systems range from" $50-200k per MMBTU of heat delivered (assuming on a per hour basis)
B64: ='Use Phase Energy'!C98 -> 61.033344 | C64: MMBTUs of heat delivered per day
B65: =B64/24 -> 2.543056 | C65: MMBTUs per hour of heat delivered
B66: 100000 | C66: assumed price per MMBTU based on defined range above
B67: =B65*B66 -> 254305.6 | C67: cost of heat pump system
B69: *assume install costs are 50% of equipment costs
B70: *assume piping and engineering design costs are the same for both scenarios
B79: Return to Home Page

Sheet OpEx
B1: U.S. DEPARTMENT OF ENERGY (DOE) OFFICE OF ENERGY EFFICIENCY AND RENEWABLE ENERGY (EERE)
B2: Techno-economic, Energy & Carbon Heuristic Tool for Early Stage Technologies (TECHTEST)
D3: Return to Planning Page
B4: Manufacturing Operating Expenses (OpEx)
B6: In this tab, you will estimate operating expenses (OpEx - i.e., recurring costs) for the new technology (left) and for the commercial benchmark (right). Operating expenses include labor, materials, energy, and other recurring costs. Materials and energy costs were calculated in prior tabs and data are reproduced here for convenience (entries may be edited directly in the Raw Materials and Manufacturing Energy tabs if edits are needed). You will enter data only for labor and (optional) other recurring costs in the blue cells of this tab. In estimates, consider the annual costs for a facility of the size indicated in the CapEx tab. The reference production volumes (as entered into the Reference Volume tab) and facility production volumes (as entered into the CapEx tab) are shown below for each technology.
C8: New Technology (at Industrial Scale) | J8: Commercial Benchmark
B9: Technology Name | C9: =New_Technology -> Waste Heat Recovery (Heat Pump) | I9: Technology Name | J9: =Commercial_Benchmark -> Evaporative Condenser
B10: Specific Product | C10: =New_Technology_Apps -> Cooled Waste Water | I10: Specific Product | J10: =Benchmark_Apps -> Cooled Waste Water
B11: Reference Production Volume | C11: =Ref_Volume -> 2 | D11: =Ref_Volume_Unit -> Million Gallons | I11: Reference Volume | J11: =Ref_Volume_Benchmark -> 2 | K11: =Ref_Volume_Unit -> Million Gallons
B12: Annual Facility Production Volume | C12: =Facility_Production_NewTech -> 730 | D12: =Ref_Volume_Unit -> Million Gallons | I12: Annual Facility Production Volume | J12: =Facility_Production_Benchmark -> 730 | K12: =Ref_Volume_Unit -> Million Gallons
C13: (volume) | D13: (units) | J13: (volume) | K13: (units)
B15: Direct Labor Costs
B16: Estimate annual direct (operating) labor costs in the blue cells below, considering a facility of the size and annual production indicated in the CapEx tab. By default, annual costs are calculated from the number of full-time-equivalent (FTE) employees and annual pay rates. If data are available as a total annual labor cost instead, data may be entered directly in the "Labor Cost ($) (per year)" column, over-writing the default formulas. Do not include administrative labor in this section. The default percentage for fringe benefits and general overhead is 72% (considered a typical value) but this can be overwritten if needed.
B17: If labor costs are unknown, rules-of-thumb based estimation methods may be used. See the tab linked below for rules of thumb (and a calculator that will aid you in completing this section).
B18: Calculation Tool: Labor Cost Estimation Rules-of-Thumb
B20: New Technology - Direct Labor Costs | I20: Commercial Benchmark - Direct Labor Costs
C21: Number of FTE Employees | D21: Average Annual Pay Rate | E21: Employee Fringe Benefits & General Overhead Rate (%) | F21: Annual Labor Cost ($) (for facility of size shown above) | G21: Labor Cost ($) (per reference volume) | J21: Number of FTE Employees | K21: Average Annual Pay Rate | L21: Employee Fringe Benefits & General Overhead Rate (%) | M21: Annual Labor Cost ($) (for facility of size shown above) | N21: Scaled Annual Labor Cost ($) (adjusted to new tech. facility size) | O21: Labor Cost ($) (per reference volume)
B22: Direct Labor (equipment operators & supervisors) | C22: =D124 -> 0.0096153846 | D22: 75000 | E22: 0.72 | F22: =IF(C22<>"",C22*D22*(1+E22),"") -> 1240.3846 | G22: =IF(F22<>"",IF(Facility_Production_NewTech<>"",F22*Ref_Volume/Facility_Production_NewTech,""),"") -> 3.398314 | I22: Direct Labor (equipment operators & supervisors) | J22: =E125 -> 0.033173077 | K22: 75000 | L22: 0.72 | M22: =IF(J22<>"",J22*K22*(1+L22),"") -> 4279.3269 | N22: =IF(M22<>"",M22*(Facility_Production_NewTech/Facility_Production_Benchmark)*(Ref_Volume_Benchmark/Ref_Volume),"") -> 4279.3269 | O22: =IF(M22<>"",IF(Facility_Production_NewTech<>"",N22*Ref_Volume/Facility_Production_NewTech,""),"") -> 11.724183
E23: Total Operating Labor Cost: | F23: =SUM(F22) -> 1240.3846 | G23: =SUM(G22) -> 3.398314 | L23: Total Operating Labor Cost: | M23: =SUM(M22) -> 4279.3269 | N23: =SUM(N22) -> 4279.3269 | O23: =SUM(O22) -> 11.724183
F24: per | G24: per | M24: per | N24: per | O24: per
F25: =TEXT(Facility_Production_NewTech,"#,##0")&" "&Ref_Volume_Unit -> 730 Million Gallons | G25: =TEXT(Ref_Volume,"#,##0")&" "&Ref_Volume_Unit -> 2 Million Gallons | M25: =TEXT(Facility_Production_Benchmark,"#,##0")&" "&Ref_Volume_Unit -> 730 Million Gallons | N25: =TEXT(Facility_Production_NewTech*Ref_Volume_Benchmark/Ref_Volume,"#,##0")&" "&Ref_Volume_Unit -> 730 Million Gallons | O25: =TEXT(Ref_Volume_Benchmark,"#,##0")&" "&Ref_Volume_Unit -> 2 Million Gallons
F26: (Annual Facility Production) | G26: (Reference Volume) | M26: (Annual Facility Production) | N26: (Scaled Facility Production, New Tech Equivalent) | O26: (Reference Volume)
B28: Raw Materials Costs
B29: Materials costs entered into the "Raw Materials" tab are reprinted here for convenience. If data need to be adjusted, make changes in the Raw Materials tab.
B31: New Technology - Raw Material Inputs | I31: Commercial Benchmark - Raw Material Inputs
B32: Material Inputs (list) | C32: Amount of Material (to produce reference volume) | D32: unit | E32: Specific Cost ($/unit) (for this material) | F32: Annual Materials Cost ($) (per year) | G32: Materials Cost ($) (per reference volume) | I32: Material Inputs (list) | J32: Amount of Material (to produce reference volume) | K32: unit | L32: Specific Cost ($/unit) (for this material) | M32: Annual Materials Cost ($) (per year) | N32: Scaled Annual Materials Cost ($) (adjusted to new tech. facility size) | O32: Materials Cost ($) (per reference volume)
B33: =IF('Raw Materials'!B18<>"",'Raw Materials'!B18,"") -> Lubrication | C33: =IF('Raw Materials'!C18<>"",'Raw Materials'!C18,"") -> 2.34 | D33: =IF('Raw Materials'!D18<>"",'Raw Materials'!D18,"") -> kg | E33: =IF('Raw Materials'!G18<>"",'Raw Materials'!G18,"") -> 6 | F33: =IF(G33<>"",IF(Ref_Volume>0,G33*Facility_Production_NewTech/Ref_Volume,""),"") -> 5124.6 | G33: =IF('Raw Materials'!J18<>"",'Raw Materials'!J18,"") -> 14.04 | I33: =IF('Raw Materials'!L18<>"",'Raw Materials'!L18,"") -> City water supply to evaporative condensers | J33: =IF('Raw Materials'!M18<>"",'Raw Materials'!M18,"") -> 17010.309 | K33: =IF('Raw Materials'!N18<>"",'Raw Materials'!N18,"") -> gallons | L33: =IF('Raw Materials'!Q18<>"",'Raw Materials'!Q18,"") -> 0.002 | M33: =IF(O33<>"",O33*Facility_Production_Benchmark/Ref_Volume_Benchmark,"") -> 12417.526 | N33: =IF(M33<>"",M33*(Facility_Production_NewTech/Facility_Production_Benchmark)*(Ref_Volume_Benchmark/Ref_Volume),"") -> 12417.526 | O33: =IF('Raw Materials'!T18<>"",'Raw Materials'!T18,"") -> 34.020619
B34: =IF('Raw Materials'!B19<>"",'Raw Materials'!B19,"") -> Copper | C34: =IF('Raw Materials'!C19<>"",'Raw Materials'!C19,"") -> 0.36730356 | D34: =IF('Raw Materials'!D19<>"",'Raw Materials'!D19,"") -> kg | E34: =IF('Raw Materials'!G19<>"",'Raw Materials'!G19,"") | F34: =IF(G34<>"",IF(Ref_Volume>0,G34*Facility_Production_NewTech/Ref_Volume,""),"") -> 0 | G34: =IF('Raw Materials'!J19<>"",'Raw Materials'!J19,"") -> 0 | I34: =IF('Raw Materials'!L19<>"",'Raw Materials'!L19,"") -> Biocide chemical additon to cooling loop for micro mitigation | J34: =IF('Raw Materials'!M19<>"",'Raw Materials'!M19,"") -> 3.322326 | K34: =IF('Raw Materials'!N19<>"",'Raw Materials'!N19,"") -> gallons | L34: =IF('Raw Materials'!Q19<>"",'Raw Materials'!Q19,"") -> 19.090909 | M34: =IF(O34<>"",O34*Facility_Production_Benchmark/Ref_Volume_Benchmark,"") -> 23150.572 | N34: =IF(M34<>"",M34*(Facility_Production_NewTech/Facility_Production_Benchmark)*(Ref_Volume_Benchmark/Ref_Volume),"") -> 23150.572 | O34: =IF('Raw Materials'!T19<>"",'Raw Materials'!T19,"") -> 63.426224
B35: =IF('Raw Materials'!B20<>"",'Raw Materials'!B20,"") -> Elastomer | C35: =IF('Raw Materials'!C20<>"",'Raw Materials'!C20,"") -> 0.16056986 | D35: =IF('Raw Materials'!D20<>"",'Raw Materials'!D20,"") -> kg | E35: =IF('Raw Materials'!G20<>"",'Raw Materials'!G20,"") | F35: =IF(G35<>"",IF(Ref_Volume>0,G35*Facility_Production_NewTech/Ref_Volume,""),"") -> 0 | G35: =IF('Raw Materials'!J20<>"",'Raw Materials'!J20,"") -> 0 | I35: =IF('Raw Materials'!L20<>"",'Raw Materials'!L20,"") -> Steel low Alloy | J35: =IF('Raw Materials'!M20<>"",'Raw Materials'!M20,"") -> 0.31749784 | K35: =IF('Raw Materials'!N20<>"",'Raw Materials'!N20,"") -> kg | L35: =IF('Raw Materials'!Q20<>"",'Raw Materials'!Q20,"") | M35: =IF(O35<>"",O35*Facility_Production_Benchmark/Ref_Volume_Benchmark,"") -> 0 | N35: =IF(M35<>"",M35*(Facility_Production_NewTech/Facility_Production_Benchmark)*(Ref_Volume_Benchmark/Ref_Volume),"") -> 0 | O35: =IF('Raw Materials'!T20<>"",'Raw Materials'!T20,"") -> 0
B36: =IF('Raw Materials'!B21<>"",'Raw Materials'!B21,"") -> HDPE | C36: =IF('Raw Materials'!C21<>"",'Raw Materials'!C21,"") -> 0.0050178082 | D36: =IF('Raw Materials'!D21<>"",'Raw Materials'!D21,"") -> kg | E36: =IF('Raw Materials'!G21<>"",'Raw Materials'!G21,"") | F36: =IF(G36<>"",IF(Ref_Volume>0,G36*Facility_Production_NewTech/Ref_Volume,""),"") -> 0 | G36: =IF('Raw Materials'!J21<>"",'Raw Materials'!J21,"") -> 0 | I36: =IF('Raw Materials'!L21<>"",'Raw Materials'!L21,"") -> Stainless Steel | J36: =IF('Raw Materials'!M21<>"",'Raw Materials'!M21,"") -> 0.34946467 | K36: =IF('Raw Materials'!N21<>"",'Raw Materials'!N21,"") -> kg | L36: =IF('Raw Materials'!Q21<>"",'Raw Materials'!Q21,"") | M36: =IF(O36<>"",O36*Facility_Production_Benchmark/Ref_Volume_Benchmark,"") -> 0 | N36: =IF(M36<>"",M36*(Facility_Production_NewTech/Facility_Production_Benchmark)*(Ref_Volume_Benchmark/Ref_Volume),"") -> 0 | O36: =IF('Raw Materials'!T21<>"",'Raw Materials'!T21,"") -> 0
B37: =IF('Raw Materials'!B22<>"",'Raw Materials'!B22,"") -> Low alloyed steel | C37: =IF('Raw Materials'!C22<>"",'Raw Materials'!C22,"") -> 0.32113973 | D37: =IF('Raw Materials'!D22<>"",'Raw Materials'!D22,"") -> kg | E37: =IF('Raw Materials'!G22<>"",'Raw Materials'!G22,"") | F37: =IF(G37<>"",IF(Ref_Volume>0,G37*Facility_Production_NewTech/Ref_Volume,""),"") -> 0 | G37: =IF('Raw Materials'!J22<>"",'Raw Materials'!J22,"") -> 0 | I37: =IF('Raw Materials'!L22<>"",'Raw Materials'!L22,"") -> Aluminium | J37: =IF('Raw Materials'!M22<>"",'Raw Materials'!M22,"") -> 0.39875732 | K37: =IF('Raw Materials'!N22<>"",'Raw Materials'!N22,"") -> kg | L37: =IF('Raw Materials'!Q22<>"",'Raw Materials'!Q22,"") | M37: =IF(O37<>"",O37*Facility_Production_Benchmark/Ref_Volume_Benchmark,"") -> 0 | N37: =IF(M37<>"",M37*(Facility_Production_NewTech/Facility_Production_Benchmark)*(Ref_Volume_Benchmark/Ref_Volume),"") -> 0 | O37: =IF('Raw Materials'!T22<>"",'Raw Materials'!T22,"") -> 0
B38: =IF('Raw Materials'!B23<>"",'Raw Materials'!B23,"") -> Lubricating Oil (Manufacturing) | C38: =IF('Raw Materials'!C23<>"",'Raw Materials'!C23,"") -> 0.027096164 | D38: =IF('Raw Materials'!D23<>"",'Raw Materials'!D23,"") -> kg | E38: =IF('Raw Materials'!G23<>"",'Raw Materials'!G23,"") | F38: =IF(G38<>"",IF(Ref_Volume>0,G38*Facility_Production_NewTech/Ref_Volume,""),"") -> 0 | G38: =IF('Raw Materials'!J23<>"",'Raw Materials'!J23,"") -> 0 | I38: =IF('Raw Materials'!L23<>"",'Raw Materials'!L23,"") -> Bricks | J38: =IF('Raw Materials'!M23<>"",'Raw Materials'!M23,"") -> 0.34626548 | K38: =IF('Raw Materials'!N23<>"",'Raw Materials'!N23,"") -> Bricks | L38: =IF('Raw Materials'!Q23<>"",'Raw Materials'!Q23,"") | M38: =IF(O38<>"",O38*Facility_Production_Benchmark/Ref_Volume_Benchmark,"") -> 0 | N38: =IF(M38<>"",M38*(Facility_Production_NewTech/Facility_Production_Benchmark)*(Ref_Volume_Benchmark/Ref_Volume),"") -> 0 | O38: =IF('Raw Materials'!T23<>"",'Raw Materials'!T23,"") -> 0
B39: =IF('Raw Materials'!B24<>"",'Raw Materials'!B24,"") -> PVC | C39: =IF('Raw Materials'!C24<>"",'Raw Materials'!C24,"") -> 0.016056986 | D39: =IF('Raw Materials'!D24<>"",'Raw Materials'!D24,"") -> kg | E39: =IF('Raw Materials'!G24<>"",'Raw Materials'!G24,"") | F39: =IF(G39<>"",IF(Ref_Volume>0,G39*Facility_Production_NewTech/Ref_Volume,""),"") -> 0 | G39: =IF('Raw Materials'!J24<>"",'Raw Materials'!J24,"") -> 0 | I39: =IF('Raw Materials'!L24<>"",'Raw Materials'!L24,"") -> Methacrylate | J39: =IF('Raw Materials'!M24<>"",'Raw Materials'!M24,"") -> 0.28817819 | K39: =IF('Raw Materials'!N24<>"",'Raw Materials'!N24,"") -> kg | L39: =IF('Raw Materials'!Q24<>"",'Raw Materials'!Q24,"") | M39: =IF(O39<>"",O39*Facility_Production_Benchmark/Ref_Volume_Benchmark,"") -> 0 | N39: =IF(M39<>"",M39*(Facility_Production_NewTech/Facility_Production_Benchmark)*(Ref_Volume_Benchmark/Ref_Volume),"") -> 0 | O39: =IF('Raw Materials'!T24<>"",'Raw Materials'!T24,"") -> 0
B40: =IF('Raw Materials'!B25<>"",'Raw Materials'!B25,"") -> Reinforced Steel | C40: =IF('Raw Materials'!C25<>"",'Raw Materials'!C25,"") -> 1.3046301 | D40: =IF('Raw Materials'!D25<>"",'Raw Materials'!D25,"") -> kg | E40: =IF('Raw Materials'!G25<>"",'Raw Materials'!G25,"") | F40: =IF(G40<>"",IF(Ref_Volume>0,G40*Facility_Production_NewTech/Ref_Volume,""),"") -> 0 | G40: =IF('Raw Materials'!J25<>"",'Raw Materials'!J25,"") -> 0 | I40: =IF('Raw Materials'!L25<>"",'Raw Materials'!L25,"") -> Polyurethane | J40: =IF('Raw Materials'!M25<>"",'Raw Materials'!M25,"") -> 0.025744085 | K40: =IF('Raw Materials'!N25<>"",'Raw Materials'!N25,"") -> kg | L40: =IF('Raw Materials'!Q25<>"",'Raw Materials'!Q25,"") | M40: =IF(O40<>"",O40*Facility_Production_Benchmark/Ref_Volume_Benchmark,"") -> 0 | N40: =IF(M40<>"",M40*(Facility_Production_NewTech/Facility_Production_Benchmark)*(Ref_Volume_Benchmark/Ref_Volume),"") -> 0 | O40: =IF('Raw Materials'!T25<>"",'Raw Materials'!T25,"") -> 0
B41: =IF('Raw Materials'!B26<>"",'Raw Materials'!B26,"") | C41: =IF('Raw Materials'!C26<>"",'Raw Materials'!C26,"") | D41: =IF('Raw Materials'!D26<>"",'Raw Materials'!D26,"") | E41: =IF('Raw Materials'!G26<>"",'Raw Materials'!G26,"") | F41: =IF(G41<>"",IF(Ref_Volume>0,G41*Facility_Production_NewTech/Ref_Volume,""),"") | G41: =IF('Raw Materials'!J26<>"",'Raw Materials'!J26,"") | I41: =IF('Raw Materials'!L26<>"",'Raw Materials'!L26,"") -> PVC | J41: =IF('Raw Materials'!M26<>"",'Raw Materials'!M26,"") -> 0.49518472 | K41: =IF('Raw Materials'!N26<>"",'Raw Materials'!N26,"") -> kg | L41: =IF('Raw Materials'!Q26<>"",'Raw Materials'!Q26,"") | M41: =IF(O41<>"",O41*Facility_Production_Benchmark/Ref_Volume_Benchmark,"") -> 0 | N41: =IF(M41<>"",M41*(Facility_Production_NewTech/Facility_Production_Benchmark)*(Ref_Volume_Benchmark/Ref_Volume),"") -> 0 | O41: =IF('Raw Materials'!T26<>"",'Raw Materials'!T26,"") -> 0
E42: Total Materials Cost: | F42: =SUM(F33:F41) -> 5124.6 | G42: =SUM(G33:G41) -> 14.04 | L42: Total Materials Cost: | M42: =SUM(M33:M41) -> 35568.098 | N42: =SUM(N33:N41) -> 35568.098 | O42: =SUM(O33:O41) -> 97.446843
F43: per | G43: per | M43: per | N43: per | O43: per
F44: =TEXT(Facility_Production_NewTech,"#,##0")&" "&Ref_Volume_Unit -> 730 Million Gallons | G44: =TEXT(Ref_Volume,"#,##0")&" "&Ref_Volume_Unit -> 2 Million Gallons | M44: =TEXT(Facility_Production_Benchmark,"#,##0")&" "&Ref_Volume_Unit -> 730 Million Gallons | N44: =TEXT(Facility_Production_NewTech*Ref_Volume_Benchmark/Ref_Volume,"#,##0")&" "&Ref_Volume_Unit -> 730 Million Gallons | O44: =TEXT(Ref_Volume_Benchmark,"#,##0")&" "&Ref_Volume_Unit -> 2 Million Gallons
F45: (Annual Facility Production) | G45: (Reference Volume) | M45: (Annual Facility Production) | N45: (Scaled Facility Production, New Tech Equivalent) | O45: (Reference Volume)
B47: Energy Costs
B48: Energy costs entered into the "Manufacturing Energy" tab are reprinted here for convenience. If data need to be adjusted, make changes in the Manufacturing Energy tab.
B50: New Technology - Energy Cost Data | I50: Commercial Benchmark - Energy Cost Data
B51: Energy Source | C51: Onsite Energy Consumption (MMBtu) (to produce reference volume) | D51: unit | E51: Annual Energy Cost ($) | F51: Energy Cost ($) (per reference volume) | I51: Energy Source | J51: Onsite Energy Consumption (MMBtu) (to produce reference volume) | K51: unit | L51: Annual Energy Cost ($) | M51: Scaled Annual Energy Cost ($) (adjusted to new tech. facility size) | N51: Energy Cost ($) (per reference volume)
B52: Electricity | C52: ='Manufacturing Energy'!D17 -> 0.0048050532 | D52: MMBtu | E52: =IF(F52>0,F52*Facility_Production_NewTech/Ref_Volume,"") -> 36.906808 | F52: =SUM('Manufacturing Energy'!I17) -> 0.10111454 | I52: Electricity | J52: ='Manufacturing Energy'!N17 -> 0.37120338 | K52: MMBtu | L52: =IF(N52>0,N52*Facility_Production_Benchmark/Ref_Volume_Benchmark,"") -> 2851.1509 | M52: =IF(L52<>"",L52*(Facility_Production_NewTech/Facility_Production_Benchmark)*(Ref_Volume_Benchmark/Ref_Volume),"") -> 2851.1509 | N52: =SUM('Manufacturing Energy'!S17) -> 7.8113723
B53: Petroleum | C53: =SUM('Manufacturing Energy'!D18:D23) -> 0.01334737 | D53: MMBtu | E53: =IF(F53>0,F53*Facility_Production_NewTech/Ref_Volume,"") | F53: =SUM('Manufacturing Energy'!I18) -> 0 | I53: Petroleum | J53: =SUM('Manufacturing Energy'!N18:N23) -> 0.01334737 | K53: MMBtu | L53: =IF(N53>0,N53*Facility_Production_Benchmark/Ref_Volume_Benchmark,"") | M53: =IF(L53<>"",L53*(Facility_Production_NewTech/Facility_Production_Benchmark)*(Ref_Volume_Benchmark/Ref_Volume),"") | N53: =SUM('Manufacturing Energy'!S18) -> 0
B54: Coal | C54: =SUM('Manufacturing Energy'!D19:D23) -> 0.01334737 | D54: MMBtu | E54: =IF(F54>0,F54*Facility_Production_NewTech/Ref_Volume,"") | F54: =SUM('Manufacturing Energy'!I19) -> 0 | I54: Coal | J54: =SUM('Manufacturing Energy'!N19:N23) -> 0.01334737 | K54: MMBtu | L54: =IF(N54>0,N54*Facility_Production_Benchmark/Ref_Volume_Benchmark,"") | M54: =IF(L54<>"",L54*(Facility_Production_NewTech/Facility_Production_Benchmark)*(Ref_Volume_Benchmark/Ref_Volume),"") | N54: =SUM('Manufacturing Energy'!S19) -> 0
B55: Natural Gas | C55: =SUM('Manufacturing Energy'!D20) -> 0.01334737 | D55: MMBtu | E55: =IF(F55>0,F55*Facility_Production_NewTech/Ref_Volume,"") -> 28.227311 | F55: =SUM('Manufacturing Energy'!I20) -> 0.077335098 | I55: Natural Gas | J55: =SUM('Manufacturing Energy'!N20) -> 0.01334737 | K55: MMBtu | L55: =IF(N55>0,N55*Facility_Production_Benchmark/Ref_Volume_Benchmark,"") -> 28.227311 | M55: =IF(L55<>"",L55*(Facility_Production_NewTech/Facility_Production_Benchmark)*(Ref_Volume_Benchmark/Ref_Volume),"") -> 28.227311 | N55: =SUM('Manufacturing Energy'!S20) -> 0.077335098
B56: Renewable Sources | C56: =SUM('Manufacturing Energy'!D21:D26) -> 0 | D56: MMBtu | E56: =IF(F56>0,F56*Facility_Production_NewTech/Ref_Volume,"") | F56: =SUM('Manufacturing Energy'!I21) -> 0 | I56: Renewable Sources | J56: =SUM('Manufacturing Energy'!N21:N26) -> 0 | K56: MMBtu | L56: =IF(N56>0,N56*Facility_Production_Benchmark/Ref_Volume_Benchmark,"") | M56: =IF(L56<>"",L56*(Facility_Production_NewTech/Facility_Production_Benchmark)*(Ref_Volume_Benchmark/Ref_Volume),"") | N56: =SUM('Manufacturing Energy'!S21) -> 0
B57: Steam | C57: =SUM('Manufacturing Energy'!D22) -> 0 | D57: MMBtu | E57: =IF(F57>0,F57*Facility_Production_NewTech/Ref_Volume,"") | F57: =SUM('Manufacturing Energy'!I22) -> 0 | I57: Steam | J57: =SUM('Manufacturing Energy'!N22) -> 0 | K57: MMBtu | L57: =IF(N57>0,N57*Facility_Production_Benchmark/Ref_Volume_Benchmark,"") | M57: =IF(L57<>"",L57*(Facility_Production_NewTech/Facility_Production_Benchmark)*(Ref_Volume_Benchmark/Ref_Volume),"") | N57: =SUM('Manufacturing Energy'!S22) -> 0
B58: Custom Inputs | C58: =SUM('Manufacturing Energy'!D23:D25) -> 0 | D58: MMBtu | E58: =IF(F58>0,F58*Facility_Production_NewTech/Ref_Volume,"") | F58: =SUM('Manufacturing Energy'!I23:I25) -> 0 | I58: Custom Inputs | J58: =SUM('Manufacturing Energy'!K23) -> 0 | K58: MMBtu | L58: =IF(N58>0,N58*Facility_Production_Benchmark/Ref_Volume_Benchmark,"") | M58: =IF(L58<>"",L58*(Facility_Production_NewTech/Facility_Production_Benchmark)*(Ref_Volume_Benchmark/Ref_Volume),"") | N58: =SUM('Manufacturing Energy'!S22:S25) -> 0
D59: Total Energy Cost: | E59: =SUM(E52:E57) -> 65.134118 | F59: =SUM(F52:F57) -> 0.17844964 | K59: Total Energy Cost: | L59: =SUM(L52:L57) -> 2879.3782 | M59: =SUM(M52:M57) -> 2879.3782 | N59: =SUM(N52:N57) -> 7.8887074
E60: per | F60: per | L60: per | M60: per | N60: per
E61: =TEXT(Facility_Production_NewTech,"#,##0")&" "&Ref_Volume_Unit -> 730 Million Gallons | F61: =TEXT(Ref_Volume,"#,##0")&" "&Ref_Volume_Unit -> 2 Million Gallons | L61: =TEXT(Facility_Production_Benchmark,"#,##0")&" "&Ref_Volume_Unit -> 730 Million Gallons | M61: =TEXT(Facility_Production_NewTech*Ref_Volume_Benchmark/Ref_Volume,"#,##0")&" "&Ref_Volume_Unit -> 730 Million Gallons | N61: =TEXT(Ref_Volume_Benchmark,"#,##0")&" "&Ref_Volume_Unit -> 2 Million Gallons
E62: (Annual Facility Production) | F62: (Reference Volume) | L62: (Annual Facility Production) | M62: (Scaled Facility Production, New Tech Equivalent) | N62: (Reference Volume)
B64: Other Recurring Costs
B65: In this optional section, enter any other significant recurring costs (not listed in the Labor, Materials, or Energy categories above) in the table below. Estimate data on an annual basis, considering a facility of the size indicated earlier. Credits (e.g., refunds from tax incentives, money received from sale of secondary products or spent materials) may also be provided in this table as negative values, if applicable. Note on Overhead: most indirect costs such as supplies, property tax, and R&D are now excluded by default in TECHTEST. Accurate estimation of indirect costs for early-stage technologies can be challenging, and it would be unusual for these costs to drive major differences between the new technology and commercial benchmark. Including these costs generally does not significantly affect comparisons between technologies. However, if data are available, indirect costs may be included in this table for completeness. General overhead, employee fringe benefits, and facility/equipment maintenance costs are addressed elsewhere in TECHTEST (in the Labor and CapEx sections) and should not be duplicated here.
B67: New Technology - Other Recurring Costs | I67: Commercial Benchmark - Other Recurring Costs
B68: Recurring Cost (description) | F68: Annual Recurring Cost ($) | G68: Recurring Cost ($) (per reference volume) | I68: Recurring Cost (description) | M68: Annual Recurring Cost ($) | N68: Scaled Annual Other Recurring Cost ($) (adjusted to new tech. facility size) | O68: Recurring Cost ($) (per reference volume)
B69: Lubrication & Maintenance Services | F69: 5000 | G69: =IF(F69<>"",F69*Ref_Volume/Facility_Production_NewTech,"") -> 13.69863 | I69: Water treatment management for cooling water supplied to condensers | M69: =B107 -> 12000 | N69: =IF(M69<>"",M69*(Facility_Production_NewTech/Facility_Production_Benchmark)*(Ref_Volume_Benchmark/Ref_Volume),"") -> 12000 | O69: =IF(N69<>"",N69*Ref_Volume_Benchmark/Facility_Production_Benchmark,"") -> 32.876712
G70: =IF(F70<>"",F70*Ref_Volume/Facility_Production_NewTech,"") | N70: =IF(M70<>"",M70*(Facility_Production_NewTech/Facility_Production_Benchmark)*(Ref_Volume_Benchmark/Ref_Volume),"") | O70: =IF(N70<>"",N70*Ref_Volume_Benchmark/Facility_Production_Benchmark,"")
G71: =IF(F71<>"",F71*Ref_Volume/Facility_Production_NewTech,"") | N71: =IF(M71<>"",M71*(Facility_Production_NewTech/Facility_Production_Benchmark)*(Ref_Volume_Benchmark/Ref_Volume),"") | O71: =IF(N71<>"",N71*Ref_Volume_Benchmark/Facility_Production_Benchmark,"")
G72: =IF(F72<>"",F72*Ref_Volume/Facility_Production_NewTech,"") | N72: =IF(M72<>"",M72*(Facility_Production_NewTech/Facility_Production_Benchmark)*(Ref_Volume_Benchmark/Ref_Volume),"") | O72: =IF(N72<>"",N72*Ref_Volume_Benchmark/Facility_Production_Benchmark,"")
G73: =IF(F73<>"",F73*Ref_Volume/Facility_Production_NewTech,"") | N73: =IF(M73<>"",M73*(Facility_Production_NewTech/Facility_Production_Benchmark)*(Ref_Volume_Benchmark/Ref_Volume),"") | O73: =IF(N73<>"",N73*Ref_Volume_Benchmark/Facility_Production_Benchmark,"")
G74: =IF(F74<>"",F74*Ref_Volume/Facility_Production_NewTech,"") | N74: =IF(M74<>"",M74*(Facility_Production_NewTech/Facility_Production_Benchmark)*(Ref_Volume_Benchmark/Ref_Volume),"") | O74: =IF(N74<>"",N74*Ref_Volume_Benchmark/Facility_Production_Benchmark,"")
G75: =IF(F75<>"",F75*Ref_Volume/Facility_Production_NewTech,"") | N75: =IF(M75<>"",M75*(Facility_Production_NewTech/Facility_Production_Benchmark)*(Ref_Volume_Benchmark/Ref_Volume),"") | O75: =IF(N75<>"",N75*Ref_Volume_Benchmark/Facility_Production_Benchmark,"")
E76: Total Other Recurring Cost: | F76: =SUM(F69:F75) -> 5000 | G76: =SUM(G69:G75) -> 13.69863 | L76: Total Other Recurring Cost: | M76: =SUM(M69:M75) -> 12000 | N76: =SUM(N69:N75) -> 12000 | O76: =SUM(O69:O75) -> 32.876712
F77: per | G77: per | M77: per | N77: per | O77: per
F78: =TEXT(Facility_Production_NewTech,"#,##0")&" "&Ref_Volume_Unit -> 730 Million Gallons | G78: =TEXT(Ref_Volume,"#,##0")&" "&Ref_Volume_Unit -> 2 Million Gallons | M78: =TEXT(Facility_Production_Benchmark,"#,##0")&" "&Ref_Volume_Unit -> 730 Million Gallons | N78: =TEXT(Facility_Production_NewTech*Ref_Volume_Benchmark/Ref_Volume,"#,##0")&" "&Ref_Volume_Unit -> 730 Million Gallons | O78: =TEXT(Ref_Volume_Benchmark,"#,##0")&" "&Ref_Volume_Unit -> 2 Million Gallons
F79: (Annual Facility Production) | G79: (Reference Volume) | M79: (Annual Facility Production) | N79: (Scaled Facility Production, New Tech Equivalent) | O79: (Reference Volume)
B81: OpEx Summary
B82: Operating expenses listed above are summarized for each technology in the tables below.
D83: New Technology - OpEx Summary | K83: Commercial Benchmark - OpEx Summary
D84: =New_Technology -> Waste Heat Recovery (Heat Pump) | K84: =Commercial_Benchmark -> Evaporative Condenser
D85: OpEx Category | F85: Annual Recurring Cost ($) | G85: Recurring Cost ($) (per reference volume) | K85: OpEx Category | M85: Annual Recurring Cost ($) | N85: Scaled Annual Recurring Cost ($) (adjusted to new tech. facility size) | O85: Recurring Cost ($) (per reference volume)
D86: Direct Labor Cost | F86: =F23 -> 1240.3846 | G86: =G23 -> 3.398314 | K86: Direct Labor Costs | M86: =M23 -> 4279.3269 | N86: =N23 -> 4279.3269 | O86: =O23 -> 11.724183
D87: Raw Materials Cost | F87: =F42 -> 5124.6 | G87: =G42 -> 14.04 | K87: Raw Materials Costs | M87: =M42 -> 35568.098 | N87: =N42 -> 35568.098 | O87: =O42 -> 97.446843
D88: Energy Cost | F88: =E59 -> 65.134118 | G88: =F59 -> 0.17844964 | K88: Energy Costs | M88: =L59 -> 2879.3782 | N88: =M59 -> 2879.3782 | O88: =N59 -> 7.8887074
D89: Other Recurring Costs | F89: =F76 -> 5000 | G89: =G76 -> 13.69863 | K89: Other Recurring Costs | M89: =M76 -> 12000 | N89: =N76 -> 12000 | O89: =O76 -> 32.876712
D90: Total Operating Expense: | F90: =SUM(F86:F89) -> 11430.119 | G90: =SUM(G86:G89) -> 31.315394 | K90: Total Operating Expense: | M90: =SUM(M86:M89) -> 54726.803 | N90: =SUM(N86:N89) -> 54726.803 | O90: =SUM(O86:O89) -> 149.93645
F91: per | G91: per | M91: per | N91: per | O91: per
F92: =TEXT(Facility_Production_NewTech,"#,##0")&" "&Ref_Volume_Unit -> 730 Million Gallons | G92: =TEXT(Ref_Volume,"#,##0")&" "&Ref_Volume_Unit -> 2 Million Gallons | M92: =TEXT(Facility_Production_Benchmark,"#,##0")&" "&Ref_Volume_Unit -> 730 Million Gallons | N92: =TEXT(Facility_Production_NewTech*Ref_Volume_Benchmark/Ref_Volume,"#,##0")&" "&Ref_Volume_Unit -> 730 Million Gallons | O92: =TEXT(Ref_Volume_Benchmark,"#,##0")&" "&Ref_Volume_Unit -> 2 Million Gallons
F93: (Annual Facility Production) | G93: (Reference Volume) | M93: (Annual Facility Production) | N93: (Scaled Facility Production, New Tech Equivalent) | O93: (Reference Volume)
B95: References, Notes, and Assumptions
B97: List key references and assumptions used to prepare the data provided in this sheet. Add as many rows as needed. | C97: $20k per month for brewery water treatment services, so estimating wastewater treatment for cooling water loop to be 5% of these costs
C98: DOE Heat Pump Maintenance: https://www.energy.gov/energysaver/operating-and-maintaining-your-heat-pump
B103: Calculations
B104: Use this section for project-specific calculations and detailed references supporting the data above. Add as many rows as needed.
B105: 20000 | C105: per month in total brewery water/chemical treatment services.
B106: 0.05 | C106: estimation of wastewater chemical treatment % to total brewery water treatment costs
B107: =B105*B106*12 -> 12000 | C107: annual water treatment/chemical costs for evaproative coolers as part of benchmark technology
B113: Maintenance Hours Estimation
B115: Heat Pump Maintenance | I115: Evaporative Condenser Maintenance: | K115: 4 | L115: total units
B116: Activity | C116: Frequency (instances per year) | D116: Time to complete (days) | I116: Activity | J116: Frequency (instances per year) | K116: Time to complete (days)
B117: Replace filters | C117: 12 | D117: 0.5 | I117: Condenser Running Inspection | J117: 12 | K117: =1/8 -> 0.125
B118: Annual OH/Service (recommended by DOE) | C118: 1 | D118: 2 | I118: City Water and Biocide Pump Inspection | J118: 2 | K118: 0.125
C119: Total Annual Time: | D119: =SUM(D117:D118) -> 2.5 | E119: days | I119: Evaporative Condenser Annual OH | J119: 1 | K119: 2
J120: Total Annual Time: | K120: =K117*K115+K118+K119*K115 -> 8.625 | L120: days
B122: *assume an employee works | C122: 260 | D122: days in a calendar year
B124: # Employees Needed for Heat Pump Maintenance: | D124: =D119/C122 -> 0.0096153846
B125: # Employees Needed for Evaporative Condenser Maintenance: | E125: =K120/C122 -> 0.033173077
...

Sheet Unit Conversion Page
B1: U.S. DEPARTMENT OF ENERGY (DOE) OFFICE OF ENERGY EFFICIENCY AND RENEWABLE ENERGY (EERE)
B2: Techno-economic, Energy & Carbon Heuristic Tool for Early Stage Technologies (TECHTEST)
B3: Return to Planning Page
B4: This tab allows for simple conversion to the units used by TECHTEST. The "From" and "To" units can be chosen in the yellow cells on each converter. Each unit converter is independent, and both can be used in parallel.
F9: Conversion Factor: | O9: Conversion Factor:
F10: {=_xlfn.SWITCH(B9,'Dropdown Menu Options'!D75,'Dropdown Menu Options'!D76,'Dropdown Menu Options'!E75,'Dropdown Menu Options'!E76,'Dropdown Menu Options'!F75,'Dropdown Menu Options'!F76,'Dropdown Menu Options'!G75,'Dropdown Menu Options'!G76,'Dropdown Menu Options'!H75,'Dropdown Menu Options'!H76,'Dropdown Menu Options'!I75,'Dropdown Menu Options'!I76,'Dropdown Menu Options'!J75,'Dropdown Menu Options'!J76,'Dropdown Menu Options'!K75,'Dropdown Menu Options'!K76,'Dropdown Menu Options'!L75,'Dropdown Menu Options'!L76,'Dropdown Menu Options'!M75,'Dropdown Menu Options'!M76,"")} | O10: {=_xlfn.SWITCH(K9,'Dropdown Menu Options'!D75,'Dropdown Menu Options'!D76,'Dropdown Menu Options'!E75,'Dropdown Menu Options'!E76,'Dropdown Menu Options'!H75,'Dropdown Menu Options'!H76,'Dropdown Menu Options'!I75,'Dropdown Menu Options'!I76,'Dropdown Menu Options'!J75,'Dropdown Menu Options'!J76,'Dropdown Menu Options'!K75,'Dropdown Menu Options'!K76,'Dropdown Menu Options'!L75,'Dropdown Menu Options'!L76,'Dropdown Menu Options'!M75,'Dropdown Menu Options'!M76,"")}
B12: Input Original Values | F12: Converted Values | K12: Input Original Values | O12: Converted Values
E13: =IF(B13="","","=") | F13: =IF(B13="","",B13*F$10) | N13: =IF(K13="","","=") | O13: =IF(K13="","",K13*O$10)
E14: =IF(B14="","","=") | F14: =IF(B14="","",B14*F$10) | N14: =IF(K14="","","=") | O14: =IF(K14="","",K14*O$10)
E15: =IF(B15="","","=") | F15: =IF(B15="","",B15*F$10) | N15: =IF(K15="","","=") | O15: =IF(K15="","",K15*O$10)
E16: =IF(B16="","","=") | F16: =IF(B16="","",B16*F$10) | N16: =IF(K16="","","=") | O16: =IF(K16="","",K16*O$10)
E17: =IF(B17="","","=") | F17: =IF(B17="","",B17*F$10) | N17: =IF(K17="","","=") | O17: =IF(K17="","",K17*O$10)
E18: =IF(B18="","","=") | F18: =IF(B18="","",B18*F$10) | N18: =IF(K18="","","=") | O18: =IF(K18="","",K18*O$10)
E19: =IF(B19="","","=") | F19: =IF(B19="","",B19*F$10) | N19: =IF(K19="","","=") | O19: =IF(K19="","",K19*O$10)
E20: =IF(B20="","","=") | F20: =IF(B20="","",B20*F$10) | N20: =IF(K20="","","=") | O20: =IF(K20="","",K20*O$10)
E21: =IF(B21="","","=") | F21: =IF(B21="","",B21*F$10) | N21: =IF(K21="","","=") | O21: =IF(K21="","",K21*O$10)
E22: =IF(B22="","","=") | F22: =IF(B22="","",B22*F$10) | N22: =IF(K22="","","=") | O22: =IF(K22="","",K22*O$10)
E23: =IF(B23="","","=") | F23: =IF(B23="","",B23*F$10) | N23: =IF(K23="","","=") | O23: =IF(K23="","",K23*O$10)
E24: =IF(B24="","","=") | F24: =IF(B24="","",B24*F$10) | N24: =IF(K24="","","=") | O24: =IF(K24="","",K24*O$10)
... E34: =IF(B34="","","=") | F34: =IF(B34="","",B34*F$10) | N34: =IF(K34="","","=") | O34: =IF(K34="","",K34*O$10)
B35: Return to Home Page

Sheet Grid Mix Customization
B1: U.S. DEPARTMENT OF ENERGY (DOE) OFFICE OF ENERGY EFFICIENCY AND RENEWABLE ENERGY (EERE)
B2: Techno-economic, Energy & Carbon Heuristic Tool for Early Stage Technologies (TECHTEST)
D3: Return to Planning Page
B4: Grid Mix Customization
B5: On this page, you can customize the grid mix used in the calculation of electricity generation emissions in the TECHTEST tool. The specific Grid Mix is an estimation of the percentage of various energy sources used to create powerline electricity. The 2022 current US grid mix is the default. A Moderate and Net Zero scenario are also included, and can be selected using the ”Choose Grid Mix” dropdown menu.
U9: 2022 Default | V9: Custom | W9: Moderate | X9: Net Zero
B15: Choose Grid Mix (select from dropdown) | C15: 2022 Default | D15: =IF(C15=V9,"Input Custom values using the Custom Value Selector chart to the right --->", "") | I15: Custom Value Selector (Only use for selecting custom grid mix)
B17: Electricity Generation Technology | E17: Fraction of Total | F17: Life-Cycle Electricity generation emissions (lb CO2-eq/MMBtu electricity generated) based on IPCC data | G17: Default CO2-eq/MMBtu data | I17: Electricity Generation Technology | L17: Fraction of Total | M17: Life-Cycle Electricity generation emissions (lb CO2-eq/MMBtu electricity generated) based on IPCC data
B18: Electricity Generation Technologies | C18: Fossil Fuels | D18: Coal | E18: {=_xlfn.SWITCH($C$15,$U$9,'Summary Ref Tables'!G54,$V$9,L18,$W$9,'Summary Ref Tables'!G74,$X$9,'Summary Ref Tables'!G94)} -> 0.21870934 | F18: =IF(GridMix="Custom",M18,G18) -> 234.35729 | G18: 234.35729 | I18: Electricity Generation Technologies | J18: Fossil Fuels | K18: Coal | M18: 234.35729
D19: Petroleum | E19: {=_xlfn.SWITCH($C$15,$U$9,'Summary Ref Tables'!G55,$V$9,L19,$W$9,'Summary Ref Tables'!G75,$X$9,'Summary Ref Tables'!G95)} -> 0.0045708794 | F19: =IF(GridMix="Custom",M19,G19) -> 177.08289 | G19: 177.08289 | K19: Petroleum | M19: 177.08289
D20: Natural Gas | E20: {=_xlfn.SWITCH($C$15,$U$9,'Summary Ref Tables'!G56,$V$9,L20,$W$9,'Summary Ref Tables'!G76,$X$9,'Summary Ref Tables'!G96)} -> 0.38336008 | F20: =IF(GridMix="Custom",M20,G20) -> 130.61537 | G20: 130.61537 | K20: Natural Gas | M20: 130.61537
D21: Other Gases | E21: {=_xlfn.SWITCH($C$15,$U$9,'Summary Ref Tables'!G57,$V$9,L21,$W$9,'Summary Ref Tables'!G77,$X$9,'Summary Ref Tables'!G97)} -> 0.002745943 | F21: =IF(GridMix="Custom",M21,G21) -> 127.12637 | G21: 127.12637 | K21: Other Gases | M21: 127.12637
C22: Renewables | D22: Nuclear | E22: {=_xlfn.SWITCH($C$15,$U$9,'Summary Ref Tables'!G58,$V$9,L22,$W$9,'Summary Ref Tables'!G78,$X$9,'Summary Ref Tables'!G98)} -> 0.18937695 | F22: =IF(GridMix="Custom",M22,G22) -> 7.760718 | G22: 7.760718 | J22: Renewables | K22: Nuclear | M22: 7.760718
D23: Hydropower | E23: {=_xlfn.SWITCH($C$15,$U$9,'Summary Ref Tables'!G59,$V$9,L23,$W$9,'Summary Ref Tables'!G79,$X$9,'Summary Ref Tables'!G99)} -> 0.063330336 | F23: =IF(GridMix="Custom",M23,G23) -> 15.521436 | G23: 15.521436 | K23: Hydropower | M23: 15.521436
D24: Biomass - Wood | E24: {=_xlfn.SWITCH($C$15,$U$9,'Summary Ref Tables'!G60,$V$9,L24,$W$9,'Summary Ref Tables'!G80,$X$9,'Summary Ref Tables'!G100)} -> 0.0090460883 | F24: =IF(GridMix="Custom",M24,G24) -> 148.7471 | G24: 148.7471 | K24: Biomass - Wood | M24: 148.7471
D25: Biomass - Waste | E25: {=_xlfn.SWITCH($C$15,$U$9,'Summary Ref Tables'!G61,$V$9,L25,$W$9,'Summary Ref Tables'!G81,$X$9,'Summary Ref Tables'!G101)} -> 0.0045765299 | F25: =IF(GridMix="Custom",M25,G25) -> 148.7471 | G25: 148.7471 | K25: Biomass - Waste | M25: 148.7471
D26: Geothermal | E26: {=_xlfn.SWITCH($C$15,$U$9,'Summary Ref Tables'!G62,$V$9,L26,$W$9,'Summary Ref Tables'!G82,$X$9,'Summary Ref Tables'!G102)} -> 0.0039517768 | F26: =IF(GridMix="Custom",M26,G26) -> 24.575607 | G26: 24.575607 | K26: Geothermal | M26: 24.575607
D27: Solar | E27: {=_xlfn.SWITCH($C$15,$U$9,'Summary Ref Tables'!G63,$V$9,L27,$W$9,'Summary Ref Tables'!G83,$X$9,'Summary Ref Tables'!G103)} -> 0.027908981 | F27: =IF(GridMix="Custom",M27,G27) -> 31.042872 | G27: 31.042872 | K27: Solar | M27: 31.042872
D28: Wind | E28: {=_xlfn.SWITCH($C$15,$U$9,'Summary Ref Tables'!G64,$V$9,L28,$W$9,'Summary Ref Tables'!G84,$X$9,'Summary Ref Tables'!G104)} -> 0.092423088 | F28: =IF(GridMix="Custom",M28,G28) -> 7.1139915 | G28: 7.1139915 | K28: Wind | M28: 7.1139915
E29: =SUM(E18:E28) -> 1 | L29: =SUM(L18:L28) -> 0
E31: Weighted average emissions for U.S. electricity generation: | F31: =SUMPRODUCT(E18:E28,F18:F28) -> 108.58735 | L31: Weighted average emissions for U.S. electricity generation: | M31: =SUMPRODUCT(L18:L28,M18:M28) -> 0
B33: Return to Home Page

Sheet Summary Tables
B1: U.S. DEPARTMENT OF ENERGY (DOE) OFFICE OF ENERGY EFFICIENCY AND RENEWABLE ENERGY (EERE)
B2: Techno-economic, Energy & Carbon Heuristic Tool for Early Stage Technologies (TECHTEST)
B3: Results Summary Tables
B5: This worksheet auto-calculates. Do not enter data in this tab. After entering data into the data input tabs, results will appear in the green cells of the summary tables below automatically.
B6: Project Basics | C6: Project Title | D6: =IF(Project_Title="","",Project_Title) -> Waste Heat Recovery Cooling in Beverage Manufacturing
C7: Lead Organization | D7: =IF(Project_Lead="","",Project_Lead) -> Hypothetical Organization
C8: Collaborative Partner(s) | D8: =IF(Project_Collaborators="","",Project_Collaborators) -> Staff
C9: Principal Investigator | D9: =IF(Project_PI&Project_PI_Org="","",Project_PI&", "&Project_PI_Org) -> John Doe, Hypotentical National Laboratory
C10: AMO Technology Manager | D10: =IF(AMO_TM="","",AMO_TM) -> Jane Doe
C11: Project Timeline | D11: =IF(Project_Start="","",TEXT(Project_Start,"[$-en-US]mmmm yyyy;@")&" to "&TEXT(Project_End,"[$-en-US]mmmm yyyy;@")) -> January 2023 to January 2025
C12: Funding Mechanism | D12: =IF(Funding_Mech="","",Funding_Mech) -> R&D Project
H13: =IF(Project_Start<>"",IF(Project_Start<TODAY(),IF(Project_End+30>TODAY(),"Status: Project Underway","Status: Project Complete"),"Status: Future Project"),"") -> Status: Project Complete
B14: End-Use Market | C14: Market End-Use Product | D14: =EndUse_Product -> Cooled Waste Water
C15: Current Annual US Production | D15: =US_Annual_Production -> 7300000 | E15: =US_Annual_Production_Unit -> Million Gallons
C16: U.S. Production that Could be Replaced by New Technology | D16: =US_Annual_Production*H20 -> 7300000 | E16: =US_Annual_Production_Unit -> Million Gallons | F16: ="(assuming replacement of "&TEXT(H20,"0%")&" of the end-use market)" -> (assuming replacement of 100% of the end-use market)
C17: U.S. Potential Production using New Technology | D17: =IF(Ref_Volume_Benchmark>0,ReplaceableProduction*Ref_Volume/Ref_Volume_Benchmark,"") -> 7300000 | E17: =US_Annual_Production_Unit -> Million Gallons | F17: (based on substitution ratios for new product, if replacing benchmark product)
B19: Benchmarking | D19: Technology Definition(s) | E19: Product or Application | F19: Current Technology Status | G19: Current Estimated Market Share | H19: Potential Future Market Share
C20: New Technology (developed in this project) | D20: =IF(New_Technology="","",New_Technology) -> Waste Heat Recovery (Heat Pump) | E20: =IF(New_Technology_Apps="","",New_Technology_Apps) -> Cooled Waste Water | F20: =IF(NewTech_Status="","",NewTech_Status) -> Typical Technology | G20: =IF(CurrentMarketShare_NewTech="","",CurrentMarketShare_NewTech) -> 0 | H20: =IF(PotentialMarketShare_NewTech="","",PotentialMarketShare_NewTech) -> 1
C21: Commercial Benchmark (used in comparisons) | D21: =IF(Commercial_Benchmark="","",Commercial_Benchmark) -> Evaporative Condenser | E21: =IF(Benchmark_Apps="","",Benchmark_Apps) -> Cooled Waste Water | F21: =IF(Benchmark_Status="","",Benchmark_Status) -> Typical Technology | G21: =CurrentMarketShare_Benchmark -> 1 | H21: =IF(PotentialMarketShare_Benchmark="","",PotentialMarketShare_Benchmark) -> 0
C22: Other Competing Technologies (list) | D22: =IF(Other_Competing="","",Other_Competing) | E22: =IF(Other_Competing_Apps="","",Other_Competing_Apps) | F22: =IF(OtherTech_Status="","",OtherTech_Status) | G22: =IF(CurrentMarketShare_OtherTech="","",CurrentMarketShare_OtherTech) | H22: =IF(PotentialMarketShare_OtherTech="","",PotentialMarketShare_OtherTech)
B24: Manufacturing Cost Results
B26: Manufacturing Cost Comparison | G26: Manufacturing Cost Comparison | M26: Manufacturing Cost Comparison
B27: Based on Equivalent Reference Volume | D27: New Technology, at Industrial Scale | E27: Commercial Benchmark | G27: Based on Facility Size | I27: New Technology, at Industrial Scale | J27: Commercial Benchmark | K27: Commercial Benchmark Scaled to Size of New Technology Facility* | M27: Based on Overall Potential U.S. Market | O27: New Technology, at Industrial Scale | P27: Commercial Benchmark
C28: Technology Name | D28: =New_Technology -> Waste Heat Recovery (Heat Pump) | E28: =Commercial_Benchmark -> Evaporative Condenser | H28: Technology Name | I28: =New_Technology -> Waste Heat Recovery (Heat Pump) | J28: =Commercial_Benchmark -> Evaporative Condenser | K28: =Commercial_Benchmark -> Evaporative Condenser | N28: Technology Name | O28: =New_Technology -> Waste Heat Recovery (Heat Pump) | P28: =Commercial_Benchmark -> Evaporative Condenser
C29: Reference Volume | D29: =TEXT(Ref_Volume,"#,##0")&" "&Ref_Volume_Unit -> 2 Million Gallons | E29: =TEXT(Ref_Volume_Benchmark,"#,##0")&" "&Ref_Volume_Unit -> 2 Million Gallons | H29: Annual Facility Production | I29: =TEXT(Facility_Production_NewTech,"#,##0")&" "&Ref_Volume_Unit -> 730 Million Gallons | J29: =TEXT(Facility_Production_Benchmark,"#,##0")&" "&Ref_Volume_Unit -> 730 Million Gallons | K29: =IF(Ref_Volume>0,TEXT(Facility_Production_NewTech*Ref_Volume_Benchmark/Ref_Volume,"#,##0")&" "&Ref_Volume_Unit,"") -> 730 Million Gallons | N29: Annual U.S. Production Replaced* | O29: =TEXT(PotentialProduction,"#,##0")&" "&Ref_Volume_Unit -> 7,300,000 Million Gallons | P29: =TEXT(ReplaceableProduction,"#,##0")&" "&Ref_Volume_Unit -> 7,300,000 Million Gallons
D30: =" of "&EndUse_Product -> of Cooled Waste Water | E30: =" of "&EndUse_Product -> of Cooled Waste Water | I30: =" of "&EndUse_Product -> of Cooled Waste Water | J30: =" of "&EndUse_Product -> of Cooled Waste Water | K30: =" of "&EndUse_Product -> of Cooled Waste Water | O30: =" of "&EndUse_Product -> of Cooled Waste Water | P30: =" of "&EndUse_Product -> of Cooled Waste Water
D31: Manufacturing Cost ($) for Functional Unit | J31: Annual Manufacturing Cost ($) for Facility | O31: Manufacturing Cost ($) for Overall U.S. Market
B32: Capital Expenses (CapEx) | C32: Process Equipment | D32: =RefProcessCapEx_NewTech -> 69.672767 | E32: =RefProcessCapEx_Benchmark -> 109.58904 | G32: Capital Expenses (CapEx) | H32: Process Equipment | I32: =AnnualProcessCapEx_NewTech -> 25430.56 | J32: =AnnualProcessCapEx_Benchmark -> 40000 | K32: =ScaledProcessCapEx_Benchmark -> 40000 | M32: Capital Expenses (CapEx) | N32: Process Equipment | O32: =IF(D32<>"",IF(PotentialProduction<>"",PotentialProduction*D32/Ref_Volume,0),0) -> 2.543056e+08 | P32: =IF(E32<>"",IF(PotentialProduction<>"",PotentialProduction*E32/Ref_Volume,0),0) -> 400000000
C33: Non-process Equipment | D33: =RefNonProcessCapEx_NewTech -> 3.9138943 | E33: =RefNonProcessCapEx_Benchmark -> 3.9138943 | H33: Non-process Equipment | I33: =AnnualNonProcessCapEx_NewTech -> 1428.5714 | J33: =AnnualNonProcessCapEx_Benchmark -> 1428.5714 | K33: =ScaledNonProcessCapEx_Benchmark -> 1428.5714 | N33: Non-process Equipment | O33: =IF(D33<>"",PotentialProduction*D33/Ref_Volume,0) -> 14285714 | P33: =IF(E33<>"",PotentialProduction*E33/Ref_Volume,0) -> 14285714
C34: Engineering & Construction | D34: =RefConstructionCapEx_NewTech -> 25.05074 | E34: =RefConstructionCapEx_Benchmark -> 55.890411 | H34: Engineering & Construction | I34: =AnnualConstructionCapEx_NewTech -> 9143.5199 | J34: =AnnualConstructionCapEx_Benchmark -> 20400 | K34: =ScaledConstructionCapEx_Benchmark -> 20400 | N34: Engineering & Construction | O34: =IF(D34<>"",PotentialProduction*D34/Ref_Volume,0) -> 91435199 | P34: =IF(E34<>"",PotentialProduction*E34/Ref_Volume,0) -> 204000000
C35: Other Capital Expenses | D35: =RefOtherCapEx_NewTech | E35: =RefOtherCapEx_Benchmark | H35: Other Capital Expenses | I35: =AnnualOtherCapEx_NewTech | J35: =AnnualOtherCapEx_Benchmark | K35: =ScaledOtherCapEx_Benchmark | N35: Other Capital Expenses | O35: =IF(D35<>"",PotentialProduction*D35/Ref_Volume,0) -> 0 | P35: =IF(E35<>"",PotentialProduction*E35/Ref_Volume,0) -> 0
C36: Facility & Equipment Maintenance | D36: =EquipMaintenanceRate_NewTech*SUM(D32:D35) -> 4.93187 | E36: =EquipMaintenanceRate_Benchmark*SUM(E32:E35) -> 8.4696673 | H36: Facility & Equipment Maintenance | I36: =EquipMaintenanceRate_NewTech*SUM(I32:I35) -> 1800.1326 | J36: =EquipMaintenanceRate_Benchmark*SUM(J32:J35) -> 3091.4286 | K36: =EquipMaintenanceRate_Benchmark*SUM(K32:K35) -> 3091.4286 | N36: Facility & Equipment Maintenance | O36: =EquipMaintenanceRate_NewTech*SUM(O32:O35) -> 18001326 | P36: =EquipMaintenanceRate_Benchmark*SUM(P32:P35) -> 30914286
B37: Operating Expenses (OpEx) | C37: Raw Materials | D37: =RefMatCost_NewTech -> 14.04 | E37: =RefMatCost_Benchmark -> 97.446843 | G37: Operating Expenses (OpEx) | H37: Raw Materials | I37: =AnnualMatCost_NewTech -> 5124.6 | J37: =AnnualMatCost_Benchmark -> 35568.098 | K37: =ScaledMatCost_Benchmark -> 35568.098 | M37: Operating Expenses (OpEx) | N37: Raw Materials | O37: =IF(D37>0,PotentialProduction*D37/Ref_Volume,0) -> 51246000 | P37: =IF(E37>0,PotentialProduction*E37/Ref_Volume,0) -> 3.5568098e+08
C38: Energy | D38: =RefEnergyCost_NewTech -> 0.17844964 | E38: =RefEnergyCost_Benchmark -> 7.8887074 | H38: Energy | I38: =AnnualEnergyCost_NewTech -> 65.134118 | J38: =AnnualEnergyCost_Benchmark -> 2879.3782 | K38: =ScaledEnergyCost_Benchmark -> 2879.3782 | N38: Energy | O38: =IF(D38>0,PotentialProduction*D38/Ref_Volume,0) -> 651341.18 | P38: =IF(E38>0,PotentialProduction*E38/Ref_Volume,0) -> 28793782
C39: Direct Labor | D39: =RefLaborCost_NewTech -> 3.398314 | E39: =RefLaborCost_Benchmark -> 11.724183 | H39: Direct Labor | I39: =AnnualLaborCost_NewTech -> 1240.3846 | J39: =AnnualLaborCost_Benchmark -> 4279.3269 | K39: =ScaledLaborCost_Benchmark -> 4279.3269 | N39: Direct Labor | O39: =IF(D39>0,PotentialProduction*D39/Ref_Volume,0) -> 12403846 | P39: =IF(E39>0,PotentialProduction*E39/Ref_Volume,0) -> 42793269
C40: Other Recurring Costs | D40: =RefOtherRecurring_NewTech -> 13.69863 | E40: =RefOtherRecurring_Benchmark -> 32.876712 | H40: Other Recurring Costs | I40: =AnnualOtherRecurring_NewTech -> 5000 | J40: =AnnualOtherRecurring_Benchmark -> 12000 | K40: =ScaledOtherRecurring_Benchmark -> 12000 | N40: Other Recurring Costs | O40: =IF(D40>0,PotentialProduction*D40/Ref_Volume,0) -> 50000000 | P40: =IF(E40>0,PotentialProduction*E40/Ref_Volume,0) -> 1.2e+08
B41: Total Manufacturing Cost | C41: CapEx Subtotal | D41: =SUM(D32:D36)*(1+EquipMaintenanceRate_NewTech) -> 108.74773 | E41: =SUM(E32:E36)*(1+EquipMaintenanceRate_Benchmark) -> 186.75616 | G41: Total Manufacturing Cost | H41: CapEx Subtotal | I41: =SUM(I32:I36)*(1+EquipMaintenanceRate_NewTech) -> 39692.923 | J41: =SUM(J32:J36)*(1+EquipMaintenanceRate_Benchmark) -> 68166 | K41: =SUM(K32:K36)*(1+EquipMaintenanceRate_Benchmark) -> 68166 | M41: Total Manufacturing Cost | N41: CapEx Subtotal | O41: =SUM(O32:O36)*(1+EquipMaintenanceRate_NewTech) -> 3.9692923e+08 | P41: =SUM(P32:P36)*(1+EquipMaintenanceRate_Benchmark) -> 681660000
C42: OpEx Subtotal | D42: =SUM(D37:D40) -> 31.315394 | E42: =SUM(E37:E40) -> 149.93645 | H42: OpEx Subtotal | I42: =SUM(I37:I40) -> 11430.119 | J42: =SUM(J37:J40) -> 54726.803 | K42: =SUM(K37:K40) -> 54726.803 | N42: OpEx Subtotal | O42: =SUM(O37:O40) -> 1.1430119e+08 | P42: =SUM(P37:P40) -> 5.4726803e+08
C43: Total Cost (CapEx + OpEx) | D43: =SUM(D41:D42) -> 140.06313 | E43: =SUM(E41:E42) -> 336.69261 | H43: Total Cost (CapEx + OpEx) | I43: =SUM(I41:I42) -> 51123.042 | J43: =SUM(J41:J42) -> 122892.8 | K43: =SUM(K41:K42) -> 122892.8 | N43: Total Cost (CapEx + OpEx) | O43: =SUM(O41:O42) -> 5.1123042e+08 | P43: =SUM(P41:P42) -> 1.228928e+09
G44: * In this column, production volume is scaled to be equivalent to the facility production of the New Technology facility. | M44: * This is the potential market: the total U.S. production that could potentially be replaced by the new technology.
G45: This includes a scale factor for performance-equivalence (if the reference volume for the New Technology and Commercial Benchmark differ). | M45: The production volumes shown for the two technologies are equivalent on a performance basis ("apples to apples")
B46: If the new technology were immediately and fully deployed at its maximum U.S. market share (i.e. in the "overnight replacement" scenario), the annual potential cost savings for U.S. manufacturers is:
C47: =P43-O43 -> 7.1769761e+08 | D47: Annual Potential Cost Savings to U.S. Manufacturers
C48: ="("&TEXT(C47/P43,"0.0%") -> (58.4% | D48: cost savings for production replaced) | G48: =IF(C47<0,"Warning: Analysis is currently showing a cost increase for the new technology.","")
B50: Life Cycle Energy & Emissions Results
B52: Life Cycle Comparison | I52: Life Cycle Comparison
B53: Based on Equivalent Reference Volume | D53: New Technology | F53: Commercial Benchmark | I53: Based on Overall Potential U.S. Market | K53: New Technology | M53: Commercial Benchmark
B54: (Cradle to Gate) | C54: Technology Name | D54: =New_Technology -> Waste Heat Recovery (Heat Pump) | F54: =Commercial_Benchmark -> Evaporative Condenser | I54: (Cradle to Grave) | J54: Technology Name | K54: =New_Technology -> Waste Heat Recovery (Heat Pump) | M54: =Commercial_Benchmark -> Evaporative Condenser
C55: Reference Volume | D55: =TEXT(Ref_Volume,"#,##0")&" "&Ref_Volume_Unit -> 2 Million Gallons | F55: =TEXT(Ref_Volume_Benchmark,"#,##0")&" "&Ref_Volume_Unit -> 2 Million Gallons | J55: Production Volume | K55: =TEXT(PotentialProduction,"#,##0")&" "&Ref_Volume_Unit -> 7,300,000 Million Gallons | M55: =TEXT(ReplaceableProduction,"#,##0")&" "&Ref_Volume_Unit -> 7,300,000 Million Gallons
D56: =" of "&EndUse_Product -> of Cooled Waste Water | F56: =" of "&EndUse_Product -> of Cooled Waste Water | K56: =" of "&EndUse_Product -> of Cooled Waste Water | M56: =" of "&EndUse_Product -> of Cooled Waste Water
D57: Energy | E57: Emissions (100-yr GWP) | F57: Energy | G57: Emissions (100-yr GWP) | K57: Energy | L57: Emissions (100-yr GWP) | M57: Energy | N57: Emissions (100-yr GWP)
B58: Cradle-to-Gate | C58: Raw Materials | D58: =RefEmbodiedEnergy_NewTech -> 0.25303942 | E58: =RefEmbodiedEmissions_NewTech -> 15.275945 | F58: =RefEmbodiedEnergy_Benchmark -> 0.4596635 | G58: =RefEmbodiedEmissions_Benchmark -> 52.283311 | I58: Cradle-to-Gate Energy** | J58: Raw Materials | K58: =IF(D58>0,D58*0.000001*PotentialProduction/Ref_Volume,0) -> 0.92359389 | L58: =IF(E58>0,E58*(1/2000)*0.000001*PotentialProduction/Ref_Volume,0) -> 0.0278786 | M58: =IF(F58>0,F58*0.000001*PotentialProduction/Ref_Volume,0) -> 1.6777718 | N58: =IF(G58>0,G58*(1/2000)*0.000001*PotentialProduction/Ref_Volume,0) -> 0.095417043
C59: Manufacturing | D59: =RefManufEnergy_NewTech -> 0.027086726 | E59: =RefManufEmissions_NewTech+RefProcessEmissions_NewTech -> 66.19201 | F59: =RefManufEnergy_Benchmark -> 1.0747499 | G59: =RefManufEmissions_Benchmark+RefProcessEmissions_Benchmark -> 42.051355 | J59: Manufacturing | K59: =IF(D59>0,D59*0.000001*PotentialProduction/Ref_Volume,0) -> 0.098866551 | L59: =IF(E59>0,E59*(1/2000)*0.000001*PotentialProduction/Ref_Volume,0) -> 0.12080042 | M59: =IF(F59>0,F59*0.000001*PotentialProduction/Ref_Volume,0) -> 3.9228371 | N59: =IF(G59>0,G59*(1/2000)*0.000001*PotentialProduction/Ref_Volume,0) -> 0.076743723
B60: Total | C60: Cradle-to-Gate Total | D60: =SUM(D58:D59) -> 0.28012615 | E60: =SUM(E58:E59) -> 81.467955 | F60: =SUM(F58:F59) -> 1.5344134 | G60: =SUM(G58:G59) -> 94.334666 | I60: Gate-to-Grave*** | J60: Use Phase | K60: ='Use Phase Energy'!M35 -> 86.410986 | L60: ='Use Phase Energy'!O35 -> -8.6778668 | M60: ='Use Phase Energy'!H35 -> 127.46279 | N60: ='Use Phase Energy'!J35 -> 2.4202735
B61: * While cradle-to-grave energy is tied to a specific production volume, gate-to-grave energy (use phase) is tied to a scenario involving an overall "fleet" of products (produced using different technologies, in different years, etc.). In this analysis, use phase energy is computed only as an annual total and not in terms of the reference volume. | I61: Total Energy | J61: Cradle-to-Gate Subtotal | K61: =SUM(K58:K59) -> 1.0224604 | L61: =SUM(L58:L59) -> 0.14867902 | M61: =SUM(M58:M59) -> 5.6006088 | N61: =SUM(N58:N59) -> 0.17216077
J62: Gate-to-Grave Subtotal | K62: =SUM(K60) -> 86.410986 | L62: =SUM(L60) -> -8.6778668 | M62: =SUM(M60) -> 127.46279 | N62: =SUM(N60) -> 2.4202735
J63: Total Energy (Cradle-to-Grave) | K63: =SUM(K61:K62) -> 87.433446 | L63: =SUM(L61:L62) -> -8.5291878 | M63: =SUM(M61:M62) -> 133.0634 | N63: =SUM(N61:N62) -> 2.5924343
I64: ** Cradle-to-gate energy is computed in terms of the total annual U.S. production ("overnight replacement" scenario or current).
I65: ** Gate-to-grave energy is computed in terms of the overall fleet of products in use ("overnight replacement" scenario or current).
B67: If the new technology were immediately and fully deployed at its maximum U.S. market share (i.e. in the "overnight replacement" scenario), the annual potential life cycle energy & emissions impact for the U.S. market is:
C68: =M63-K63 -> 45.629951 | D68: Annual Potential U.S. Lifetime Energy Savings
C69: =IF(M63>0,"("&TEXT(C68/M63,"0.0%"),"(TBD") -> (34.3% | D69: energy savings in affected markets) | G69: =IF(C68<0,"Warning: Analysis is currently showing a life cycle energy increase for the new technology.","")
C71: =N63-L63 -> 11.121622 | D71: Annual Potential U.S. Emissions Reduction
C72: =IF(N63>0,"("&TEXT(C71/N63,"0.0%"),"(TBD") -> (429.0% | D72: emissions reduction in affected markets)
P73: For summary plots, see the next tab.
B74: Return to Home Page

Sheet Results Dashboard
B1: U.S. DEPARTMENT OF ENERGY (DOE) OFFICE OF ENERGY EFFICIENCY AND RENEWABLE ENERGY (EERE)
B2: Techno-economic, Energy & Carbon Heuristic Tool for Early Stage Technologies (TECHTEST) | W2: The data below are used in calculations. Do not delete or hide these columns!
B3: ="Results Summary Plots" -> Results Summary Plots | D3: Note 1: Results will populate as data entried are made in the tool. | L3: Results in charts below are in annual impact, some inputs have been scaled up from a per functional unit basis. | X3: Manufacturing Cost Comparison for Reference Volume
C4: Cradle-to-Gate Cost / Reference Volume | F4: Cradle-to-Gate Energy / Reference Volume | I4: Cradle-to-Gate Emissions / Reference Volume | L4: Cradle-to-Gate Cost / Entire U.S. Market | O4: Cradle-to-Grave Energy / Entire U.S. Market | R4: Cradle-to-Grave Emissions / Entire U.S. Market | X4: New Technology, Industrial Scale | Y4: Commercial Benchmark | Z4: New Technology, Industrial Scale | AA4: Commercial Benchmark
C5: Manufacturing Cost Comparison (for Reference Volume) | F5: Cradle-to-Gate Energy Comparison (for Reference Volume) | I5: Cradle-to-Gate Emissions Comparison (for Reference Volume) | L5: Manufacturing Cost Comparison (for Potential U.S. Market) | O5: Cradle-to-Grave Energy Comparison (for Potential U.S. Market) | R5: Cradle-to-Grave Emissions Comparison (for Potential U.S. Market) | X5: =New_Technology -> Waste Heat Recovery (Heat Pump) | Y5: =Commercial_Benchmark -> Evaporative Condenser | Z5: Label (if >2%) | AA5: Label (if >2%)
C6: New Technology (at Industrial Scale) | D6: Commercial Benchmark | F6: New Technology (at Industrial Scale) | G6: Commercial Benchmark | I6: New Technology (at Industrial Scale) | J6: Commercial Benchmark | L6: Hypothetical (Fully Deployed) | M6: Current (Pre-Deployment) | O6: Hypothetical (Fully Deployed) | P6: Current (Pre-Deployment) | R6: Hypothetical (Fully Deployed) | S6: Current (Pre-Deployment) | W6: CapEx Costs | X6: =RefCapEx_NewTech_withMaintenance -> 103.56927 | Y6: =RefCapEx_Benchmark_withMaintenance -> 177.86301 | Z6: =IF(X$11>0,IF((X6/X$11)>0.02,$W6&": "&TEXT(X6,"$#,##0"),""),"") -> CapEx Costs: $104 | AA6: =IF(Y$11>0,IF((Y6/Y$11)>0.02,$W6&": "&TEXT(Y6,"$#,##0"),""),"") -> CapEx Costs: $178
C7: ="Reference Volume:"&CHAR(10)&TEXT(Ref_Volume,"#,##0")&" "&Ref_Volume_Unit -> Reference Volume: 2 Million Gallons | D7: ="Equivalent Reference Volume:"&CHAR(10)&TEXT(Ref_Volume_Benchmark,"#,##0")&" "&Ref_Volume_Unit -> Equivalent Reference Volume: 2 Million Gallons | F7: ="Reference Volume:"&CHAR(10)&TEXT(Ref_Volume,"#,##0")&" "&Ref_Volume_Unit -> Reference Volume: 2 Million Gallons | G7: ="Equivalent Reference Volume:"&CHAR(10)&TEXT(Ref_Volume_Benchmark,"#,##0")&" "&Ref_Volume_Unit -> Equivalent Reference Volume: 2 Million Gallons | I7: ="Reference Volume:"&CHAR(10)&TEXT(Ref_Volume,"#,##0")&" "&Ref_Volume_Unit -> Reference Volume: 2 Million Gallons | J7: ="Equivalent Reference Volume:"&CHAR(10)&TEXT(Ref_Volume_Benchmark,"#,##0")&" "&Ref_Volume_Unit -> Equivalent Reference Volume: 2 Million Gallons | L7: ="Hypothetical Production:"&CHAR(10)&TEXT(PotentialProduction,"#,##0")&" "&Ref_Volume_Unit -> Hypothetical Production: 7,300,000 Million Gallons | M7: ="Replaced Production:"&CHAR(10)&TEXT(ReplaceableProduction,"#,##0")&" "&Ref_Volume_Unit -> Replaced Production: 7,300,000 Million Gallons | O7: ="Hypothetical Production:"&CHAR(10)&TEXT(PotentialProduction,"#,##0")&" "&Ref_Volume_Unit -> Hypothetical Production: 7,300,000 Million Gallons | P7: ="Replaced Production:"&CHAR(10)&TEXT(ReplaceableProduction,"#,##0")&" "&Ref_Volume_Unit -> Replaced Production: 7,300,000 Million Gallons | R7: ="Hypothetical Production:"&CHAR(10)&TEXT(PotentialProduction,"#,##0")&" "&Ref_Volume_Unit -> Hypothetical Production: 7,300,000 Million Gallons | S7: ="Replaced Production:"&CHAR(10)&TEXT(ReplaceableProduction,"#,##0")&" "&Ref_Volume_Unit -> Replaced Production: 7,300,000 Million Gallons | W7: Raw Materials Costs | X7: =RefMatCost_NewTech -> 14.04 | Y7: =RefMatCost_Benchmark -> 97.446843 | Z7: =IF(X$11>0,IF((X7/X$11)>0.02,$W7&": "&TEXT(X7,"$#,##0"),""),"") -> Raw Materials Costs: $14 | AA7: =IF(Y$11>0,IF((Y7/Y$11)>0.02,$W7&": "&TEXT(Y7,"$#,##0"),""),"") -> Raw Materials Costs: $97
C8: =X11 -> 134.88466 | D8: =Y11 -> 327.79946 | F8: =X28 -> 0.28012615 | G8: =Y28 -> 1.5344134 | I8: =X43 -> 81.467955 | J8: =Y43 -> 94.334666 | L8: =TEXT(X21/1000000,"$#,##0")&" million" -> $461 million | M8: =TEXT(Y21/1000000,"$#,##0")&" million" -> $1,109 million | O8: =X36 -> 87.433446 | P8: =Y36 -> 133.0634 | R8: =X50 -> -8.5291878 | S8: =Y50 -> 2.5924343 | W8: Energy Costs | X8: =RefEnergyCost_NewTech -> 0.17844964 | Y8: =RefEnergyCost_Benchmark -> 7.8887074 | Z8: =IF(X$11>0,IF((X8/X$11)>0.02,$W8&": "&TEXT(X8,"$#,##0"),""),"") | AA8: =IF(Y$11>0,IF((Y8/Y$11)>0.02,$W8&": "&TEXT(Y8,"$#,##0"),""),"") -> Energy Costs: $8
W9: Labor Costs | X9: =RefLaborCost_NewTech -> 3.398314 | Y9: =RefLaborCost_Benchmark -> 11.724183 | Z9: =IF(X$11>0,IF((X9/X$11)>0.02,$W9&": "&TEXT(X9,"$#,##0"),""),"") -> Labor Costs: $3 | AA9: =IF(Y$11>0,IF((Y9/Y$11)>0.02,$W9&": "&TEXT(Y9,"$#,##0"),""),"") -> Labor Costs: $12
W10: Other Costs | X10: =RefOtherRecurring_NewTech -> 13.69863 | Y10: =RefOtherRecurring_Benchmark -> 32.876712 | Z10: =IF(X$11>0,IF((X10/X$11)>0.02,$W10&": "&TEXT(X10,"$#,##0"),""),"") -> Other Costs: $14 | AA10: =IF(Y$11>0,IF((Y10/Y$11)>0.02,$W10&": "&TEXT(Y10,"$#,##0"),""),"") -> Other Costs: $33
W11: Total | X11: =SUM(X6:X10) -> 134.88466 | Y11: =SUM(Y6:Y10) -> 327.79946
X13: Manufacturing Cost Comparison for US Market
X14: New Technology, Industrial Scale | Y14: Commercial Benchmark | Z14: New Technology, Industrial Scale | AA14: Commercial Benchmark
X15: =New_Technology -> Waste Heat Recovery (Heat Pump) | Y15: =Commercial_Benchmark -> Evaporative Condenser | Z15: Label (if >2%) | AA15: Label (if >2%)
W16: CapEx Costs | X16: ='Summary Tables'!O41 -> 3.9692923e+08 | Y16: ='Summary Tables'!P41 -> 681660000 | Z16: =IF(X$21>0,IF((X16/X$21)>0.02,$W16&": "&TEXT(X16,"$#,##0"),""),"") -> CapEx Costs: $396,929,230 | AA16: =IF(Y$21>0,IF((Y16/Y$21)>0.02,$W16&": "&TEXT(Y16,"$#,##0"),""),"") -> CapEx Costs: $681,660,000
W17: Raw Materials Costs | X17: ='Summary Tables'!O37 -> 51246000 | Y17: ='Summary Tables'!P37 -> 3.5568098e+08 | Z17: =IF(X$21>0,IF((X17/X$21)>0.02,$W17&": "&TEXT(X17,"$#,##0"),""),"") -> Raw Materials Costs: $51,246,000 | AA17: =IF(Y$21>0,IF((Y17/Y$21)>0.02,$W17&": "&TEXT(Y17,"$#,##0"),""),"") -> Raw Materials Costs: $355,680,976
W18: Energy Costs | X18: ='Summary Tables'!O38 -> 651341.18 | Y18: ='Summary Tables'!P38 -> 28793782 | Z18: =IF(X$21>0,IF((X18/X$21)>0.02,$W18&": "&TEXT(X18,"$#,##0"),""),"") | AA18: =IF(Y$21>0,IF((Y18/Y$21)>0.02,$W18&": "&TEXT(Y18,"$#,##0"),""),"") -> Energy Costs: $28,793,782
W19: Labor Costs | X19: ='Summary Tables'!O39 -> 12403846 | Y19: ='Summary Tables'!P39 -> 42793269 | Z19: =IF(X$21>0,IF((X19/X$21)>0.02,$W19&": "&TEXT(X19,"$#,##0"),""),"") -> Labor Costs: $12,403,846 | AA19: =IF(Y$21>0,IF((Y19/Y$21)>0.02,$W19&": "&TEXT(Y19,"$#,##0"),""),"") -> Labor Costs: $42,793,269
W20: Other Costs | X20: ='Summary Tables'!O40 -> 50000000 | Y20: ='Summary Tables'!P40 -> 1.2e+08 | Z20: =IF(X$21>0,IF((X20/X$21)>0.02,$W20&": "&TEXT(X20,"$#,##0"),""),"") -> Other Costs: $50,000,000 | AA20: =IF(Y$21>0,IF((Y20/Y$21)>0.02,$W20&": "&TEXT(Y20,"$#,##0"),""),"") -> Other Costs: $120,000,000
W21: Total | X21: =SUM(X16:X19) -> 4.6123042e+08 | Y21: =SUM(Y16:Y19) -> 1.108928e+09
X23: Manufacturing Energy Comparison for Reference Volume
X24: New Technology, Industrial Scale | Y24: Commercial Benchmark | Z24: New Technology, Industrial Scale | AA24: Commercial Benchmark
X25: =New_Technology -> Waste Heat Recovery (Heat Pump) | Y25: =Commercial_Benchmark -> Evaporative Condenser | Z25: Label (if >2%) | AA25: Label (if >2%)
W26: Raw Materials Energy | X26: ='Summary Tables'!D58 -> 0.25303942 | Y26: ='Summary Tables'!F58 -> 0.4596635 | Z26: =IF(X$28>0,IF((X26/X$28)>0.02,$W26&": "&CHAR(10)&TEXT(X26,"#,##0.0")&" MMBtu",""),"") -> Raw Materials Energy: 0.3 MMBtu | AA26: =IF(Y$28>0,IF((Y26/Y$28)>0.02,$W26&": "&CHAR(10)&TEXT(Y26,"#,##0.0")&" MMBtu",""),"") -> Raw Materials Energy: 0.5 MMBtu
W27: Manufacturing Energy | X27: ='Summary Tables'!D59 -> 0.027086726 | Y27: ='Summary Tables'!F59 -> 1.0747499 | Z27: =IF(X$28>0,IF((X27/X$28)>0.02,$W27&": "&CHAR(10)&TEXT(X27,"#,##0.0")&" MMBtu",""),"") -> Manufacturing Energy: 0.0 MMBtu | AA27: =IF(Y$28>0,IF((Y27/Y$28)>0.02,$W27&": "&CHAR(10)&TEXT(Y27,"#,##0.0")&" MMBtu",""),"") -> Manufacturing Energy: 1.1 MMBtu
W28: Total | X28: =SUM(X26:X27) -> 0.28012615 | Y28: =SUM(Y26:Y27) -> 1.5344134
X30: Energy Comparison for US Market
X31: New Technology, Industrial Scale | Y31: Commercial Benchmark | Z31: New Technology, Industrial Scale | AA31: Commercial Benchmark
X32: =New_Technology -> Waste Heat Recovery (Heat Pump) | Y32: =Commercial_Benchmark -> Evaporative Condenser | Z32: Label (if >2%) | AA32: Label (if >2%)
C33: Potential Manufacturing Cost Savings per Reference Volume Manufactured: | F33: Potential Cradle-to-Gate Energy Savings per Reference Volume Manufactured: | I33: Potential Cradle-to-Gate Emissions Reduction per Reference Volume Manufactured: | L33: Annual Potential Cost Savings to U.S. Manufacturers: | O33: Annual Potential Life Cycle Energy Savings for Affected U.S. Markets: | R33: Annual Potential Life Cycle Energy Savings for Affected U.S. Markets: | W33: Raw Materials Energy | X33: ='Summary Tables'!K58 -> 0.92359389 | Y33: ='Summary Tables'!M58 -> 1.6777718 | Z33: =IF(X$36>0,IF((X33/X$36)>0.02,$W33&": "&CHAR(10)&TEXT(X33,"#,##0.0")&" TBtu",""),"") | AA33: =IF(Y$36>0,IF((Y33/Y$36)>0.02,$W33&": "&CHAR(10)&TEXT(Y33,"#,##0.0")&" TBtu",""),"")
C34: =Y11-X11 -> 192.9148 | D34: saved per ref. volume | F34: =Y28-X28 -> 1.2542872 | G34: saved per ref. volume | I34: =Y43-X43 -> 12.866711 | J34: saved per ref. volume | L34: =(Y21-X21)*0.000001 -> 647.69761 | M34: saved per year | O34: ='Results Dashboard'!Y36-'Results Dashboard'!X36 -> 45.629951 | P34: saved per year | R34: =Y50-X50 -> 11.121622 | S34: saved per year | W34: Manufacturing Energy | X34: ='Summary Tables'!K59 -> 0.098866551 | Y34: ='Summary Tables'!M59 -> 3.9228371 | Z34: =IF(X$36>0,IF((X34/X$36)>0.02,$W34&": "&CHAR(10)&TEXT(X34,"#,##0.0")&" TBtu",""),"") | AA34: =IF(Y$36>0,IF((Y34/Y$36)>0.02,$W34&": "&CHAR(10)&TEXT(Y34,"#,##0.0")&" TBtu",""),"") -> Manufacturing Energy: 3.9 TBtu
C35: =C34/Y11 -> 0.58851468 | D35: cost savings per unit of production replaced | F35: =F34/Y28 -> 0.81743763 | G35: manufacturing energy savings per unit of production replaced | I35: =I34/Y43 -> 0.1363943 | J35: manufacturing energy savings per unit of production replaced | L35: =(Y21-X21)/Y21 -> 0.58407543 | M35: cost savings per unit of production replaced | O35: =O34/Y36 -> 0.34291888 | P35: life cycle energy savings in affected markets | R35: =R34/Y50 -> 4.2900305 | S35: life cycle emissions reduction in affected markets | W35: Use Phase Energy | X35: ='Summary Tables'!K60 -> 86.410986 | Y35: ='Summary Tables'!M60 -> 127.46279 | Z35: =IF(X$36>0,IF((X35/X$36)>0.02,$W35&": "&CHAR(10)&TEXT(X35,"#,##0.0")&" TBtu",""),"") -> Use Phase Energy: 86.4 TBtu | AA35: =IF(Y$36>0,IF((Y35/Y$36)>0.02,$W35&": "&CHAR(10)&TEXT(Y35,"#,##0.0")&" TBtu",""),"") -> Use Phase Energy: 127.5 TBtu
W36: Total | X36: =SUM(X33:X35) -> 87.433446 | Y36: =SUM(Y33:Y35) -> 133.0634
C37: Cost Impact Summary (Reference Volume) | F37: Energy Impact Summary (Reference Volume) | I37: Emissions (GWP) Impact Summary (Reference Volume) | L37: Cost Impact Summary (U.S. Manufacturers) | O37: Energy Impact Summary (U.S. Market) | R37: Emissions (GWP) Impact Summary (U.S. Market)
C38: Manufacturing Cost Category | D38: Cost Savings | F38: Life Cycle Phase | G38: Energy Savings | I38: Life Cycle Phase | J38: Emissions (GWP) Reduction | L38: Manufacturing Cost Category | M38: Cost Savings | O38: Life Cycle Phase | P38: Energy Savings | R38: Life Cycle Phase | S38: Emissions (GWP) Reduction | X38: Manufacturing Emissions Comparison for Reference Volume
C39: Capital Expenses | D39: =Y6-X6 -> 74.293743 | F39: Raw Materials | G39: =Y26-X26 -> 0.20662408 | I39: Raw Materials | J39: =Y41-X41 -> 37.007366 | L39: Capital Expenses | M39: =(Y16-X16)*0.000001 -> 284.73077 | O39: Raw Mater. Embodied Energy | P39: =Y33-X33 -> 0.75417788 | R39: Raw Mater. Embodied Energy | S39: =Y47-X47 -> 0.067538443 | X39: New Technology, Industrial Scale | Y39: Commercial Benchmark | Z39: New Technology, Industrial Scale | AA39: Commercial Benchmark
C40: Raw Materials | D40: =Y7-X7 -> 83.406843 | F40: Manufacturing | G40: =Y27-X27 -> 1.0476632 | I40: Manufacturing | J40: =Y42-X42 -> -24.140655 | L40: Raw Materials | M40: =(Y17-X17)*0.000001 -> 304.43498 | O40: Manufacturing | P40: =Y34-X34 -> 3.8239705 | R40: Manufacturing | S40: =Y48-X48 -> -0.044056696 | X40: =New_Technology -> Waste Heat Recovery (Heat Pump) | Y40: =Commercial_Benchmark -> Evaporative Condenser | Z40: Label (if >2%) | AA40: Label (if >2%)
C41: Energy (Utilities) | D41: =Y8-X8 -> 7.7102578 | F41: Total Energy Savings | G41: =SUM(G39:G40) -> 1.2542872 | I41: Total Energy Savings | J41: =SUM(J39:J40) -> 12.866711 | L41: Energy (Utilities) | M41: =(Y18-X18)*0.000001 -> 28.142441 | O41: Use Phase | P41: =Y35-X35 -> 41.051803 | R41: Use Phase | S41: =Y49-X49 -> 11.09814 | W41: Raw Materials Emissions | X41: ='Summary Tables'!E58 -> 15.275945 | Y41: ='Summary Tables'!G58 -> 52.283311 | Z41: =IF(X$43>0,IF((X41/X$43)>0.02,$W41&": "&CHAR(10)&TEXT(X41,"#,##0")&" lbs CO2-e",""),"") -> Raw Materials Emissions: 15 lbs CO2-e | AA41: =IF(Y$43>0,IF((Y41/Y$43)>0.02,$W41&": "&CHAR(10)&TEXT(Y41,"#,##0")&" lbs CO2-e",""),"") -> Raw Materials Emissions: 52 lbs CO2-e
C42: Direct Labor | D42: =Y9-X9 -> 8.3258693 | L42: Direct Labor | M42: =(Y19-X19)*0.000001 -> 30.389423 | O42: Total Energy Savings | P42: =SUM(P39:P41) -> 45.629951 | R42: Total Energy Savings | S42: =SUM(S39:S41) -> 11.121622 | W42: Manufacturing Emissions | X42: ='Summary Tables'!E59 -> 66.19201 | Y42: ='Summary Tables'!G59 -> 42.051355 | Z42: =IF(X$43>0,IF((X42/X$43)>0.02,$W42&": "&CHAR(10)&TEXT(X42,"#,##0")&" lbs CO2-e",""),"") -> Manufacturing Emissions: 66 lbs CO2-e | AA42: =IF(Y$43>0,IF((Y42/Y$43)>0.02,$W42&": "&CHAR(10)&TEXT(Y42,"#,##0")&" lbs CO2-e",""),"") -> Manufacturing Emissions: 42 lbs CO2-e
C43: Total Cost Savings | D43: =SUM(D39:D42) -> 173.73671 | L43: Total Cost Savings | M43: =SUM(M39:M42) -> 647.69761 | W43: Total | X43: =SUM(X41:X42) -> 81.467955 | Y43: =SUM(Y41:Y42) -> 94.334666
C45: Key | X45: New Technology, Industrial Scale | Y45: Commercial Benchmark | Z45: New Technology, Industrial Scale | AA45: Commercial Benchmark
C46: Net Savings | D46: =1 -> 1 | X46: =New_Technology -> Waste Heat Recovery (Heat Pump) | Y46: =Commercial_Benchmark -> Evaporative Condenser | Z46: Label (if >2%) | AA46: Label (if >2%)
C47: Even | D47: =0 -> 0 | W47: Raw Materials Emissions | X47: ='Summary Tables'!L58 -> 0.0278786 | Y47: ='Summary Tables'!N58 -> 0.095417043 | Z47: =IF(X$50>0,IF((X47/X$50)>0.02,$W47&": "&CHAR(10)&TEXT(X47,"#,##0.0")&" million tons CO2-e",""),"") | AA47: =IF(Y$50>0,IF((Y47/Y$50)>0.02,$W47&": "&CHAR(10)&TEXT(Y47,"#,##0.0")&" million tons CO2-e",""),"") -> Raw Materials Emissions: 0.1 million tons CO2-e
C48: Net Increase | D48: =-1 -> -1 | W48: Manufacturing Emissions | X48: ='Summary Tables'!L59 -> 0.12080042 | Y48: ='Summary Tables'!N59 -> 0.076743723 | Z48: =IF(X$50>0,IF((X48/X$50)>0.02,$W48&": "&CHAR(10)&TEXT(X48,"#,##0.0")&" million tons CO2-e",""),"") | AA48: =IF(Y$50>0,IF((Y48/Y$50)>0.02,$W48&": "&CHAR(10)&TEXT(Y48,"#,##0.0")&" million tons CO2-e",""),"") -> Manufacturing Emissions: 0.1 million tons CO2-e
W49: Use Phase Emissions | X49: ='Summary Tables'!L60 -> -8.6778668 | Y49: ='Summary Tables'!N60 -> 2.4202735 | Z49: =IF(X$50>0,IF((X49/X$50)>0.02,$W49&": "&CHAR(10)&TEXT(X49,"#,##0.0")&" million tons CO2-e",""),"") | AA49: =IF(Y$50>0,IF((Y49/Y$50)>0.02,$W49&": "&CHAR(10)&TEXT(Y49,"#,##0.0")&" million tons CO2-e",""),"") -> Use Phase Emissions: 2.4 million tons CO2-e
B50: Return to Home Page | W50: Total | X50: =SUM(X47:X49) -> -8.5291878 | Y50: =SUM(Y47:Y49) -> 2.5924343

Sheet Rapid Data Input (Method 2)
B1: U.S. DEPARTMENT OF ENERGY (DOE) OFFICE OF ENERGY EFFICIENCY AND RENEWABLE ENERGY (EERE)
B2: Techno-economic, Energy & Carbon Heuristic Tool for Early Stage Technologies (TECHTEST)
B3: Rapid Data Input Data Sheet
B5: This is the data input sheet for the Rapid Data Entry Approach. This approach, which requires high-level data entries only, is intended for users who have already completed an analysis in another format, but wish to quickly "port" results into TECHTEST to generate results tables and dashboards in the standardized IPA format. To use this method, first complete the "Project Basics and Benchmarks" and "Metrics" (Tier 1) data input tabs, linked below:
B6: Project Basics and Benchmarks (Tier 1)
B7: Performance Metrics (Tier 1)
B8: Then, enter high-level data in the blue input cells in this sheet. Results will be summarized in the two Results tabs that follow.
B10: End-Use Market | D10: Market End-Use Product | E10: =EndUse_Product -> Cooled Waste Water
B11: Enter the current annual U.S. production for the market end-use product. | D11: Current Annual U.S. Production
D12: Units for Annual U.S. Production
B16: Technology Benchmarking
B17: Complete the benchmarking table by defining the new technology and competing technologies, estimating curent and potential market shares, and providing the annual production of typical facilities for each technology. | E17: Technology Definition(s) | F17: Product or Application | G17: Current Technology Status (Emerging, State of Art, Current Typical) | H17: Current Estimated Market Share for This Technology (%) | I17: Potential Future Market Share for This Technology (%) | J17: ="Annual Production of Typical Industrial-Scale Facility ("&E12&"/yr)*" -> Annual Production of Typical Industrial-Scale Facility (/yr)*
D18: New Technology (developed in this project)
D19: Commercial Benchmark (used in comparisons)
D20: Other Competing Technologies (list) | J20: n/a
D21: * Input the annual production volume of a typical commercial facility for the Commercial Benchmark technology, and a hypothetical industrial scale facility for the New Technology.
B24: Reference Volume | D24: ="Reference Volume ("&RapidAnnualProdUnits&")*" -> Reference Volume ()* | F24: for New Technology
B25: Enter the reference volumes to be used in this analysis. Values should be equivalent for the New Technology and Commercial Benchmark. | D25: ="Equivalent Reference Volume ("&E12&")" -> Equivalent Reference Volume () | F25: for Commercial Benchmark Technology
D26: * All manufacturing costs and data will be provided in terms of this reference volume. Units should match those used to describe annual U.S. production.
D27: The equivalent reference volume for the Commercial Benchmark should be equivalent on a mass substitution (performance equivalent) basis.
B31: Potential U.S. Market Size | D31: ="Potentially Replaceable Production ("&RapidAnnualProdUnits&")*" -> Potentially Replaceable Production ()* | E31: =RapidAnnualProd*RapidPotentialMarketShare -> 0 | F31: (based on annual U.S. production and potential future market share for new technology)
B32: (autocalculates from above) | D32: ="Potential New Technology Production ("&RapidAnnualProdUnits&")*" -> Potential New Technology Production ()* | E32: =RapidReplaceableProduction*RapidRefVolume/RapidRefVolumeBenchmark -> #DIV/0! | F32: (equivalent quantity, adjusting for substitution ratio)
B35: Manufacturing Cost Comparison | F35: Manufacturing Costs for Reference Volume
B36: Enter the manufacturing CapEx (amortized) and manufacturing OpEx, considering the reference volume. | F36: New Technology, at Industrial Scale | G36: Commercial Benchmark
E37: Technology Name | F37: =RpaidNewTech -> 0 | G37: =RapidBenchmarkTech -> 0
E38: Reference Volume | F38: =TEXT(RapidRefVolume,"#,##0")&" "&RapidAnnualProdUnits -> 0 | G38: =TEXT(RapidRefVolumeBenchmark,"#,##0")&" "&RapidAnnualProdUnits -> 0
F39: =" of "&RapidProduct -> of Cooled Waste Water | G39: =" of "&RapidProduct -> of Cooled Waste Water
F40: Manufacturing Cost ($) for Reference Volume
D41: Capital Expenses (CapEx) | E41: Process Equipment
E42: Non-process Equipment
E43: Engineering & Construction
E44: Other Capital Expenses
E45: Facility/Equipment Maintenance | H45: (Rule of thumb: 5% of capital expenses)
D46: Operating Expenses (OpEx) | E46: Raw Materials
E47: Energy
E48: Direct Labor
E49: Other Recurring Costs
D50: Total Manufacturing Cost | E50: CapEx Subtotal | F50: =SUM(F41:F44) -> 0 | G50: =SUM(G41:G44) -> 0
E51: OpEx Subtotal | F51: =SUM(F46:F49) -> 0 | G51: =SUM(G46:G49) -> 0
E52: Total Cost (CapEx + OpEx) | F52: =SUM(F50:F51) -> 0 | G52: =SUM(G50:G51) -> 0
B55: Energy & Emissions Comparison | F55: Cradle-to-Gate Energy & Emissions for Reference Volume
B56: Enter the raw materials embodied energy and emissions, and the manufacturing energy and emissions, considering the reference volume. | F56: New Technology, at Industrial Scale | H56: Commercial Benchmark
E57: Technology Name | F57: =RpaidNewTech -> 0 | H57: =RapidBenchmarkTech -> 0
E58: Reference Volume | F58: =TEXT(RapidRefVolume,"#,##0")&" "&RapidAnnualProdUnits -> 0 | H58: =TEXT(RapidRefVolumeBenchmark,"#,##0")&" "&RapidAnnualProdUnits -> 0
F59: =" of "&RapidProduct -> of Cooled Waste Water | H59: =" of "&RapidProduct -> of Cooled Waste Water
F60: Primary Energy Consumption (including offsite electricity losses) for Reference Volume (MMBtu) | G60: Emissions (100-year GWP, lbs CO2-eq) for Reference Volume | H60: Primary Energy Consumption (including offsite electricity losses) for Reference Volume (MMBtu) | I60: Emissions (100-year GWP, lbs CO2-eq) for Reference Volume
D61: Cradle-to-Gate | E61: Raw Materials*
E62: Manufacturing**
D63: Total | E63: Cradle-to-Gate Total | F63: =SUM(F61:F62) -> 0 | G63: =SUM(G61:G62) -> 0 | H63: =SUM(H61:H62) -> 0 | I63: =SUM(I61:I62) -> 0
D64: * Sum embodied energy (or emissions) for all raw materials used in manufacturing, using actual or proxy materials depending on data availability. The MFI tool is a useful resource for this task; see mini-tool linked below.
D65: Calculator Tool: Extracting Embodied Energy & Carbon from MFI
D66: ** Include onsite manufacturing energy consumption for process and non-process uses, offsite electricity losses, 100-year GWP emissions, and process emissions. For emissions data by energy source, see the reference data tab linked below.
D67: Reference Data: Global Warming Potentials
B69: Enter the use phase energy and emissions, considering the overall potential U.S. market for the new technology. Raw materials and manufacturing energy are automatically calculated based on the entries above, by scaling to the entire potential U.S. market. | F69: Cradle-to-Grave Energy & Emissions for Reference Volume
F70: New Technology, at Industrial Scale | H70: Commercial Benchmark
E71: Technology Name | F71: =RpaidNewTech -> 0 | H71: =RapidBenchmarkTech -> 0
E72: Replaceable Production Volume* | F72: =TEXT(RapidPotentialProduction,"#,##0")&" "&RapidAnnualProdUnits -> #DIV/0! | H72: =TEXT(RapidReplaceableProduction,"#,##0")&" "&RapidAnnualProdUnits -> 0
F73: =" of "&RapidProduct -> of Cooled Waste Water | H73: =" of "&RapidProduct -> of Cooled Waste Water
D74: Cradle-to-Gate | E74: Raw Materials | F74: =RapidPotentialProduction*F61/RapidRefVolume -> #DIV/0! | G74: =(RapidPotentialProduction*G61/RapidRefVolume)*(1/2000) -> #DIV/0! | H74: =RapidReplaceableProduction*H61/RapidRefVolumeBenchmark -> #DIV/0! | I74: =(RapidReplaceableProduction*I61/RapidRefVolumeBenchmark)*(1/2000) -> #DIV/0!
E75: Manufacturing | F75: =RapidPotentialProduction*F62/RapidRefVolume -> #DIV/0! | G75: =(RapidPotentialProduction*G62/RapidRefVolume)*(1/2000) -> #DIV/0! | H75: =RapidReplaceableProduction*H62/RapidRefVolumeBenchmark -> #DIV/0! | I75: =(RapidReplaceableProduction*I62/RapidRefVolumeBenchmark)*(1/2000) -> #DIV/0!
D76: Gate-to-Grave | E76: Use Phase
D77: Total | E77: Cradle-to-Grave Total | F77: =SUM(F74:F76) -> #DIV/0! | G77: =SUM(G74:G76) -> #DIV/0! | H77: =SUM(H74:H76) -> #DIV/0! | I77: =SUM(I74:I76) -> #DIV/0!
D78: * The potential U.S. market is the total potentially replaceable portion of the overall U.S. market. The production volume for the new technology is adjusted by the substitution ratio, which is unity if equivalent reference volumes are identical.
B80: References, Notes, and Assumptions
B82: List key references and assumptions used to prepare the data provided in this sheet. Add as many rows as needed.
B88: Calculations
B89: Use this section for project-specific calculations and detailed references supporting the data above. Add as many rows as needed.
B104: Return to Home Page | J104: X box when this sheet is complete:

Sheet Summary Tables (Method 2)
B1: U.S. DEPARTMENT OF ENERGY (DOE) OFFICE OF ENERGY EFFICIENCY AND RENEWABLE ENERGY (EERE)
B2: Techno-economic, Energy & Carbon Heuristic Tool for Early Stage Technologies (TECHTEST)
B3: =IF(RapidAnnualProd="","Please Refer to the other Summary Tables Tab for TECHTEST Results","Results Summary Tables (Method 2 - Rapid Data Entry)") -> Please Refer to the other Summary Tables Tab for TECHTEST Results
B5: This worksheet auto-calculates. Do not enter data in this tab. After entering data into the Method 2 data input tabs, results will appear in the green cells of the summary tables below automatically.
B6: Project Basics | C6: Project Title | D6: =Project_Title -> Waste Heat Recovery Cooling in Beverage Manufacturing
C7: Lead Organization | D7: =Project_Lead -> Hypothetical Organization
C8: Collaborative Partner(s) | D8: =Project_Collaborators -> Staff
C9: Principal Investigator | D9: =Project_PI&", "&Project_PI_Org -> John Doe, Hypotentical National Laboratory
C10: MYPP Technology Area, if any | D10: =MYPP_Area -> #REF!
C11: AMO Technology Manager | D11: =AMO_TM -> Jane Doe
C12: Project Timeline | D12: =TEXT(Project_Start,"[$-en-US]mmmm yyyy;@")&" to "&TEXT(Project_End,"[$-en-US]mmmm yyyy;@") -> January 2023 to January 2025
C13: Funding Mechanism | D13: =Funding_Mech -> R&D Project
H14: =IF(Project_Start<>"",IF(Project_Start<TODAY(),IF(Project_End+30>TODAY(),"Status: Project Underway","Status: Project Complete"),"Status: Future Project"),"") -> Status: Project Complete
B15: End-Use Market | C15: Market End-Use Product | D15: =RapidProduct -> Cooled Waste Water
C16: Current Annual US Production | D16: =RapidAnnualProd -> 0 | E16: =RapidAnnualProdUnits -> 0
C17: U.S. Production that Could be Replaced by New Technology | D17: =RapidReplaceableProduction -> 0 | E17: =RapidAnnualProdUnits -> 0 | F17: ="(assuming replacement of "&TEXT(RapidPotentialMarketShare,"0%")&" of the end-use market)" -> (assuming replacement of 0% of the end-use market)
C18: U.S. Potential Production using New Technology | D18: =ReplaceableProduction*RapidRefVolume/RapidRefVolumeBenchmark -> #DIV/0! | E18: =RapidAnnualProdUnits -> 0 | F18: (based on substitution ratios for new product, if replacing benchmark product)
B20: Benchmarking | D20: Technology Definition(s) | E20: Product or Application | F20: Current Technology Status | G20: Current Estimated Market Share | H20: Potential Future Market Share
C21: New Technology (developed in this project) | D21: =RpaidNewTech -> 0 | E21: ='Rapid Data Input (Method 2)'!F18 -> 0 | F21: ='Rapid Data Input (Method 2)'!G18 -> 0 | G21: ='Rapid Data Input (Method 2)'!H18 -> 0 | H21: =RapidPotentialMarketShare -> 0
C22: Commercial Benchmark (used in comparisons) | D22: =RapidBenchmarkTech -> 0 | E22: ='Rapid Data Input (Method 2)'!F19 -> 0 | F22: ='Rapid Data Input (Method 2)'!G19 -> 0 | G22: ='Rapid Data Input (Method 2)'!H19 -> 0 | H22: ='Rapid Data Input (Method 2)'!I19 -> 0
C23: Other Competing Technologies (list) | D23: ='Rapid Data Input (Method 2)'!E20 -> 0 | E23: ='Rapid Data Input (Method 2)'!F20 -> 0 | F23: ='Rapid Data Input (Method 2)'!G20 -> 0 | G23: ='Rapid Data Input (Method 2)'!H20 -> 0 | H23: ='Rapid Data Input (Method 2)'!I20 -> 0
B25: Manufacturing Cost Results
B27: Manufacturing Cost Comparison | G27: Manufacturing Cost Comparison | M27: Manufacturing Cost Comparison
B28: Based on Equivalent Reference Volume | D28: New Technology, at Industrial Scale | E28: Commercial Benchmark | G28: Based on Facility Size | I28: New Technology, at Industrial Scale | J28: Commercial Benchmark | K28: Commercial Benchmark Scaled to Size of New Technology Facility* | M28: Based on Overall Potential U.S. Market | O28: New Technology, at Industrial Scale | P28: Commercial Benchmark
C29: Technology Name | D29: =D21 -> 0 | E29: =D22 -> 0 | H29: Technology Name | I29: =RpaidNewTech -> 0 | J29: =RapidBenchmarkTech -> 0 | K29: =RapidBenchmarkTech -> 0 | N29: Technology Name | O29: =RpaidNewTech -> 0 | P29: =RapidBenchmarkTech -> 0
C30: Reference Volume | D30: ='Rapid Data Input (Method 2)'!F38 -> 0 | E30: ='Rapid Data Input (Method 2)'!G38 -> 0 | H30: Annual Facility Production | I30: =TEXT(RapidFacilityProduction,"#,##0")&" "&RapidAnnualProdUnits -> 0 | J30: =TEXT(RapidFacilityProductionBenchmark,"#,##0")&" "&'Rapid Data Input (Method 2)'!E12 -> 0 | K30: =TEXT(RapidFacilityProduction*RapidRefVolumeBenchmark/RapidRefVolume,"#,##0")&" "&RapidAnnualProdUnits -> #DIV/0! | N30: Annual U.S. Production Replaced* | O30: =TEXT(RapidPotentialProduction,"#,##0")&" "&RapidAnnualProdUnits -> #DIV/0! | P30: =TEXT(RapidReplaceableProduction,"#,##0")&" "&RapidAnnualProdUnits -> 0
D31: ='Rapid Data Input (Method 2)'!F39 -> of Cooled Waste Water | E31: ='Rapid Data Input (Method 2)'!G39 -> of Cooled Waste Water | I31: =" of "&RapidProduct -> of Cooled Waste Water | J31: =" of "&RapidProduct -> of Cooled Waste Water | K31: =" of "&RapidProduct -> of Cooled Waste Water | O31: =" of "&RapidProduct -> of Cooled Waste Water | P31: =" of "&RapidProduct -> of Cooled Waste Water
D32: Manufacturing Cost ($) for Reference Volume | J32: Annual Manufacturing Cost ($) for Facility | O32: Manufacturing Cost ($) for Overall U.S. Market
B33: Capital Expenses (CapEx) | C33: Process Equipment | D33: ='Rapid Data Input (Method 2)'!F41 -> 0 | E33: ='Rapid Data Input (Method 2)'!G41 -> 0 | G33: Capital Expenses (CapEx) | H33: Process Equipment | I33: =IF(D33<>"",D33*RapidFacilityProduction/RapidRefVolume,"") -> #DIV/0! | J33: =IF(E33<>"",E33*RapidFacilityProductionBenchmark/RapidRefVolumeBenchmark,"") -> #DIV/0! | K33: =IF(E33<>"",E33*(RapidFacilityProduction/RapidRefVolumeBenchmark)*(RapidRefVolumeBenchmark/RapidRefVolume),"") -> #DIV/0! | M33: Capital Expenses (CapEx) | N33: Process Equipment | O33: =IF(D33<>"",D33*RapidPotentialProduction/RapidRefVolume,"") -> #DIV/0! | P33: =IF(E33<>"",E33*RapidReplaceableProduction/RapidRefVolumeBenchmark,"") -> #DIV/0!
C34: Non-process Equipment | D34: ='Rapid Data Input (Method 2)'!F42 -> 0 | E34: ='Rapid Data Input (Method 2)'!G42 -> 0 | H34: Non-process Equipment | I34: =IF(D34<>"",D34*RapidFacilityProduction/RapidRefVolume,"") -> #DIV/0! | J34: =IF(E34<>"",E34*RapidFacilityProductionBenchmark/RapidRefVolumeBenchmark,"") -> #DIV/0! | K34: =IF(E34<>"",E34*(RapidFacilityProduction/RapidRefVolumeBenchmark)*(RapidRefVolumeBenchmark/RapidRefVolume),"") -> #DIV/0! | N34: Non-process Equipment | O34: =IF(D34<>"",D34*RapidPotentialProduction/RapidRefVolume,"") -> #DIV/0! | P34: =IF(E34<>"",E34*RapidReplaceableProduction/RapidRefVolumeBenchmark,"") -> #DIV/0!
C35: Engineering & Construction | D35: ='Rapid Data Input (Method 2)'!F43 -> 0 | E35: ='Rapid Data Input (Method 2)'!G43 -> 0 | H35: Engineering & Construction | I35: =IF(D35<>"",D35*RapidFacilityProduction/RapidRefVolume,"") -> #DIV/0! | J35: =IF(E35<>"",E35*RapidFacilityProductionBenchmark/RapidRefVolumeBenchmark,"") -> #DIV/0! | K35: =IF(E35<>"",E35*(RapidFacilityProduction/RapidRefVolumeBenchmark)*(RapidRefVolumeBenchmark/RapidRefVolume),"") -> #DIV/0! | N35: Engineering & Construction | O35: =IF(D35<>"",D35*RapidPotentialProduction/RapidRefVolume,"") -> #DIV/0! | P35: =IF(E35<>"",E35*RapidReplaceableProduction/RapidRefVolumeBenchmark,"") -> #DIV/0!
C36: Other Capital Expenses | D36: ='Rapid Data Input (Method 2)'!F44 -> 0 | E36: ='Rapid Data Input (Method 2)'!G44 -> 0 | H36: Other Capital Expenses | I36: =IF(D36<>"",D36*RapidFacilityProduction/RapidRefVolume,"") -> #DIV/0! | J36: =IF(E36<>"",E36*RapidFacilityProductionBenchmark/RapidRefVolumeBenchmark,"") -> #DIV/0! | K36: =IF(E36<>"",E36*(RapidFacilityProduction/RapidRefVolumeBenchmark)*(RapidRefVolumeBenchmark/RapidRefVolume),"") -> #DIV/0! | N36: Other Capital Expenses | O36: =IF(D36<>"",D36*RapidPotentialProduction/RapidRefVolume,"") -> #DIV/0! | P36: =IF(E36<>"",E36*RapidReplaceableProduction/RapidRefVolumeBenchmark,"") -> #DIV/0!
B37: Operating Expenses (OpEx) | C37: Raw Materials | D37: ='Rapid Data Input (Method 2)'!F46 -> 0 | E37: ='Rapid Data Input (Method 2)'!G46 -> 0 | G37: Operating Expenses (OpEx) | H37: Raw Materials | I37: =IF(D37<>"",D37*RapidFacilityProduction/RapidRefVolume,"") -> #DIV/0! | J37: =IF(E37<>"",E37*RapidFacilityProductionBenchmark/RapidRefVolumeBenchmark,"") -> #DIV/0! | K37: =IF(E37<>"",E37*(RapidFacilityProduction/RapidRefVolumeBenchmark)*(RapidRefVolumeBenchmark/RapidRefVolume),"") -> #DIV/0! | M37: Operating Expenses (OpEx) | N37: Raw Materials | O37: =IF(D37<>"",D37*RapidPotentialProduction/RapidRefVolume,"") -> #DIV/0! | P37: =IF(E37<>"",E37*RapidReplaceableProduction/RapidRefVolumeBenchmark,"") -> #DIV/0!
C38: Energy | D38: ='Rapid Data Input (Method 2)'!F47 -> 0 | E38: ='Rapid Data Input (Method 2)'!G47 -> 0 | H38: Energy | I38: =IF(D38<>"",D38*RapidFacilityProduction/RapidRefVolume,"") -> #DIV/0! | J38: =IF(E38<>"",E38*RapidFacilityProductionBenchmark/RapidRefVolumeBenchmark,"") -> #DIV/0! | K38: =IF(E38<>"",E38*(RapidFacilityProduction/RapidRefVolumeBenchmark)*(RapidRefVolumeBenchmark/RapidRefVolume),"") -> #DIV/0! | N38: Energy | O38: =IF(D38<>"",D38*RapidPotentialProduction/RapidRefVolume,"") -> #DIV/0! | P38: =IF(E38<>"",E38*RapidReplaceableProduction/RapidRefVolumeBenchmark,"") -> #DIV/0!
C39: Direct Labor | D39: ='Rapid Data Input (Method 2)'!F48 -> 0 | E39: ='Rapid Data Input (Method 2)'!G48 -> 0 | H39: Direct Labor | I39: =IF(D39<>"",D39*RapidFacilityProduction/RapidRefVolume,"") -> #DIV/0! | J39: =IF(E39<>"",E39*RapidFacilityProductionBenchmark/RapidRefVolumeBenchmark,"") -> #DIV/0! | K39: =IF(E39<>"",E39*(RapidFacilityProduction/RapidRefVolumeBenchmark)*(RapidRefVolumeBenchmark/RapidRefVolume),"") -> #DIV/0! | N39: Direct Labor | O39: =IF(D39<>"",D39*RapidPotentialProduction/RapidRefVolume,"") -> #DIV/0! | P39: =IF(E39<>"",E39*RapidReplaceableProduction/RapidRefVolumeBenchmark,"") -> #DIV/0!
C40: Other Recurring Costs | D40: ='Rapid Data Input (Method 2)'!F49 -> 0 | E40: ='Rapid Data Input (Method 2)'!G49 -> 0 | H40: Other Recurring Costs | I40: =IF(D40<>"",D40*RapidFacilityProduction/RapidRefVolume,"") -> #DIV/0! | J40: =IF(E40<>"",E40*RapidFacilityProductionBenchmark/RapidRefVolumeBenchmark,"") -> #DIV/0! | K40: =IF(E40<>"",E40*(RapidFacilityProduction/RapidRefVolumeBenchmark)*(RapidRefVolumeBenchmark/RapidRefVolume),"") -> #DIV/0! | N40: Other Recurring Costs | O40: =IF(D40<>"",D40*RapidPotentialProduction/RapidRefVolume,"") -> #DIV/0! | P40: =IF(E40<>"",E40*RapidReplaceableProduction/RapidRefVolumeBenchmark,"") -> #DIV/0!
B41: Total Manufacturing Cost | C41: CapEx Subtotal | D41: ='Rapid Data Input (Method 2)'!F50 -> 0 | E41: ='Rapid Data Input (Method 2)'!G50 -> 0 | G41: Total Manufacturing Cost | H41: CapEx Subtotal | I41: =SUM(I33:I36) -> #DIV/0! | J41: =SUM(J33:J36) -> #DIV/0! | K41: =SUM(K33:K36) -> #DIV/0! | M41: Total Manufacturing Cost | N41: CapEx Subtotal | O41: =SUM(O33:O36) -> #DIV/0! | P41: =SUM(P33:P36) -> #DIV/0!
C42: OpEx Subtotal | D42: ='Rapid Data Input (Method 2)'!F51 -> 0 | E42: ='Rapid Data Input (Method 2)'!G51 -> 0 | H42: OpEx Subtotal | I42: =SUM(I37:I40) -> #DIV/0! | J42: =SUM(J37:J40) -> #DIV/0! | K42: =SUM(K37:K40) -> #DIV/0! | N42: OpEx Subtotal | O42: =SUM(O37:O40) -> #DIV/0! | P42: =SUM(P37:P40) -> #DIV/0!
C43: Total Cost (CapEx + OpEx) | D43: =SUM(D41:D42) -> 0 | E43: =SUM(E41:E42) -> 0 | H43: Total Cost (CapEx + OpEx) | I43: =SUM(I41:I42) -> #DIV/0! | J43: =SUM(J41:J42) -> #DIV/0! | K43: =SUM(K41:K42) -> #DIV/0! | N43: Total Cost (CapEx + OpEx) | O43: =SUM(O41:O42) -> #DIV/0! | P43: =SUM(P41:P42) -> #DIV/0!
G44: * In this column, production volume is scaled to be equivalent to the facility production of the New Technology facility. | M44: * This is the potential market: the total U.S. production that could potentially be replaced by the new technology.
G45: This includes a scale factor for performance-equivalence (if the reference volume for the New Technology and Commercial Benchmark differ). | M45: The production volumes shown for the two technologies are equivalent on a performance basis ("apples to apples")
B46: If the new technology were immediately and fully deployed at its maximum U.S. market share (i.e. in the "overnight replacement" scenario), the annual potential cost savings for U.S. manufacturers is:
C47: =P43-O43 -> #DIV/0! | D47: Annual Potential Cost Savings to U.S. Manufacturers
C48: ="("&TEXT(C47/P43,"0.0%") -> #DIV/0! | D48: cost savings for production replaced) | G48: =IF(C47<0,"Warning: Analysis is currently showing a cost increase for the new technology.","") -> #DIV/0!
B50: Life Cycle Energy & Emissions Results
B52: Life Cycle Comparison | I52: Life Cycle Comparison
B53: Based on Equivalent Reference Volume | D53: New Technology | F53: Commercial Benchmark | I53: Based on Overall Potential U.S. Market | K53: New Technology | M53: Commercial Benchmark
B54: (Cradle to Gate) | C54: Technology Name | D54: =RpaidNewTech -> 0 | F54: =RapidBenchmarkTech -> 0 | I54: (Cradle to Grave) | J54: Technology Name | K54: =O29 -> 0 | M54: =P29 -> 0
C55: Reference Volume | D55: =TEXT(RapidRefVolume,"#,##0")&" "&RapidAnnualProdUnits -> 0 | F55: =TEXT(RapidRefVolumeBenchmark,"#,##0")&" "&RapidAnnualProdUnits -> 0 | J55: Production Volume | K55: =O30 -> #DIV/0! | M55: =P30 -> 0
D56: =" of "&RapidProduct -> of Cooled Waste Water | F56: =" of "&RapidProduct -> of Cooled Waste Water | K56: =O31 -> of Cooled Waste Water | M56: =P31 -> of Cooled Waste Water
D57: Energy | E57: Emissions (100-yr GWP) | F57: Energy | G57: Emissions (100-yr GWP) | K57: Energy | L57: Emissions (100-yr GWP) | M57: Energy | N57: Emissions (100-yr GWP)
B58: Cradle-to-Gate | C58: Raw Materials | D58: ='Rapid Data Input (Method 2)'!F61 -> 0 | E58: ='Rapid Data Input (Method 2)'!G61 -> 0 | F58: ='Rapid Data Input (Method 2)'!H61 -> 0 | G58: ='Rapid Data Input (Method 2)'!I61 -> 0 | I58: Cradle-to-Gate Energy** | J58: Raw Materials | K58: ='Rapid Data Input (Method 2)'!F74*0.000001 -> #DIV/0! | L58: ='Rapid Data Input (Method 2)'!G74/1000000 -> #DIV/0! | M58: ='Rapid Data Input (Method 2)'!H74/1000000 -> #DIV/0! | N58: ='Rapid Data Input (Method 2)'!I74/1000000 -> #DIV/0!
C59: Manufacturing | D59: ='Rapid Data Input (Method 2)'!F62 -> 0 | E59: ='Rapid Data Input (Method 2)'!G62 -> 0 | F59: ='Rapid Data Input (Method 2)'!H62 -> 0 | G59: ='Rapid Data Input (Method 2)'!I62 -> 0 | J59: Manufacturing | K59: ='Rapid Data Input (Method 2)'!F75*0.000001 -> #DIV/0! | L59: ='Rapid Data Input (Method 2)'!G75/1000000 -> #DIV/0! | M59: ='Rapid Data Input (Method 2)'!H75/1000000 -> #DIV/0! | N59: ='Rapid Data Input (Method 2)'!I75/1000000 -> #DIV/0!
B60: Total | C60: Cradle-to-Gate Total | D60: =SUM(D58:D59) -> 0 | E60: =SUM(E58:E59) -> 0 | F60: =SUM(F58:F59) -> 0 | G60: =SUM(G58:G59) -> 0 | I60: Gate-to-Grave*** | J60: Use Phase | K60: ='Rapid Data Input (Method 2)'!F76*0.000001 -> 0 | L60: ='Rapid Data Input (Method 2)'!G76/1000000 -> 0 | M60: ='Rapid Data Input (Method 2)'!H76/1000000 -> 0 | N60: ='Rapid Data Input (Method 2)'!I76/1000000 -> 0
B61: * While cradle-to-grave energy is tied to a specific production volume, gate-to-grave energy (use phase) is tied to a scenario involving an overall "fleet" of products (produced using different technologies, in different years, etc.). In this analysis, use phase energy is computed only as an annual total and not in terms of the reference volume. | I61: Total Energy | J61: Cradle-to-Gate Subtotal | K61: =SUM(K58:K59) -> #DIV/0! | L61: =SUM(L58:L59) -> #DIV/0! | M61: =SUM(M58:M59) -> #DIV/0! | N61: =SUM(N58:N59) -> #DIV/0!
J62: Gate-to-Grave Subtotal | K62: =SUM(K60) -> 0 | L62: =SUM(L60) -> 0 | M62: =SUM(M60) -> 0 | N62: =SUM(N60) -> 0
J63: Total Energy (Cradle-to-Grave) | K63: =SUM(K61:K62) -> #DIV/0! | L63: =SUM(L61:L62) -> #DIV/0! | M63: =SUM(M61:M62) -> #DIV/0! | N63: =SUM(N61:N62) -> #DIV/0!
I64: ** Cradle-to-gate energy is computed in terms of the total annual U.S. production ("overnight replacement" scenario or current).
I65: ** Gate-to-grave energy is computed in terms of the overall fleet of products in use ("overnight replacement" scenario or current).
B67: If the new technology were immediately and fully deployed at its maximum U.S. market share (i.e. in the "overnight replacement" scenario), the annual potential life cycle energy & emissions impact for the U.S. market is:
C68: =M63-K63 -> #DIV/0! | D68: Annual Potential U.S. Energy Savings
C69: =IF(M63>0,"("&TEXT(C68/M63,"0.0%"),"(TBD") -> #DIV/0! | D69: energy savings in affected markets) | G69: =IF(C68<0,"Warning: Analysis is currently showing a life cycle energy increase for the new technology.","") -> #DIV/0!
C71: =N63-L63 -> #DIV/0! | D71: Annual Potential U.S. Emissions Reduction
C72: =IF(N63>0,"("&TEXT(C71/N63,"0.0%"),"(TBD") -> #DIV/0! | D72: emissions reduction in affected markets)
P73: For summary plots, see the next tab.
B74: Return to Home Page

Sheet Rapid Results Dashboard
B1: U.S. DEPARTMENT OF ENERGY (DOE) OFFICE OF ENERGY EFFICIENCY AND RENEWABLE ENERGY (EERE)
B2: Techno-economic, Energy & Carbon Heuristic Tool for Early Stage Technologies (TECHTEST) | W2: The data below are used in calculations. Do not delete or hide these columns!
B3: =IF(RapidAnnualProd="","Please refer to the other Results Dashboard tab for TECHTEST Results","Results Summary Plots: "&Project_Title) -> Please refer to the other Results Dashboard tab for TECHTEST Results | G3: Note: Results will populate as data entried are made in the tool. | X3: Manufacturing Cost Comparison for Reference Volume
C5: Cradle-to-Gate Cost / Reference Volume | F5: Cradle-to-Gate Energy / Reference Volume | I5: Cradle-to-Gate Emissions / Reference Volume | L5: Cradle-to-Gate Cost / Entire U.S. Market | O5: Cradle-to-Grave Energy / Entire U.S. Market | R5: Cradle-to-Grave Emissions / Entire U.S. Market | X5: New Technology, Industrial Scale | Y5: Commercial Benchmark | Z5: New Technology, Industrial Scale | AA5: Commercial Benchmark
C6: Manufacturing Cost Comparison (for Reference Volume) | F6: Cradle-to-Gate Energy Comparison (for Reference Volume) | I6: Cradle-to-Gate Emissions Comparison (for Reference Volume) | L6: Manufacturing Cost Comparison (for Potential U.S. Market) | O6: Cradle-to-Grave Energy Comparison (for Potential U.S. Market) | R6: Cradle-to-Grave Emissions Comparison (for Potential U.S. Market) | X6: =RpaidNewTech -> 0 | Y6: =RapidBenchmarkTech -> 0 | Z6: Label (if >2%) | AA6: Label (if >2%)
C7: New Technology (at Industrial Scale) | D7: Commercial Benchmark | F7: New Technology (at Industrial Scale) | G7: Commercial Benchmark | I7: New Technology (at Industrial Scale) | J7: Commercial Benchmark | L7: Hypothetical (Fully Deployed) | M7: Current (Pre-Deployment) | O7: Hypothetical (Fully Deployed) | P7: Current (Pre-Deployment) | R7: Hypothetical (Fully Deployed) | S7: Current (Pre-Deployment) | W7: CapEx | X7: ='Summary Tables (Method 2)'!D41 -> 0 | Y7: ='Summary Tables (Method 2)'!E41 -> 0 | Z7: =IF(X$11>0,IF((X7/X$11)>0.02,$W7&": "&TEXT(X7,"$#,##0"),""),"") | AA7: =IF(Y$11>0,IF((Y7/Y$11)>0.02,$W7&": "&TEXT(Y7,"$#,##0"),""),"")
C8: ="Reference Volume:"&CHAR(10)&TEXT(RapidRefVolume,"#,##0")&" "&RapidAnnualProdUnits -> Reference Volume: 0 | D8: ="Equivalent Reference Volume:"&CHAR(10)&TEXT(RapidRefVolumeBenchmark,"#,##0")&" "&RapidAnnualProdUnits -> Equivalent Reference Volume: 0 | F8: ="Reference Volume:"&CHAR(10)&TEXT(RapidRefVolume,"#,##0")&" "&RapidAnnualProdUnits -> Reference Volume: 0 | G8: ="Equivalent Reference Volume:"&CHAR(10)&TEXT(RapidRefVolumeBenchmark,"#,##0")&" "&RapidAnnualProdUnits -> Equivalent Reference Volume: 0 | I8: ="Reference Volume:"&CHAR(10)&TEXT(RapidRefVolume,"#,##0")&" "&RapidAnnualProdUnits -> Reference Volume: 0 | J8: ="Equivalent Reference Volume:"&CHAR(10)&TEXT(RapidRefVolumeBenchmark,"#,##0")&" "&RapidAnnualProdUnits -> Equivalent Reference Volume: 0 | L8: ="Hypothetical Production:"&CHAR(10)&TEXT(RapidPotentialProduction,"#,##0")&" "&RapidAnnualProdUnits -> #DIV/0! | M8: ="Replaced Production:"&CHAR(10)&TEXT(RapidReplaceableProduction,"#,##0")&" "&RapidAnnualProdUnits -> Replaced Production: 0 | O8: ="Hypothetical Production:"&CHAR(10)&TEXT(RapidPotentialProduction,"#,##0")&" "&RapidAnnualProdUnits -> #DIV/0! | P8: ="Replaced Production:"&CHAR(10)&TEXT(RapidReplaceableProduction,"#,##0")&" "&RapidAnnualProdUnits -> Replaced Production: 0 | R8: ="Hypothetical Production:"&CHAR(10)&TEXT(RapidPotentialProduction,"#,##0")&" "&RapidAnnualProdUnits -> #DIV/0! | S8: ="Replaced Production:"&CHAR(10)&TEXT(RapidReplaceableProduction,"#,##0")&" "&RapidAnnualProdUnits -> Replaced Production: 0 | W8: Raw Materials | X8: ='Summary Tables (Method 2)'!D37 -> 0 | Y8: ='Summary Tables (Method 2)'!E37 -> 0 | Z8: =IF(X$11>0,IF((X8/X$11)>0.02,$W8&": "&TEXT(X8,"$#,##0"),""),"") | AA8: =IF(Y$11>0,IF((Y8/Y$11)>0.02,$W8&": "&TEXT(Y8,"$#,##0"),""),"")
C9: =X11 -> 0 | D9: =Y11 -> 0 | F9: =X27 -> 0 | G9: =Y27 -> 0 | I9: =X42 -> 0 | J9: =Y42 -> 0 | L9: =TEXT(X20/1000000,"$#,##0")&" million" -> #DIV/0! | M9: =TEXT(Y20/1000000,"$#,##0")&" million" -> #DIV/0! | O9: =X35 -> #DIV/0! | P9: =Y35 -> #DIV/0! | R9: =X49 -> #DIV/0! | S9: =Y49 -> #DIV/0! | W9: Energy | X9: ='Summary Tables (Method 2)'!D38 -> 0 | Y9: ='Summary Tables (Method 2)'!E38 -> 0 | Z9: =IF(X$11>0,IF((X9/X$11)>0.02,$W9&": "&TEXT(X9,"$#,##0"),""),"") | AA9: =IF(Y$11>0,IF((Y9/Y$11)>0.02,$W9&": "&TEXT(Y9,"$#,##0"),""),"")
W10: Labor | X10: ='Summary Tables (Method 2)'!D39 -> 0 | Y10: ='Summary Tables (Method 2)'!E39 -> 0 | Z10: =IF(X$11>0,IF((X10/X$11)>0.02,$W10&": "&TEXT(X10,"$#,##0"),""),"") | AA10: =IF(Y$11>0,IF((Y10/Y$11)>0.02,$W10&": "&TEXT(Y10,"$#,##0"),""),"")
W11: Total | X11: =SUM(X7:X10) -> 0 | Y11: =SUM(Y7:Y10) -> 0
X13: Manufacturing Cost Comparison for US Market
X14: New Technology, Industrial Scale | Y14: Commercial Benchmark | Z14: New Technology, Industrial Scale | AA14: Commercial Benchmark
X15: ='Summary Tables (Method 2)'!D29 -> 0 | Y15: ='Summary Tables (Method 2)'!E29 -> 0 | Z15: Label (if >2%) | AA15: Label (if >2%)
W16: CapEx | X16: ='Summary Tables (Method 2)'!O41 -> #DIV/0! | Y16: ='Summary Tables (Method 2)'!P41 -> #DIV/0! | Z16: =IF(X$20>0,IF((X16/X$20)>0.02,$W16&": "&TEXT(X16,"$#,##0"),""),"") -> #DIV/0! | AA16: =IF(Y$20>0,IF((Y16/Y$20)>0.02,$W16&": "&TEXT(Y16,"$#,##0"),""),"") -> #DIV/0!
W17: Raw Materials | X17: ='Summary Tables (Method 2)'!O37 -> #DIV/0! | Y17: ='Summary Tables (Method 2)'!P37 -> #DIV/0! | Z17: =IF(X$20>0,IF((X17/X$20)>0.02,$W17&": "&TEXT(X17,"$#,##0"),""),"") -> #DIV/0! | AA17: =IF(Y$20>0,IF((Y17/Y$20)>0.02,$W17&": "&TEXT(Y17,"$#,##0"),""),"") -> #DIV/0!
W18: Energy | X18: ='Summary Tables (Method 2)'!O38 -> #DIV/0! | Y18: ='Summary Tables (Method 2)'!P38 -> #DIV/0! | Z18: =IF(X$20>0,IF((X18/X$20)>0.02,$W18&": "&TEXT(X18,"$#,##0"),""),"") -> #DIV/0! | AA18: =IF(Y$20>0,IF((Y18/Y$20)>0.02,$W18&": "&TEXT(Y18,"$#,##0"),""),"") -> #DIV/0!
W19: Labor | X19: ='Summary Tables (Method 2)'!O39 -> #DIV/0! | Y19: ='Summary Tables (Method 2)'!P39 -> #DIV/0! | Z19: =IF(X$20>0,IF((X19/X$20)>0.02,$W19&": "&TEXT(X19,"$#,##0"),""),"") -> #DIV/0! | AA19: =IF(Y$20>0,IF((Y19/Y$20)>0.02,$W19&": "&TEXT(Y19,"$#,##0"),""),"") -> #DIV/0!
W20: Total | X20: =SUM(X16:X19) -> #DIV/0! | Y20: =SUM(Y16:Y19) -> #DIV/0!
X22: Manufacturing Energy Comparison for Reference Volume
X23: New Technology, Industrial Scale | Y23: Commercial Benchmark | Z23: New Technology, Industrial Scale | AA23: Commercial Benchmark
X24: ='Summary Tables (Method 2)'!D54 -> 0 | Y24: ='Summary Tables (Method 2)'!F54 -> 0 | Z24: Label (if >2%) | AA24: Label (if >2%)
W25: Raw Materials | X25: ='Summary Tables (Method 2)'!D58 -> 0 | Y25: ='Summary Tables (Method 2)'!F58 -> 0 | Z25: =IF(X$27>0,IF((X25/X$27)>0.02,$W25&": "&CHAR(10)&TEXT(X25,"#,##0.0")&" MMBtu",""),"") | AA25: =IF(Y$27>0,IF((Y25/Y$27)>0.02,$W25&": "&CHAR(10)&TEXT(Y25,"#,##0.0")&" MMBtu",""),"")
W26: Manufacturing | X26: ='Summary Tables (Method 2)'!D59 -> 0 | Y26: ='Summary Tables (Method 2)'!F59 -> 0 | Z26: =IF(X$27>0,IF((X26/X$27)>0.02,$W26&": "&CHAR(10)&TEXT(X26,"#,##0.0")&" MMBtu",""),"") | AA26: =IF(Y$27>0,IF((Y26/Y$27)>0.02,$W26&": "&CHAR(10)&TEXT(Y26,"#,##0.0")&" MMBtu",""),"")
W27: Total | X27: =SUM(X25:X26) -> 0 | Y27: =SUM(Y25:Y26) -> 0
X29: Energy Comparison for US Market
X30: New Technology, Industrial Scale | Y30: Commercial Benchmark | Z30: New Technology, Industrial Scale | AA30: Commercial Benchmark
X31: ='Summary Tables (Method 2)'!D54 -> 0 | Y31: ='Summary Tables (Method 2)'!F54 -> 0 | Z31: Label (if >2%) | AA31: Label (if >2%)
W32: Raw Materials | X32: ='Summary Tables (Method 2)'!K58 -> #DIV/0! | Y32: ='Summary Tables (Method 2)'!M58 -> #DIV/0! | Z32: =IF(X$35>0,IF((X32/X$35)>0.02,$W32&": "&CHAR(10)&TEXT(X32,"#,##0.0")&" TBtu",""),"") -> #DIV/0! | AA32: =IF(Y$35>0,IF((Y32/Y$35)>0.02,$W32&": "&CHAR(10)&TEXT(Y32,"#,##0.0")&" TBtu",""),"") -> #DIV/0!
W33: Manufacturing | X33: ='Summary Tables (Method 2)'!K59 -> #DIV/0! | Y33: ='Summary Tables (Method 2)'!M59 -> #DIV/0! | Z33: =IF(X$35>0,IF((X33/X$35)>0.02,$W33&": "&CHAR(10)&TEXT(X33,"#,##0.0")&" TBtu",""),"") -> #DIV/0! | AA33: =IF(Y$35>0,IF((Y33/Y$35)>0.02,$W33&": "&CHAR(10)&TEXT(Y33,"#,##0.0")&" TBtu",""),"") -> #DIV/0!
C34: Potential Manufacturing Cost Savings per Reference Volume Manufactured: | F34: Potential Cradle-to-Gate Energy Savings per Reference Volume Manufactured: | I34: Potential Cradle-to-Gate Emissions Reduction per Reference Volume Manufactured: | L34: Annual Potential Cost Savings to U.S. Manufacturers: | O34: Annual Potential Life Cycle Energy Savings for Affected U.S. Markets: | R34: Annual Potential Life Cycle Energy Savings for Affected U.S. Markets: | W34: Use Phase | X34: ='Summary Tables (Method 2)'!K60 -> 0 | Y34: ='Summary Tables (Method 2)'!M60 -> 0 | Z34: =IF(X$35>0,IF((X34/X$35)>0.02,$W34&": "&CHAR(10)&TEXT(X34,"#,##0.0")&" TBtu",""),"") -> #DIV/0! | AA34: =IF(Y$35>0,IF((Y34/Y$35)>0.02,$W34&": "&CHAR(10)&TEXT(Y34,"#,##0.0")&" TBtu",""),"") -> #DIV/0!
C35: =Y11-X11 -> 0 | D35: saved per ref. volume | F35: =Y27-X27 -> 0 | G35: saved per ref. volume | I35: =Y42-X42 -> 0 | J35: saved per ref. volume | L35: =(Y20-X20)*0.000001 -> #DIV/0! | M35: saved per year | O35: ='Rapid Results Dashboard'!Y35-'Rapid Results Dashboard'!X35 -> #DIV/0! | P35: saved per year | R35: =Y49-X49 -> #DIV/0! | S35: saved per year | W35: Total | X35: =SUM(X32:X34) -> #DIV/0! | Y35: =SUM(Y32:Y34) -> #DIV/0!
C36: =C35/Y11 -> #DIV/0! | D36: cost savings per unit of production replaced | F36: =F35/Y27 -> #DIV/0! | G36: manufacturing energy savings per unit of production replaced | I36: =I35/Y42 -> #DIV/0! | J36: manufacturing energy savings per unit of production replaced | L36: =(Y20-X20)/Y20 -> #DIV/0! | M36: cost savings per unit of production replaced | O36: =O35/Y35 -> #DIV/0! | P36: life cycle energy savings in affected markets | R36: =R35/Y49 -> #DIV/0! | S36: life cycle emissions reduction in affected markets
X37: Manufacturing Emissions Comparison for Reference Volume
C38: Cost Impact Summary (Reference Volume) | F38: Energy Impact Summary (Reference Volume) | I38: Emissions (GWP) Impact Summary (Reference Volume) | L38: Cost Impact Summary (U.S. Manufacturers) | O38: Energy Impact Summary (U.S. Market) | R38: Emissions (GWP) Impact Summary (U.S. Market) | X38: New Technology, Industrial Scale | Y38: Commercial Benchmark | Z38: New Technology, Industrial Scale | AA38: Commercial Benchmark
C39: Manufacturing Cost Category | D39: Cost Savings | F39: Life Cycle Phase | G39: Energy Savings | I39: Life Cycle Phase | J39: Emissions (GWP) Reduction | L39: Manufacturing Cost Category | M39: Cost Savings | O39: Life Cycle Phase | P39: Energy Savings | R39: Life Cycle Phase | S39: Emissions (GWP) Reduction | X39: ='Summary Tables (Method 2)'!D54 -> 0 | Y39: ='Summary Tables (Method 2)'!F54 -> 0 | Z39: Label (if >2%) | AA39: Label (if >2%)
C40: Capital Expenses | D40: =Y7-X7 -> 0 | F40: Raw Materials | G40: =Y25-X25 -> 0 | I40: Raw Materials | J40: =Y40-X40 -> 0 | L40: Capital Expenses | M40: =(Y16-X16)*0.000001 -> #DIV/0! | O40: Raw Mater. Embodied Energy | P40: =Y32-X32 -> #DIV/0! | R40: Raw Mater. Embodied Energy | S40: =Y46-X46 -> #DIV/0! | W40: Raw Materials | X40: ='Summary Tables (Method 2)'!E58 -> 0 | Y40: ='Summary Tables (Method 2)'!G58 -> 0 | Z40: =IF(X$42>0,IF((X40/X$42)>0.02,$W40&": "&CHAR(10)&TEXT(X40,"#,##0")&" lbs CO2-e",""),"") | AA40: =IF(Y$42>0,IF((Y40/Y$42)>0.02,$W40&": "&CHAR(10)&TEXT(Y40,"#,##0")&" lbs CO2-e",""),"")
C41: Raw Materials | D41: =Y8-X8 -> 0 | F41: Manufacturing | G41: =Y26-X26 -> 0 | I41: Manufacturing | J41: =Y41-X41 -> 0 | L41: Raw Materials | M41: =(Y17-X17)*0.000001 -> #DIV/0! | O41: Manufacturing | P41: =Y33-X33 -> #DIV/0! | R41: Manufacturing | S41: =Y47-X47 -> #DIV/0! | W41: Manufacturing | X41: ='Summary Tables (Method 2)'!E59 -> 0 | Y41: ='Summary Tables (Method 2)'!G59 -> 0 | Z41: =IF(X$42>0,IF((X41/X$42)>0.02,$W41&": "&CHAR(10)&TEXT(X41,"#,##0")&" lbs CO2-e",""),"") | AA41: =IF(Y$42>0,IF((Y41/Y$42)>0.02,$W41&": "&CHAR(10)&TEXT(Y41,"#,##0")&" lbs CO2-e",""),"")
C42: Energy (Utilities) | D42: =Y9-X9 -> 0 | F42: Total Energy Savings | G42: =SUM(G40:G41) -> 0 | I42: Total Energy Savings | J42: =SUM(J40:J41) -> 0 | L42: Energy (Utilities) | M42: =(Y18-X18)*0.000001 -> #DIV/0! | O42: Use Phase | P42: =Y34-X34 -> 0 | R42: Use Phase | S42: =Y48-X48 -> 0 | W42: Total | X42: =SUM(X40:X41) -> 0 | Y42: =SUM(Y40:Y41) -> 0
C43: Direct Labor | D43: =Y10-X10 -> 0 | L43: Direct Labor | M43: =(Y19-X19)*0.000001 -> #DIV/0! | O43: Total Energy Savings | P43: =SUM(P40:P42) -> #DIV/0! | R43: Total Energy Savings | S43: =SUM(S40:S42) -> #DIV/0!
C44: Total Cost Savings | D44: =SUM(D40:D43) -> 0 | L44: Total Cost Savings | M44: =SUM(M40:M43) -> #DIV/0! | X44: New Technology, Industrial Scale | Y44: Commercial Benchmark | Z44: New Technology, Industrial Scale | AA44: Commercial Benchmark
X45: ='Summary Tables (Method 2)'!K54 -> 0 | Y45: ='Summary Tables (Method 2)'!M54 -> 0 | Z45: Label (if >2%) | AA45: Label (if >2%)
C46: Key | W46: Raw Materials | X46: ='Summary Tables (Method 2)'!L58 -> #DIV/0! | Y46: ='Summary Tables (Method 2)'!N58 -> #DIV/0! | Z46: =IF(X$49>0,IF((X46/X$49)>0.02,$W46&": "&CHAR(10)&TEXT(X46,"#,##0.0")&" million tons CO2-e",""),"") -> #DIV/0! | AA46: =IF(Y$49>0,IF((Y46/Y$49)>0.02,$W46&": "&CHAR(10)&TEXT(Y46,"#,##0.0")&" million tons CO2-e",""),"") -> #DIV/0!
C47: Net Savings | D47: =1 -> 1 | W47: Manufacturing | X47: ='Summary Tables (Method 2)'!L59 -> #DIV/0! | Y47: ='Summary Tables (Method 2)'!N59 -> #DIV/0! | Z47: =IF(X$49>0,IF((X47/X$49)>0.02,$W47&": "&CHAR(10)&TEXT(X47,"#,##0.0")&" million tons CO2-e",""),"") -> #DIV/0! | AA47: =IF(Y$49>0,IF((Y47/Y$49)>0.02,$W47&": "&CHAR(10)&TEXT(Y47,"#,##0.0")&" million tons CO2-e",""),"") -> #DIV/0!
